Workbook
Name _R01: LGU_Masterlist!$E$3:$E$9
Name _R02: LGU_Masterlist!$F$3:$F$9
Name _R03: LGU_Masterlist!$G$3:$G$9
Name _R04_A: LGU_Masterlist!$H$4:$H$9
Name _R04_B: LGU_Masterlist!$I$3:$I$9
Name _R05: LGU_Masterlist!$J$3:$J$9
Name _R06: LGU_Masterlist!$K$3:$K$9
Name _R07: LGU_Masterlist!$M$3:$M$9
Name _R08: LGU_Masterlist!$N$3:$N$9
Name _R09: LGU_Masterlist!$O$3:$O$9
Name _R10: LGU_Masterlist!$P$3:$P$9
Name _R11: LGU_Masterlist!$Q$3:$Q$9
Name _R12: LGU_Masterlist!$R$3:$R$9
Name _R13: LGU_Masterlist!$S$3:$S$9
Name Abra: LGU_Masterlist!$C$12:$C$38
Name Agusan_del_Norte: LGU_Masterlist!$BW$12:$BW$23
Name Agusan_del_Sur: LGU_Masterlist!$BX$12:$BX$25
Name Aklan: LGU_Masterlist!$AO$12:$AO$28
Name Albay: LGU_Masterlist!$AI$12:$AI$29
Name Antique: LGU_Masterlist!$AP$12:$AP$30
Name Apayao: LGU_Masterlist!$D$12:$D$18
Name Aurora: LGU_Masterlist!$X$12:$X$19
Name BARMM: LGU_Masterlist!$B$3:$B$7
Name Basilan: LGU_Masterlist!$BH$12
Name Bataan: LGU_Masterlist!$R$12:$R$23
Name Batanes: LGU_Masterlist!$M$12:$M$17
Name Batangas: LGU_Masterlist!$Y$12:$Y$45
Name Benguet: LGU_Masterlist!$E$12:$E$25
Name Biliran: LGU_Masterlist!$BD$12:$BD$19
Name Bohol: LGU_Masterlist!$AW$12:$AW$59
Name Bukidnon: LGU_Masterlist!$BI$12:$BI$33
Name Bulacan: LGU_Masterlist!$S$12:$S$35
Name Cagayan: LGU_Masterlist!$N$12:$N$40
Name Camarines_Norte: LGU_Masterlist!$AJ$12:$AJ$23
Name Camarines_Sur: LGU_Masterlist!$AK$12:$AK$48
Name Camiguin: LGU_Masterlist!$BJ$12:$BJ$16
Name Capiz: LGU_Masterlist!$AQ$12:$AQ$28
Name CAR: LGU_Masterlist!$E$3:$E$8
Name Catanduanes: LGU_Masterlist!$AL$12:$AL$22
Name Cavite: LGU_Masterlist!$Z$12:$Z$34
Name Cebu: LGU_Masterlist!$AX$12:$AX$64
Name cit_mun: LGU_Table!$C$2:$C$1635
Name cm_class: LGU_Table!$G$2:$G$1635
Name Cordilla_Administrative_Region: LGU_Masterlist!$D$3:$D$8
Name Cotabato: LGU_Masterlist!$BS$12:$BS$29
Name Davao_de_Oro: LGU_Masterlist!$BQ$12:$BQ$22
Name Davao_del_Norte: LGU_Masterlist!$BN$12:$BN$22
Name Davao_del_Sur: LGU_Masterlist!$BO$12:$BO$22
Name Davao_Occidental: LGU_Masterlist!$BR$12:$BR$16
Name Davao_Oriental: LGU_Masterlist!$BP$12:$BP$22
Name Dinagat_Islands: LGU_Masterlist!$CA$12:$CA$18
Name Eastern_Samar: LGU_Masterlist!$AY$12:$AY$34
Name Guimaras: LGU_Masterlist!$AS$12:$AS$16
Name h_sett: LGU_Table!$F$2:$F$1635
Name Ifugao: LGU_Masterlist!$F$12:$F$22
Name Ilocos_Norte: LGU_Masterlist!$I$12:$I$34
Name Ilocos_Sur: LGU_Masterlist!$J$12:$J$45
Name Iloilo: LGU_Masterlist!$AR$12:$AR$55
Name inc_class: LGU_Table!$H$2:$H$1635
Name Isabela: LGU_Masterlist!$O$12:$O$48

Sheet LGU2

Sheet Regions
A1: regions
A2: BARMM
A3: Cordillera Administrative Region
A4: National Capital Region
A5: Region 01 (Ilocos Region)
A6: Region 02 (Cagayan Valley)
A7: Region 03 (Central Luzon)
A8: Region 04-A (CALABARZON)
A9: Region 04-B (MIMAROPA)
A10: Region 05 (Bicol Region)
A11: Region 06 (Western Visayas)
A12: Region 07 (Central Visayas Region)
... A18: Region 13 (Caraga Region)

Sheet Home
A1: MONTHLY ACCOMPLISHMENT COLLECTION AND REPORTING MANUAL
A2: ENVIRONMENTAL, LAND USE AND URBAN PLANNING AND DEVELOPMENT DIVISION (ELUPDD)
A4: OVERVIEW AND RATIONALE
A6: The Monthly Accomplishment Collection and Reporting Manual was primarily developed to serve as a reference guide for the Monitoring and Evaluation Focal Persons of the DHSUD Regional Offices (ROs) - Environmental, Land Use, and Urban Planning and Development Division (ELUPDD) in the data collection and reporting of their accomplishments pursuant to ELUPDD’s functions and DHSUD’s mandates and programs. This tool consolidates the accomplishment indicators and targets to be collected and reported in ELUPDD's accomplishment report as agreed with the Central Office. Moreover, this tool was developed to monitor and report process, activities, and functions of ELUPDD pursuant to DHSUD’s Operations Manual and Quality Management System (QMS).
A8: ACCOMPLISHMENT REPORTING PROCESS
A10: The Accomplishment reports submitted by the ELUPDD are consolidated, processed, and reported by ELUPDB. The processed reports are submitted by ELUPDB internally to the DHSUD Planning Service (PS) and/or DHSUD Executive Offices (Office of Assistant Secretary, Office of Undersecretary, Office of Secretary) and externally, to National Government Agencies, Legislature (Congress and Senate), Executive Offices including the Office of the President, International Funding Agencies, and other stakeholders. The accomplishment reports serve as a measure of success in attaining the tasks and functions mandated to the DHSUD specifically to ELUPDD. Furthermore, the accomplishment report shall be a basis for additional support (mainly financial) from the National Government and/or International Funding Agencies to DHSUD and ELUPDD.
B11: `
A12: UPDATING, AND SCOPE AND LIMITATIONS
A14: Mid-year and end-of-year assessment and updating activities will be held among ELUPDB’s Monitoring and Evaluation Division and ELUPDD’s Monitoring and Evaluation Focal Persons. These activities shall ensure that the tool and the manual is updated and adaptive to the most important programs to solve societal issues. If in need of updating, the new version of the tool and manual shall be released a month after the Mid-year and/or the End-of-Year assessment and updating activity. The data and indicators included in this manual shall only cover ELUPDD and ELUPDB accomplishments of functions as mandated by law or programs required by the direction of the DHSUD Secretary.
B17: Regional ELUPDD Functions as Mandated by Law
A18: GENERAL FUNCTIONS OF REGIONAL OFFICES AS PER IRR OF RA 11201
A19: 24.1 | B19: Implement laws, and the Department's policies, plans, programs, projects, rules and regulations;
A20: 24.2 | B20: Coordinate and maintain linkage with NGAs, LGUs, private entities, NGOs, CSOs, academe, and other stakeholders;
A21: 24.3 | B21: Act on applications for the issuance of various permits, licenses, clearances and certifications;
A22: 24.4 | B22: Conduct conciliation proceedings on issues and disputes relating to the implementation of the Department's mandates, including the regulation of real estate development and HOAs; and
A23: 24.5 | B23: Perform such other functions that are implied, necessary or incidental in carryi out the above or as may be assigned by the Secretary
A25: CORE FUNCTIONS AS PER IRR OF RA 11201
A26: Environmental, Land Use and Urban Planning and Development Functions
A27: 25.1.1 | B27: Provide technical assistance to provinces, cities and municipalities in the preparation and updating of CLUPs, ZOs, and PCLUPs/PPFPs;
A28: 25.1.2 | B28: Conduct technology transfer and capability building programs for LGUs in the implementation of CLUP and ZO enforcement and development control;
A29: 25.1.3 | B29: Conduct training and mentoring in addressing urban development, management and governance concerns such as housing, establishment of government centers, new towns, settlements, and planned unit development, urban renewal, open spaces, traffic concerns, sewerage, waste management, and energy efficiency, among others;
A30: 25.1.4 | B30: Undertake review of PPFPs, CLUPs and ZOs of provinces, cities and municipalities as a member of the Provincial Land Use Committee or Regional Land Use Committee;
A31: 25.1.5 | B31: Extend technical assistance to and conduct technology transfer and capability building of cities and municipalities in the formulation, legitimization and implementation of LSPs, which shall include plans and strategies for the utilization of the socialized housing tax as provided under Section 43 of RA 7279 and other sources of funds for housing and urban development;
A32: 25.1.6 | B32: Monitor land use changes, particularly the reclassification of agricultural lands into other uses and implementation of ZOs of cities and municipalities;
A33: 25.1.7 | B33: Update an inventory of idle lands, existing CLUPs, ZOs, PCLUPs/PPFPs, and LSPs, inventory of housing stock and listing of government-housing program beneficiaries;
A34: 25.1.8 | B34: Maintain a geographic information system for monitoring of land use and zoning particularly on but not limited to:
B35: (a) Compliance of LGUs to guidelines set by the Department in preparing and updating their respective CLUPs and ZOs; and
B36: (b) Implementation of CLUPs and ZOs through monitoring of land use changes and reclassification; and
A37: 25.1.9 | B37: Perform such other functions that are implied, necessary or incide tal in carrying out the above or as may be assigned by the Regional Directors.

Sheet LGU_Masterlist
A1: PROVINCES
B2: BARMM | C2: PLGU | D2: NCR | E2: CAR | F2: RO_1 | G2: RO_2 | H2: RO_3 | I2: RO_4A | J2: RO_4B | K2: RO_5 | L2: RO_6 | M2: NIR | N2: RO_7 | O2: RO_8 | P2: RO_9 | Q2: R_10 | R2: R_11 | S2: R_12 | T2: R_13
B3: Basilan | C3: Province_PLGU | D3: Metro_Manila | E3: Abra | F3: Ilocos_Norte | G3: Batanes | H3: Aurora | I3: Batangas | J3: Marinduque | K3: Albay | L3: Aklan | M3: Negros_Occidental | N3: Bohol | O3: Biliran | P3: Zamboanga_del_Norte | Q3: Bukidnon | R3: Davao_del_Norte | S3: Cotabato | T3: Agusan_del_Norte
B4: Lanao_del_Sur | E4: Apayao | F4: Ilocos_Sur | G4: Cagayan | H4: Bataan | I4: Cavite | J4: Occidental_Mindoro | K4: Camarines_Norte | L4: Antique | M4: Negros_Oriental | N4: Cebu | O4: Eastern_Samar | P4: Zamboanga_del_Sur | Q4: Camiguin | R4: Davao_del_Sur | S4: South_Cotabato | T4: Agusan_del_Sur
B5: Tawi-Tawi | E5: Benguet | F5: La_Union | G5: Isabela | H5: Bulacan | I5: Laguna | J5: Oriental_Mindoro | K5: Camarines_Sur | L5: Capiz | M5: Siquijor | O5: Leyte | P5: Zamboanga_Sibugay | Q5: Lanao_del_Norte | R5: Davao_Oriental | S5: Sultan_Kudarat | T5: Surigao_del_Norte
B6: Maguindanao_del_Norte | E6: Ifugao | F6: Pangasinan | G6: Nueva_Vizcaya | H6: Nueva_Ecija | I6: Quezon | J6: Palawan | K6: Catanduanes | L6: Iloilo | O6: Northern_Samar | P6: Basilan | Q6: Misamis_Occidental | R6: Davao_de_Oro | S6: Sarangani | T6: Surigao_del_Sur
B7: Maguindanao_del_Sur | E7: Kalinga | G7: Quirino | H7: Pampanga | I7: Rizal | J7: Romblon | K7: Masbate | L7: Guimaras | O7: Samar | P7: Sulu | Q7: Misamis_Oriental | R7: Davao_Occidental | T7: Dinagat_Islands
E8: Mountain_Province | H8: Tarlac | K8: Sorsogon | N8: Biliran | O8: Southern_Leyte
H9: Zambales
A10: PROVINCES
A11: Province_PLGU | B11: Metro_Manila | C11: Abra | D11: Apayao | E11: Benguet | F11: Ifugao | G11: Kalinga | H11: Mountain_Province | I11: Ilocos_Norte | J11: Ilocos_Sur | K11: La_Union | L11: Pangasinan | M11: Batanes | N11: Cagayan | O11: Isabela | P11: Nueva_Vizcaya | Q11: Quirino | R11: Bataan | S11: Bulacan | T11: Nueva_Ecija | U11: Pampanga | V11: Tarlac | W11: Zambales | X11: Aurora | Y11: Batangas | Z11: Cavite | AA11: Laguna | AB11: Quezon | AC11: Rizal | AD11: Marinduque | AE11: Occidental_Mindoro | AF11: Oriental_Mindoro | AG11: Palawan | AH11: Romblon | AI11: Albay | AJ11: Camarines_Norte | AK11: Camarines_Sur | AL11: Catanduanes | AM11: Masbate | AN11: Sorsogon | AO11: Aklan | AP11: Antique | AQ11: Capiz | AR11: Iloilo | AS11: Guimaras | AT11: Negros_Occidental | AU11: Negros_Oriental | AV11: Siquijor | AW11: Bohol | AX11: Cebu | AY11: Eastern_Samar | AZ11: Leyte | BA11: Northern_Samar | BB11: Samar | BC11: Southern_Leyte | BD11: Biliran | BE11: Zamboanga_del_Norte | BF11: Zamboanga_del_Sur | BG11: Zamboanga_Sibugay | BH11: Basilan | BI11: Bukidnon | BJ11: Camiguin | BK11: Lanao_del_Norte | BL11: Misamis_Occidental | BM11: Misamis_Oriental | BN11: Davao_del_Norte | BO11: Davao_del_Sur | BP11: Davao_Oriental | BQ11: Davao_de_Oro | BR11: Davao_Occidental | BS11: Cotabato | BT11: South_Cotabato | BU11: Sultan_Kudarat | BV11: Sarangani | BW11: Agusan_del_Norte | BX11: Agusan_del_Sur | BY11: Surigao_del_Norte | BZ11: Surigao_del_Sur | CA11: Dinagat_Islands | CB11: Sulu
A12: Abra | B12: City_of_Caloocan | C12: Bangued | D12: Calanasan | E12: Atok | F12: Aguinaldo | G12: Balbalan | H12: Barlig | I12: Adams | J12: Alilem | K12: Agoo | L12: Agno | M12: Basco | N12: Abulug | O12: Alicia | P12: Alfonso_Castañeda | Q12: Aglipay | R12: Abucay | S12: Angat | T12: Aliaga | U12: Apalit | V12: Anao | W12: Botolan | X12: Baler | Y12: Agoncillo | Z12: Alfonso | AA12: Alaminos | AB12: Agdangan | AC12: Angono | AD12: Boac | AE12: Abra_De_Ilog | AF12: Baco | AG12: Aborlan | AH12: Alcantara | AI12: Bacacay | AJ12: Basud | AK12: Baao | AL12: Bagamanoc | AM12: Aroroy | AN12: Barcelona | AO12: Altavas | AP12: Anini-Y | AQ12: City_of_Roxas | AR12: Ajuy | AS12: Buenavista | AT12: Binalbagan | AU12: Amlan | AV12: Enrique_Villanueva | AW12: Alburquerque | AX12: Alcantara | AY12: Arteche | AZ12: Abuyog | BA12: Allen | BB12: Almagro | BC12: Anahawan | BD12: Almeria | BE12: Baliguian | BF12: Aurora | BG12: Alicia | BH12: City_of_Isabela | BI12: Baungon | BJ12: Catarman | BK12: Bacolod | BL12: Aloran | BM12: Alubijid | BN12: Asuncion | BO12: Bansalan | BP12: Baganga | BQ12: Compostela | BR12: Don_Marcelino | BS12: Alamada | BT12: Banga | BU12: Bagumbayan | BV12: Alabel | BW12: Buenavista | BX12: Bunawan | BY12: Alegria | BZ12: Barobo | CA12: Basilisa | CB12: Hadji Panglima Tahil
A13: Agusan_del_Norte | B13: City_of_Las_Piñas | C13: Boliney | D13: Conner | E13: Bakun | F13: Alfonso_Lista | G13: City_of_Tabuk | H13: Bauko | I13: Bacarra | J13: Banayoyo | K13: Aringay | L13: Aguilar | M13: Itbayat | N13: Alcala | O13: Angadanan | P13: Ambaguio | Q13: Cabarroguis | R13: Bagac | S13: Balagtas | T13: Bongabon | U13: Arayat | V13: Bamban | W13: Cabangan | X13: Casiguran | Y13: Alitagtag | Z13: Amadeo | AA13: Bay | AB13: Alabat | AC13: Baras | AD13: Buenavista | AE13: Calintaan | AF13: Bansud | AG13: Agutaya | AH13: Banton | AI13: Camalig | AJ13: Capalonga | AK13: Balatan | AL13: Baras | AM13: Baleno | AN13: Bulan | AO13: Balete | AP13: Antique | AQ13: Cuartero | AR13: Alimodian | AS13: Jordan | AT13: Calatrava | AU13: Ayungon | AV13: Larena | AW13: Alicia | AX13: Alcoy | AY13: Balangiga | AZ13: Alangalang | BA13: Biri | BB13: Basey | BC13: Bontoc | BD13: Biliran | BE13: City_of_Dapitan | BF13: Bayog | BG13: Buug | BI13: Cabanglasan | BJ13: Guinsiliban | BK13: Baloi | BL13: Baliangao | BM13: Balingasag | BN13: Braulio_E_Dujali | BO13: City_of_Davao | BP13: Banaybanay | BQ13: Laak | BR13: Jose_Abad_Santos | BS13: Aleosan | BT13: City_of_General_Santos | BU13: City_of_Tacurong | BV13: Glan | BW13: Carmen_ADN | BX13: City_of_Bayugan | BY13: Bacuag | BZ13: Bayabas | CA13: Cagdianao | CB13: Indanan
A14: Agusan_del_Sur | B14: City_of_Makati | C14: Bucay | D14: Flora | E14: Bokod | F14: Asipulo | G14: Lubuagan | H14: Besao | I14: Badoc | J14: Bantay | K14: Bacnotan | L14: Alcala | M14: Ivana | N14: Allacapan | O14: Aurora | P14: Aritao | Q14: Diffun | R14: City_of_Balanga | S14: Bocaue | T14: Cabiao | U14: Bacolor | V14: Camiling | W14: Candelaria | X14: Dilasag | Y14: Balayan | Z14: City_of_Bacoor | AA14: Calauan | AB14: Atimonan | AC14: Binangonan | AD14: Gasan | AE14: Looc | AF14: Bongabong | AG14: Araceli | AH14: Cajidiocan | AI14: City_of_Legazpi | AJ14: Daet | AK14: Bato | AL14: Bato_Catanduanes | AM14: Balud | AN14: Bulusan | AO14: Banga | AP14: Barbaza | AQ14: Dao | AR14: Anilao | AS14: Nueva_Valencia | AT14: Candoni | AU14: Bacong | AV14: Lazi | AW14: Anda | AX14: Alegria | AY14: Balangkayan | AZ14: Albuera | BA14: Bobon | BB14: Calbiga | BC14: City_of_Maasin | BD14: Cabucgayan | BE14: City_of_Dipolog | BF14: City_of_Pagadian | BG14: Diplahan | BI14: City_of_Malaybalay | BJ14: Mahinog | BK14: Baroy | BL14: Bonifacio | BM14: Balingoan | BN14: Carmen | BO14: City_of_Digos | BP14: Boston | BQ14: Mabini | BR14: Malita_ | BS14: Antipas | BT14: City_of_Koronadal | BU14: Columbio | BV14: Kiamba | BW14: City_of_Butuan | BX14: Esperanza | BY14: Burgos | BZ14: Cagwait | CA14: Dinagat | CB14: Jolo
A15: Aklan | B15: City_of_Malabon | C15: Bucloc | D15: Kabugao | E15: Buguias | F15: Banaue | G15: Pasil | H15: Bontoc | I15: Bangui | J15: Burgos_Ilocos-Sur | K15: Bagulin | L15: Anda | M15: Mahatao | N15: Amulung | O15: Benito_Soliven | P15: Bagabag | Q15: Maddela | R15: Dinalupihan | S15: Bulacan | T15: Carranglan | U15: Candaba | V15: Capas | W15: Castillejos | X15: Dinalungan | Y15: Balete | Z15: City_of_Carmona | AA15: Cavinti | AB15: Buenavista | AC15: Cainta | AD15: Mogpog | AE15: Lubang | AF15: Bulalacao | AG15: Balabac | AH15: Calatrava | AI15: City_of_Ligao | AJ15: Jose_Panganiban | AK15: Bombon | AL15: Caramoran | AM15: Batuan | AN15: Casiguran | AO15: Batan | AP15: Belison | AQ15: Dumalag | AR15: Badiangan | AS15: San_Lorenzo | AT15: Cauayan | AU15: Basay | AV15: Maria | AW15: Antequera | AX15: Aloguinsan | AY15: Can-Avid | AZ15: Babatngon | BA15: Capul | BB15: City_of_Calbayog | BC15: Hinunangan | BD15: Caibiran | BE15: Godod | BF15: City_of_Zamboanga | BG15: Imelda | BI15: City_of_Valencia | BJ15: Mambajao | BK15: City_of_Iligan | BL15: Calamba | BM15: Binuangan | BN15: City_of_Panabo | BO15: Hagonoy | BP15: Caraga | BQ15: Maco | BR15: Santa_Maria | BS15: Arakan | BT15: Lake_Sebu | BU15: Esperanza | BV15: Maasim | BW15: City_of_Cabadbaran | BX15: La_Paz | BY15: City_of_Surigao | BZ15: Cantilan | CA15: Libjo | CB15: Kalingalan Caluang
A16: Albay | B16: City_of_Mandaluyong | C16: Daguioman | D16: Luna | E16: City_of_Baguio | F16: Hingyon | G16: Pinukpuk | H16: Natonin | I16: Banna | J16: Cabugao | K16: Balaoan | L16: Asingan | M16: Sabtang | N16: Aparri | O16: Burgos | P16: Bambang | Q16: Nagtipunan | R16: Hermosa | S16: Bustos | T16: City_of_Cabanatuan | U16: City_of_Angeles | V16: City_of_Tarlac | W16: City_of_Olongapo | X16: Dingalan | Y16: Batangas_City | Z16: City_of_Cavite | AA16: City_of_Biñan | AB16: Burdeos | AC16: Cardona | AD16: Santa_Cruz | AE16: Magsaysay | AF16: City_of_Calapan | AG16: Bataraza | AH16: Concepcion | AI16: City_of_Tabaco | AJ16: Labo | AK16: Buhi | AL16: Gigmoto | AM16: Cataingan | AN16: Castilla | AO16: Buruanga | AP16: Bugasong | AQ16: Dumarao | AR16: Balasan | AS16: Sibunag | AT16: City of | AU16: Bindoy | AV16: San_Juan | AW16: Baclayon | AX16: Argao | AY16: City_of_Borongan | AZ16: Barugo | BA16: Catarman | BB16: City_of_Catbalogan | BC16: Hinundayan | BD16: Culaba | BE16: Gutalac | BF16: Dimataling | BG16: Ipil | BI16: Damulog | BJ16: Sagay | BK16: Kapatagan | BL16: City_of_Oroquieta | BM16: City_of_Cagayan_De_Oro | BN16: City_of_Tagum | BO16: Kiblawan | BP16: Cateel | BQ16: Maragusan | BR16: Sarangani | BS16: Banisilan | BT16: Norala | BU16: Isulan | BV16: Maitum | BW16: Jabonga | BX16: Loreto_ADS | BY16: Claver | BZ16: Carmen | CA16: Loreto | CB16: Lugus
A17: Antique | B17: City_of_Manila | C17: Danglas | D17: Pudtol | E17: Itogon | F17: Hungduan | G17: Rizal | H17: Paracelis | I17: Burgos | J17: Caoayan | K17: Bangar | L17: Balungao | M17: Uyugan | N17: Baggao | O17: Cabagan | P17: Bayombong | Q17: Saguday | R17: Limay | S17: Calumpit | T17: City_of_Gapan | U17: City_of_San_Fernando | V17: Concepcion | W17: Iba | X17: Dipaculao | Y17: Bauan | Z17: City_of_Dasmariñas | AA17: City_of_Cabuyao | AB17: Calauag | AC17: City_of_Antipolo | AD17: Torrijos | AE17: Mamburao | AF17: Gloria | AG17: Brooke's_Point | AH17: Corcuera | AI17: Daraga | AJ17: Mercedes | AK17: Bula | AL17: Pandan | AM17: Cawayan | AN17: City_of_Sorsogon | AO17: Ibajay | AP17: Caluya | AQ17: Ivisan | AR17: Banate | AT17: City_of_Bacolod | AU17: City_of_Bais | AV17: Siquijor | AW17: Balilihan | AX17: Asturias | AY17: Dolores | AZ17: Bato | BA17: Catubig | BB17: Daram | BC17: Libagon | BD17: Kawayan | BE17: Jose_Dalman | BF17: Dinas | BG17: Kabasalan | BI17: Dangcagan | BK17: Kauswagan | BL17: City_of_Ozamiz | BM17: City_of_El_Salvador | BN17: Island_Garden_City_of_Samal | BO17: Magsaysay | BP17: City_of_Mati | BQ17: Mawab | BS17: Carmen | BT17: Polomolok | BU17: Kalamansig | BV17: Malapatan | BW17: Kitcharao | BX17: Prosperidad | BY17: Dapa | BZ17: Carrascal | CA17: San_Jose | CB17: Luuk
A18: Apayao | B18: City_of_Marikina | C18: Dolores | D18: Santa_Marcela | E18: Kabayan | F18: Kiangan | G18: Tanudan | H18: Sabangan | I18: Carasi | J18: Cervantes | K18: Bauang | L18: Bani | N18: Ballesteros | O18: Cabatuan | P18: Diadi | R18: Mariveles | S18: City_of_Baliwag | T18: City_of_Palayan | U18: Floridablanca | V18: Gerona | W18: Masinloc | X18: Maria_Aurora | Y18: Calatagan | Z18: City_of_General_Trias | AA18: City_of_Calamba | AB18: Candelaria | AC18: Jala-Jala | AE18: Paluan | AF18: Mansalay | AG18: Busuanga | AH18: Ferrol | AI18: Guinobatan | AJ18: Paracale | AK18: Cabusao | AL18: Panganiban | AM18: City_of_Masbate | AN18: Donsol | AO18: Kalibo | AP18: Culasi | AQ18: Jamindan | AR18: Barotac_Nuevo | AT18: City_of_Bago | AU18: City_of_Bayawan | AW18: Batuan | AX18: Badian | AY18: General_Macarthur | AZ18: Burauen | BA18: Gamay | BB18: Gandara | BC18: Liloan | BD18: Maripipi | BE18: Kalawit | BF18: Dumalinao | BG18: Mabuhay | BI18: Don_Carlos | BK18: Kolambugan | BL18: City_of_Tangub | BM18: City_of_Gingoog | BN18: Kapalong | BO18: Malalag | BP18: Governor_Generoso | BQ18: Monkayo | BS18: City_of_Kidapawan | BT18: Santo_Niño | BU18: Lambayong | BV18: Malungon | BW18: Las_Nieves | BX18: Rosario | BY18: Del_Carmen | BZ18: City_of_Bislig | CA18: Tubajon | CB18: Maimbung
A19: Aurora | B19: City_of_Muntinlupa | C19: La_Paz | E19: Kapangan | F19: Lagawe | G19: Tinglayan | H19: Sadanga | I19: City_of_Batac | J19: City_of_Candon | K19: Burgos_La-Union | L19: Basista | N19: Buguey | O19: City_of_Cauayan | P19: Dupax_del_Norte | R19: Morong | S19: City_of_Malolos | T19: Cuyapo | U19: Guagua | V19: La_Paz | W19: Palauig | X19: San_Luis | Y19: City_of_Calaca | Z19: City_of_Imus | AA19: City_of_San_Pablo | AB19: Catanauan | AC19: Morong | AE19: Rizal | AF19: Naujan | AG19: Cagayancillo | AH19: Looc_Romblon | AI19: Jovellar | AJ19: San_Lorenzo_Ruiz | AK19: Calabanga | AL19: San_Andres | AM19: Claveria | AN19: Gubat | AO19: Lezo | AP19: Hamtic | AQ19: Ma-Ayon | AR19: Barotac_Viejo | AT19: City_of_Cadiz | AU19: City_of_Canlaon | AW19: Bien_Unido | AX19: Balamban | AY19: Giporlos | AZ19: Calubian | BA19: Laoang | BB19: Hinabangan | BC19: Limasawa | BD19: Naval | BE19: Katipunan | BF19: Dumingag | BG19: Malangas | BI19: Impasug-ong | BK19: Lala | BL19: Clarin | BM19: Claveria | BN19: New_Corella | BO19: Matanao | BP19: Lupon | BQ19: Montevista | BS19: Kabacan | BT19: Surallah | BU19: Lebak | BW19: Magallanes | BX19: San_Francisco | BY19: General_Luna | BZ19: City_of_Tandag | CB19: Old Panamao
A20: Basilan | B20: City_of_Navotas | C20: Lacub | E20: Kibungan | F20: Lamut | H20: Sagada | I20: City_of_Laoag | J20: City_of_Vigan | K20: Caba | L20: Bautista | N20: Calayan | O20: City_of_Ilagan | P20: Dupax_del_Sur | R20: Orani | S20: City_of_Meycauayan | T20: Gabaldon | U20: Lubao | V20: Mayantoc | W20: San_Antonio | Y20: City_of_Lipa | Z20: City_of_Tagaytay | AA20: City_of_San_Pedro | AB20: City_of_Lucena | AC20: Pililla | AE20: Sablayan | AF20: Pinamalayan | AG20: City_of_Puerto_Princesa | AH20: Magdiwang | AI20: Libon | AJ20: San_Vicente | AK20: Camaligan | AL20: San_Miguel | AM20: Dimasalang | AN20: Irosin | AO20: Libacao | AP20: Laua-An | AQ20: Mambusao | AR20: Batad | AT20: City_of_Escalante | AU20: City_of_Dumaguete | AW20: Bilar | AX20: Bantayan | AY20: Guiuan | AZ20: Capoocan | BA20: Lapinig | BB20: Jiabong | BC20: Macrohon | BE20: La_Libertad | BF20: Guipos | BG20: Naga | BI20: Kadingilan | BK20: Linamon | BL20: Concepcion | BM20: Gitagum | BN20: San_Isidro_DDN | BO20: Padada | BP20: Manay | BQ20: Nabunturan | BS20: Libungan | BT20: Tampakan | BU20: Lutayan | BW20: Nasipit | BX20: San_Luis | BY20: Gigaquit | BZ20: Cortes | CB20: Omar
A21: Bataan | B21: City_of_Parañaque | C21: Lagangilang | E21: La_Trinidad | F21: Mayoyao | H21: Tadian | I21: Currimao | J21: Galimuyod | K21: City_of_San_Fernando | L21: Bayambang | N21: Camalaniugan | O21: City_of_Santiago | P21: Kasibu | R21: Orion | S21: City_of_San_Jose_Del_Monte | T21: General_Mamerto_Natividad | U21: Mabalacat_City | V21: Moncada | W21: San_Felipe | Y21: City_of_Sto_Tomas | Z21: City_of_Trece_Martires | AA21: City_of_Santa_Rosa | AB21: City_of_Tayabas | AC21: Rodriguez | AE21: San_Jose | AF21: Pola | AG21: Coron | AH21: Odiongan | AI21: Malilipot | AJ21: Santa_Elena | AK21: Canaman | AL21: Viga | AM21: Esperanza | AN21: Juban | AO21: Madalag | AP21: Libertad | AQ21: Panay | AR21: Bingawan | AT21: City_of_Himamaylan | AU21: City_of_Guihulngan | AW21: Buenavista | AX21: Barili | AY21: Hernani | AZ21: Carigara | BA21: Las_Navas | BB21: Marabut | BC21: Malitbog | BE21: Labason | BF21: Josefina | BG21: Olutanga | BI21: Kalilangan | BK21: Magsaysay | BL21: Don_Victoriano_Chiongbian | BM21: Initao | BN21: Santo_Tomas | BO21: Santa_Cruz | BP21: San_Isidro | BQ21: New_Bataan | BS21: Magpet | BT21: Tantangan | BU21: Palimbang | BW21: Remedios_T_Romualdez | BX21: Santa_Josefa | BY21: Mainit | BZ21: Hinatuan | CB21: Pandami
A22: Batanes | B22: Pasay_City | C22: Lagayan | E22: Mankayan | F22: Tinoc | I22: Dingras | J22: Gregorio_del_Pilar | K22: Luna | L22: Binalonan | N22: Claveria | O22: Cordon | P22: Kayapa | R22: Pilar | S22: Doña_Remedios_Trinidad | T22: General_Tinio | U22: Macabebe | V22: Paniqui | W22: San_Marcelino | Y22: City_of_Tanauan | Z22: Gen._Mariano_Alvarez | AA22: Famy | AB22: Dolores | AC22: San_Mateo | AE22: Santa_Cruz | AF22: Puerto_Galera | AG22: Culion | AH22: Romblon | AI22: Malinao | AJ22: Talisay | AK22: Caramoan | AL22: Virac | AM22: Mandaon | AN22: Magallanes | AO22: Makato | AP22: Pandan | AQ22: Panitan | AR22: Cabatuan | AT22: City_of_Kabankalan | AU22: City_of_Tanjay | AW22: Calape | AX22: Boljoon | AY22: Jipapad | AZ22: City_of_Baybay | BA22: Lavezares | BB22: Matuguinao | BC22: Padre_Burgos | BE22: Leon_T_Postigo | BF22: Kumalarang | BG22: Payao | BI22: Kibawe | BK22: Maigo | BL22: Jimenez | BM22: Jasaan | BN22: Talaingod | BO22: Sulop | BP22: Tarragona | BQ22: Pantukan | BS22: Makilala | BT22: T'Boli | BU22: President_Quirino | BW22: Santiago | BX22: Sibagat | BY22: Malimono | BZ22: Lanuza | CB22: Panglima Estino (New Panamao)
A23: Batangas | B23: City_of_Pasig | C23: Langiden | E23: Sablan | I23: Dumalneg | J23: Lidlidda | K23: Naguilian | L23: Binmaley | N23: Enrile | O23: Delfin_Albano | P23: Quezon | R23: Samal | S23: Guiguinto | T23: Guimba | U23: Magalang | V23: Pura | W23: San_Narciso | Y23: Cuenca | Z23: General_Emilio_Aguinaldo | AA23: Kalayaan | AB23: General_Luna | AC23: Tanay | AF23: Roxas | AG23: Cuyo | AH23: San_Agustin | AI23: Manito | AJ23: Vinzons | AK23: City_of_Iriga | AM23: Milagros | AN23: Matnog | AO23: Malay | AP23: Patnongon | AQ23: Pilar | AR23: Calinog | AT23: City_of_La_Carlota | AU23: Dauin | AW23: Candijay | AX23: Borbon | AY23: Lawaan | AZ23: City_of_Tacloban | BA23: Lope_De_Vega | BB23: Motiong | BC23: Pintuyan | BE23: Liloy | BF23: Labangan | BG23: Roseller_Lim | BI23: Kitaotao | BK23: Matungao | BL23: Lopez_Jaena | BM23: Kinoguitan | BS23: Matalam | BT23: Tupi | BU23: Sen_Ninoy_Aquino | BW23: Tubay | BX23: Talacogon | BY23: Pilar | BZ23: Lianga | CB23: Pangutaran
A24: Benguet | B24: Quezon_City | C24: Licuan-Baay | E24: Tuba | I24: Marcos | J24: Magsingal | K24: Pugo | L24: Bolinao | N24: Gattaran | O24: Dinapigue | P24: Santa_Fe | S24: Hagonoy | T24: Jaen | U24: Masantol | V24: Ramos | W24: Santa_Cruz | Y24: Ibaan | Z24: Indang | AA24: Liliw | AB24: General_Nakar | AC24: Taytay | AF24: San _Teodoro | AG24: Dumaran | AH24: San_Andres | AI24: Oas | AK24: City_of_Naga | AM24: Mobo | AN24: Pilar | AO24: Malinao | AP24: San_Jose | AQ24: Pontevedra | AR24: Carles | AT24: City_of_San_Carlos | AU24: Jimalalud | AW24: Carmen | AX24: Carmen_Cebu | AY24: Llorente | AZ24: Dagami | BA24: Mapanas | BB24: Pagsanghan | BC24: Saint_Bernard | BE24: Manukan | BF24: Lakewood | BG24: Siay | BI24: Lantapan | BK24: Munai | BL24: Panaon | BM24: Lagonglong | BS24: Midsayap | BX24: Trento | BY24: Placer | BZ24: Lingig | CB24: Parang
A25: Biliran | B25: City_of_San_Juan | C25: Luba | E25: Tublay | I25: Nueva_Era | J25: Nagbukel | K25: Rosario | L25: Bugallon | N25: Gonzaga | O25: Divilacan | P25: Solano | S25: Marilao | T25: Laur | U25: Mexico | V25: San_Clemente | W25: Subic | Y25: Laurel | Z25: Kawit | AA25: Los_Baños | AB25: Guinayangan | AC25: Teresa | AF25: Socorro | AG25: El_Nido | AH25: San_Fernando | AI25: Pio_Duran | AK25: Del_Gallego | AM25: Monreal | AN25: Prieto_Diaz | AO25: Nabas | AP25: San_Remigio | AQ25: President_Roxas | AR25: City_of_Iloilo | AT25: City_of_Silay | AU25: La_Libertad | AW25: Catigbian | AX25: Catmon | AY25: Maslog | AZ25: Dulag | BA25: Mondragon | BB25: Paranas | BC25: San_Francisco | BE25: Mutia | BF25: Lapuyan | BG25: Talusan | BI25: Libona | BK25: Nunungan | BL25: Plaridel | BM25: Laguindingan | BS25: M'Lang | BX25: Veruela | BY25: San_Benito | BZ25: Madrid | CB25: Pata
A26: Bohol | B26: City_of_Taguig | C26: Malibcong | I26: Pagudpud | J26: Narvacan | K26: San_Gabriel | L26: Burgos_Pangasinan | N26: Iguig | O26: Echague | P26: Villaverde | S26: Norzagaray | T26: Licab | U26: Minalin | V26: San_Jose | Y26: Lemery | Z26: Magallanes | AA26: Luisiana | AB26: Gumaca | AF26: Victoria | AG26: Kalayaan | AH26: San_Jose | AI26: Polangui | AK26: Gainza | AM26: Palanas | AN26: Santa_Magdalena | AO26: New_Washington | AP26: Sebaste | AQ26: Sapi-An | AR26: City_of_Passi | AT26: City_of_Sipalay | AU26: Mabinay | AW26: City_of_Tagbilaran | AX26: City_of_Bogo | AY26: Maydolong | AZ26: Hilongos | BA26: Palapag | BB26: Pinabacdao | BC26: San_Juan | BE26: Piñan | BF26: Mahayag | BG26: Titay | BI26: Malitbog | BK26: Pantao_Ragat | BL26: Sapang_Dalaga | BM26: Libertad | BS26: Pigkawayan | BY26: San_Francisco | BZ26: Marihatag | CB26: Patikul
A27: Bukidnon | B27: City_of_Valenzuela | C27: Manabo | I27: Paoay | J27: Quirino | K27: San_Juan | L27: Calasiao | N27: Lal-Lo | O27: Gamu | S27: Obando | T27: Llanera | U27: Porac | V27: San_Manuel | Y27: Lian | Z27: Maragondon | AA27: Lumban | AB27: Infanta | AG27: Linapacan | AH27: Santa_Fe | AI27: Rapu-Rapu | AK27: Garchitorena | AM27: Pio_V_Corpus | AO27: Numancia | AP27: Sibalom | AQ27: Sigma | AR27: Concepcion | AT27: City_of_Talisay | AU27: Manjuyod | AW27: Clarin | AX27: City_of_Carcar | AY27: Mercedes | AZ27: Hindang | BA27: Pambujan | BB27: San_Jorge | BC27: San_Ricardo | BE27: Polanco | BF27: Margosatubig | BG27: Tungawan | BI27: Manolo_Fortich | BK27: Pantar | BL27: Sinacaban | BM27: Lugait | BS27: Pikit | BY27: San_Isidro | BZ27: San_Agustin | CB27: Siasi
A28: Bulacan | B28: Pateros | C28: Peñarrubia | I28: Pasuquin | J28: Salcedo | K28: Santo_Tomas | L28: City_of_Alaminos | N28: Lasam | O28: Jones | S28: Pandi | T28: Lupao | U28: San_Luis | V28: Santa_Ignacia | Y28: Lobo | Z28: Mendez | AA28: Mabitac | AB28: Jomalig | AG28: Magsaysay | AH28: Santa_Maria | AI28: Santo_Domingo | AK28: Goa | AM28: Placer | AO28: Tangalan | AP28: Tibiao | AQ28: Tapaz | AR28: Dingle | AT28: City_of_Victorias | AU28: Pamplona | AW28: Corella | AX28: City_of_Cebu | AY28: Oras | AZ28: Inopacan | BA28: Rosario | BB28: San_Jose_De_Buan | BC28: Silago | BE28: Pres_Manuel_A_Roxas | BF28: Midsalip | BI28: Maramag | BK28: Poona_Piagapo | BL28: Tudela | BM28: Magsaysay | BS28: President_Roxas | BY28: Santa_Monica | BZ28: San_Miguel | CB28: Talipao
A29: Cagayan | C29: Pidigan | I29: Piddig | J29: San_Emilio | K29: Santol | L29: City_of_Dagupan | N29: Pamplona | O29: Luna | S29: Paombong | T29: Nampicuan | U29: San_Simon | V29: Victoria | Y29: Mabini | Z29: Naic | AA29: Magdalena | AB29: Lopez | AG29: Narra | AI29: Tiwi | AK29: Lagonoy | AM29: San_Fernando_Masbate | AP29: Tobias_Fornier | AR29: Dueñas | AT29: Enrique_B_Magalona | AU29: San_Jose | AW29: Cortes | AX29: City_of_Lapu-Lapu | AY29: Quinapondan | AZ29: Isabel | BA29: San_Antonio | BB29: San_Sebastian | BC29: Sogod | BE29: Rizal | BF29: Molave | BI29: Pangantucan | BK29: Salvador | BM29: Manticao | BS29: Tulunan | BY29: Sison | BZ29: Tagbina | CB29: Tapul
A30: Camarines_Norte | C30: Pilar | I30: Pinili | J30: San_Esteban | K30: Sudipen | L30: City_of_San_Carlos | N30: Peñablanca | O30: Maconacon | S30: Plaridel | T30: Pantabangan | U30: Santa_Ana | Y30: Malvar | Z30: Noveleta | AA30: Majayjay | AB30: Lucban | AG30: Quezon | AK30: Libmanan | AM30: San_Jacinto | AP30: Valderrama | AR30: Dumangas | AT30: Hinigaran | AU30: Santa_Catalina | AW30: Dagohoy | AX30: City_of_Mandaue | AY30: Salcedo | AZ30: Jaro | BA30: San_Isidro | BB30: Santa_Margarita | BC30: Tomas_Oppus | BE30: Salug | BF30: Pitogo | BI30: Quezon | BK30: Sapad | BM30: Medina | BY30: Socorro | BZ30: Tago | CB30: Tungkil (Banguingui)
A31: Camarines_Sur | C31: Sallapadan | I31: San_Nicolas | J31: San_Ildefonso | K31: Tubao | L31: City_of_Urdaneta | N31: Piat | O31: Mallig | S31: Pulilan | T31: Peñaranda | U31: Santa_Rita | Y31: Mataas_na_Kahoy | Z31: Rosario | AA31: Nagcarlan | AB31: Macalelon | AG31: Rizal | AK31: Lupi | AM31: San_Pascual | AR31: Estancia | AT31: Hinoba-an | AU31: Siaton | AW31: Danao | AX31: City_of_Naga | AY31: San_Julian | AZ31: Javier | BA31: San_Jose | BB31: Santa_Rita | BE31: Sergio_Osmeña_Sr. | BF31: Ramon_Magsaysay | BI31: San_Fernando | BK31: Sultan_Naga_Dimaporo | BM31: Naawan | BY31: Tagana-An
A32: Camiguin | C32: San_Isidro | I32: Sarrat | J32: San_Juan | L32: Dasol | N32: Rizal | O32: Naguilian | S32: San_Ildefonso | T32: Quezon | U32: Sasmuan | Y32: Nasugbu | Z32: Silang | AA32: Paete | AB32: Mauban | AG32: Roxas | AK32: Magarao | AM32: Uson | AR32: Guimbal | AT32: Ilog | AU32: Sibulan | AW32: Dauis | AX32: City_of_Talisay | AY32: San_Policarpo | AZ32: Julita | BA32: San_Roque | BB32: Santo_Niño | BE32: Siayan | BF32: San_Miguel | BI32: Sumilao | BK32: Tagoloan_LDN | BM32: Opol | BY32: Tubod
A33: Capiz | C33: San_Juan | I33: Solsona | J33: San_Vicente | L33: Infanta | N33: Sanchez-Mira | O33: Palanan | S33: San_Miguel | T33: Rizal | U33: Sto._Tomas | Y33: Padre_Garcia | Z33: Tanza | AA33: Pagsanjan | AB33: Mulanay | AG33: San_Vicente | AK33: Milaor | AR33: Igbaras | AT33: Isabela | AU33: Tayasan | AW33: Dimiao | AX33: City_of_Toledo | AY33: Sulat | AZ33: Kananga | BA33: San_Vicente | BB33: Tagapul-An | BE33: Sibuco | BF33: San_Pablo | BI33: Talakag | BK33: Tangcal | BM33: Salay
A34: Catanduanes | C34: San_Quintin | I34: Vintar | J34: Santa | L34: Labrador | N34: Santa_Ana | O34: Quezon | S34: San_Rafael | T34: San_Antonio | Y34: Rosario | Z34: Ternate | AA34: Pakil | AB34: Padre_Burgos | AG34: Sofronio_Española | AK34: Minalabac | AR34: Janiuay | AT34: La_Castellana | AU34: Valencia | AW34: Duero | AX34: Compostela | AY34: Taft | AZ34: La_Paz | BA34: Silvino_Lobos | BB34: Talalora | BE34: Sibutad | BF34: Sominot | BK34: Tubod | BM34: Sugbongcogon
A35: Cavite | C35: Tayum | J35: Santa_Catalina | L35: Laoac | N35: Santa_Praxedes | O35: Quirino | S35: Santa_Maria | T35: San_Isidro | Y35: San_Jose | AA35: Pangil | AB35: Pagbilao | AG35: Taytay | AK35: Nabua | AR35: Lambunao | AT35: Manapla | AU35: Vallehermoso | AW35: Garcia_Hernandez | AX35: Consolacion | AZ35: Leyte | BA35: Victoria | BB35: Tarangnan | BE35: Sindangan | BF35: Tabina | BM35: Tagoloan
A36: Cebu | C36: Tineg | J36: Santa_Cruz | L36: Lingayen | N36: Santa_Teresita | O36: Ramon | T36: San_Jose_City | Y36: San_Juan | AA36: Pila | AB36: Panukulan | AK36: Ocampo | AR36: Leganes | AT36: Moises_Padilla | AU36: Zamboanguita | AW36: Getafe | AX36: Cordova | AZ36: Macarthur | BB36: Villareal | BE36: Siocon | BF36: Tambulig | BM36: Talisayan
A37: Cotabato | C37: Tubo | J37: Santa_Lucia | L37: Mabini | N37: Santo_Niño | O37: Reina_Mercedes | T37: San_Leonardo | Y37: San_Luis | AA37: Rizal | AB37: Patnanungan | AK37: Pamplona | AR37: Lemery | AT37: Murcia | AW37: Guindulman | AX37: Daanbantayan | AZ37: Mahaplag | BB37: Zumarraga | BE37: Sirawai | BF37: Tigbao | BM37: Villanueva
A38: Davao_de_Oro | C38: Villaviciosa | J38: Santa_Maria | L38: Malasiqui | N38: Solana | O38: Roxas | T38: Santa_Rosa | Y38: San_Nicolas | AA38: Santa_Cruz | AB38: Perez | AK38: Pasacao | AR38: Leon | AT38: Pontevedra | AW38: Inabanga | AX38: Dalaguete | AZ38: Matag-Ob | BE38: Tampilisan | BF38: Tukuran
A39: Davao_del_Norte | J39: Santiago | L39: Manaoag | N39: Tuao | O39: San_Agustin | T39: Santo_Domingo | Y39: San_Pascual | AA39: Santa_Maria | AB39: Pitogo | AK39: Pili | AR39: Maasin | AT39: Pulupandan | AW39: Jagna | AX39: Danao_City | AZ39: Matalom | BF39: Vincenzo_A_Sagun
A40: Davao_del_Sur | J40: Santo_Domingo | L40: Mangaldan | N40: Tuguegarao_City | O40: San_Guillermo | T40: Science_City_of_Muñoz | Y40: Santa_Teresita | AA40: Siniloan | AB40: Plaridel | AK40: Presentacion | AR40: Miagao | AT40: Salvador_Benedicto | AW40: Lila | AX40: Dumanjug | AZ40: Mayorga
A41: Davao_Occidental | J41: Sigay | L41: Mangatarem | O41: San_Isidro | T41: Talavera | Y41: Taal | AA41: Victoria | AB41: Polillo | AK41: Ragay | AR41: Mina | AT41: San_Enrique_NegOcc | AW41: Loay | AX41: Ginatilan | AZ41: Merida
A42: Davao_Oriental | J42: Sinait | L42: Mapandan | O42: San_Manuel | T42: Talugtug | Y42: Talisay | AB42: Quezon | AK42: Sagñay | AR42: New_Lucena | AT42: Toboso | AW42: Loboc | AX42: Liloan | AZ42: Ormoc_City
A43: Dinagat_Islands | J43: Sugpon | L43: Natividad | O43: San_Mariano | T43: Zaragoza | Y43: Taysan | AB43: Real | AK43: San_Fernando | AR43: Oton | AT43: Valladolid | AW43: Loon | AX43: Madridejos | AZ43: Palo
A44: Eastern_Samar | J44: Suyo | L44: Pozorrubio | O44: San_Mateo | Y44: Tingloy | AB44: Sampaloc | AK44: San_Jose | AR44: Pavia | AW44: Mabini | AX44: Malabuyoc | AZ44: Palompon
A45: Guimaras | J45: Tagudin | L45: Rosales | O45: San_Pablo | Y45: Tuy | AB45: San_Andres | AK45: Sipocot | AR45: Pototan | AW45: Maribojoc | AX45: Medellin | AZ45: Pastrana
A46: Ifugao | L46: San_Fabian | O46: Santa_Maria | AB46: San_Antonio | AK46: Siruma | AR46: San_Dionisio | AW46: Panglao | AX46: Minglanilla | AZ46: San_Isidro_Leyte
A47: Ilocos_Norte | L47: San_Jacinto | O47: Santo_Tomas | AB47: San_Francisco | AK47: Tigaon | AR47: San_Enrique | AW47: Pilar_Cebu | AX47: Moalboal | AZ47: San_Miguel
A48: Ilocos_Sur | L48: San_Manuel | O48: Tumauini | AB48: San_Narciso | AK48: Tinambac | AR48: San_Joaquin | AW48: President_Carlos_P_Garcia | AX48: Oslob | AZ48: Santa_Fe
A49: Iloilo | L49: San_Nicolas | AB49: Sariaya | AR49: San_Miguel | AW49: Sagbayan | AX49: Pilar | AZ49: Tabango
A50: Isabela | L50: San_Quintin | AB50: Tagkawayan | AR50: San_Rafael | AW50: San_Isidro | AX50: Pinamungajan | AZ50: Tabontabon
A51: Kalinga | L51: Santa_Barbara | AB51: Tiaong | AR51: Santa_Barbara | AW51: San_Miguel | AX51: Poro | AZ51: Tanauan
A52: La_Union | L52: Santa_Maria | AB52: Unisan | AR52: Sara | AW52: Sevilla | AX52: Ronda | AZ52: Tolosa
A53: Laguna | L53: Santo_Tomas | AR53: Tigbauan | AW53: Sierra_Bullones | AX53: Samboan | AZ53: Tunga
A54: Lanao_del_Norte | L54: Sison | AR54: Tubungan | AW54: Sikatuna | AX54: San_Fernando | AZ54: Villaba
A55: Leyte | L55: Sual | AR55: Zarraga | AW55: Talibon | AX55: San_Francisco
A56: Marinduque | L56: Tayug | AW56: Trinidad | AX56: San_Remigio
A57: Masbate | L57: Umingan | AW57: Tubigon | AX57: Santa_Fe
A58: Metro_Manila | L58: Urbiztondo | AW58: Ubay | AX58: Santander
A59: Misamis_Occidental | L59: Villasis | AW59: Valencia_Bohol | AX59: Sibonga
A60: Misamis_Oriental | AX60: Sogod
A61: Mountain_Province | AX61: Tabogon
A62: Negros_Occidental | AX62: Tabuelan
A63: Negros_Oriental | AX63: Tuburan
A64: Northern_Samar | AX64: Tudela
A65: Nueva_Ecija
A66: Nueva_Vizcaya
A67: Occidental_Mindoro
A68: Oriental_Mindoro
A69: Palawan
A70: Pampanga
A71: Pangasinan
A72: Quezon
A73: Quirino
A74: Rizal
A75: Romblon
A76: Samar
... A89: Zamboanga_Sibugay

Sheet Accomplishment 2026
A3: Republic of the Philippines
A4: DEPARTMENT OF HUMAN SETTLEMENTS AND URBAN DEVELOPMENT
A6: DHSUD REGIONAL OFFICE NEGROS ISALAND REGION
A7: ENVIRONMENTAL, LAND USE AND URBAN PLANNING AND DEVELOPMENT DIVISION
A8: 2026 ACCOMPLISHMENT REPORT (As of FEBRUARY)
A10: INDICATORS | E10: TOTAL TARGETS (YEAR) | F10: MONTHLY ACCOMPLISHMENT | R10: 1Q | S10: 2Q | T10: 3Q | U10: 4Q | V10: TOTAL ACCOMP. (YEAR) | W10: REMARKS | X10: LINK TO ANNEX
F11: January | G11: February | H11: March | I11: April | J11: May | K11: June | L11: July | M11: August | N11: September | O11: October | P11: November | Q11: December
A12: OUTCOME INDICATORS
B13: 1 | C13: Formulation of sustainable and resilient human settlements plans
D14: 1.1. Number of LGUs with approved CLUPs within the year | E14: 5 | F14: =COUNTIF('Annex 1.1. Outcome_CLUP'!H14:H1048576,"January") -> 0 | G14: =COUNTIF('Annex 1.1. Outcome_CLUP'!H14:H1048576,"February") -> 0 | H14: =COUNTIF('Annex 1.1. Outcome_CLUP'!H14:H1048576,"March") -> 0 | I14: =COUNTIF('Annex 1.1. Outcome_CLUP'!H14:H1048576,"April") -> 0 | J14: =COUNTIF('Annex 1.1. Outcome_CLUP'!H14:H1048576,"May") -> 0 | K14: =COUNTIF('Annex 1.1. Outcome_CLUP'!H14:H1048576,"June") -> 0 | L14: =COUNTIF('Annex 1.1. Outcome_CLUP'!H14:H1048576,"July") -> 0 | M14: =COUNTIF('Annex 1.1. Outcome_CLUP'!H14:H1048576,"August") -> 0 | N14: =COUNTIF('Annex 1.1. Outcome_CLUP'!H14:H1048576,"September") -> 0 | O14: =COUNTIF('Annex 1.1. Outcome_CLUP'!H14:H1048576,"October") -> 0 | P14: =COUNTIF('Annex 1.1. Outcome_CLUP'!H14:H1048576,"November") -> 0 | Q14: =COUNTIF('Annex 1.1. Outcome_CLUP'!H14:H1048576,"December") -> 0 | R14: =SUM(F14:H14) -> 0 | S14: =SUM(I14:K14) -> 0 | T14: =SUM(L14:N14) -> 0 | U14: =SUM(O14:Q14) -> 0 | V14: =SUM(F14:Q14) -> 0 | X14: Annex 1.1. Outcome_CLUP
D15: 1.1.1 Number of LGUs with CLUPs within the year with integrated or separately prepared CLUP Communications Plan | E15: 5 | F15: =COUNTIF('Annex 1.1.1 Outcome_CommPlan'!$H$14:$H$1048576,"January") -> 0 | G15: =COUNTIF('Annex 1.1.1 Outcome_CommPlan'!$H$14:$H$1048576,"February") -> 0 | H15: =COUNTIF('Annex 1.1.1 Outcome_CommPlan'!$H$14:$H$1048576,"March") -> 0 | I15: =COUNTIF('Annex 1.1.1 Outcome_CommPlan'!$H$14:$H$1048576,"April") -> 0 | J15: =COUNTIF('Annex 1.1.1 Outcome_CommPlan'!$H$14:$H$1048576,"May") -> 0 | K15: =COUNTIF('Annex 1.1.1 Outcome_CommPlan'!$H$14:$H$1048576,"June") -> 0 | L15: =COUNTIF('Annex 1.1.1 Outcome_CommPlan'!$H$14:$H$1048576,"July") -> 0 | M15: =COUNTIF('Annex 1.1.1 Outcome_CommPlan'!$H$14:$H$1048576,"August") -> 0 | N15: =COUNTIF('Annex 1.1.1 Outcome_CommPlan'!$H$14:$H$1048576,"September") -> 0 | O15: =COUNTIF('Annex 1.1.1 Outcome_CommPlan'!$H$14:$H$1048576,"October") -> 0 | P15: =COUNTIF('Annex 1.1.1 Outcome_CommPlan'!$H$14:$H$1048576,"November") -> 0 | Q15: =COUNTIF('Annex 1.1.1 Outcome_CommPlan'!$H$14:$H$1048576,"December") -> 0 | R15: =SUM(F15:H15) -> 0 | S15: =SUM(I15:K15) -> 0 | T15: =SUM(L15:N15) -> 0 | U15: =SUM(O15:Q15) -> 0 | V15: =SUM(F15:Q15) -> 0 | X15: Annex 1.1.1 Outcome_CommPlan'!A1
D16: 1.1.2 Number of LGUs with approved Comprehensive Land Use Plans (CLUPs) within the year with integrated enhanced housing sub-sector (LSP) | E16: 5 | F16: =COUNTIF('Annex 1.1.2 Outcome_Housing'!$H$14:$H$1048576, "January") -> 0 | G16: =COUNTIF('Annex 1.1.2 Outcome_Housing'!$H$14:$H$1048576, "February") -> 0 | H16: =COUNTIF('Annex 1.1.2 Outcome_Housing'!$H$14:$H$1048576, "March") -> 0 | I16: =COUNTIF('Annex 1.1.2 Outcome_Housing'!$H$14:$H$1048576, "April") -> 0 | J16: =COUNTIF('Annex 1.1.2 Outcome_Housing'!$H$14:$H$1048576, "May") -> 0 | K16: =COUNTIF('Annex 1.1.2 Outcome_Housing'!$H$14:$H$1048576, "June") -> 0 | L16: =COUNTIF('Annex 1.1.2 Outcome_Housing'!$H$14:$H$1048576, "July") -> 0 | M16: =COUNTIF('Annex 1.1.2 Outcome_Housing'!$H$14:$H$1048576, "August") -> 0 | N16: =COUNTIF('Annex 1.1.2 Outcome_Housing'!$H$14:$H$1048576, "September") -> 0 | O16: =COUNTIF('Annex 1.1.2 Outcome_Housing'!$H$14:$H$1048576, "October") -> 0 | P16: =COUNTIF('Annex 1.1.2 Outcome_Housing'!$H$14:$H$1048576, "November") -> 0 | Q16: =COUNTIF('Annex 1.1.2 Outcome_Housing'!$H$14:$H$1048576, "December") -> 0 | R16: =SUM(F16:H16) -> 0 | S16: =SUM(I16:K16) -> 0 | T16: =SUM(L16:N16) -> 0 | U16: =SUM(O16:Q16) -> 0 | V16: =SUM(F16:Q16) -> 0 | X16: Annex 1.1.2 Outcome_Housing'!A1
D17: 1.2. Number of provinces with approved PDPFPs/PPFPs within the year | E17: 1 | F17: =COUNTIF('Annex 1.2. Outcome_PDPFP'!$G$14:$G$1048576,"January") -> 0 | G17: =COUNTIF('Annex 1.2. Outcome_PDPFP'!$G$14:$G$1048576,"February") -> 0 | H17: =COUNTIF('Annex 1.2. Outcome_PDPFP'!$G$14:$G$1048576,"March") -> 0 | I17: =COUNTIF('Annex 1.2. Outcome_PDPFP'!$G$14:$G$1048576,"April") -> 0 | J17: =COUNTIF('Annex 1.2. Outcome_PDPFP'!$G$14:$G$1048576,"May") -> 0 | K17: =COUNTIF('Annex 1.2. Outcome_PDPFP'!$G$14:$G$1048576,"June") -> 0 | L17: =COUNTIF('Annex 1.2. Outcome_PDPFP'!$G$14:$G$1048576,"July") -> 0 | M17: =COUNTIF('Annex 1.2. Outcome_PDPFP'!$G$14:$G$1048576,"August") -> 0 | N17: =COUNTIF('Annex 1.2. Outcome_PDPFP'!$G$14:$G$1048576,"September") -> 0 | O17: =COUNTIF('Annex 1.2. Outcome_PDPFP'!$G$14:$G$1048576,"October") -> 0 | P17: =COUNTIF('Annex 1.2. Outcome_PDPFP'!$G$14:$G$1048576,"November") -> 0 | Q17: =COUNTIF('Annex 1.2. Outcome_PDPFP'!$G$14:$G$1048576,"December") -> 0 | R17: =SUM(F17:H17) -> 0 | S17: =SUM(I17:K17) -> 0 | T17: =SUM(L17:N17) -> 0 | U17: =SUM(O17:Q17) -> 0 | V17: =SUM(F17:Q17) -> 0 | X17: Annex 1.2. Outcome_PDPFP'!A1
B18: 2 | C18: Implementation of inclusive, safe, resilient, and sustainable urban development programs
D19: 2.1. Number of LGUs and stakeholders with approved proposals and/or budgeted programs/projects for inclusive, safe, resilient, and sustainable urban development, demonstrating adherence to DHSUD policies, standards, and guidelines | E19: 1 | F19: =COUNTIFS('Annex 2.1. Outcome_UrbanDev'!$K$14:$K$1000,"1st",'Annex 2.1. Outcome_UrbanDev'!$I$14:$I$1000,F11) -> 0 | G19: =COUNTIFS('Annex 2.1. Outcome_UrbanDev'!$K$14:$K$1000,"1st",'Annex 2.1. Outcome_UrbanDev'!$I$14:$I$1000,G11) -> 0 | H19: =COUNTIFS('Annex 2.1. Outcome_UrbanDev'!$K$14:$K$1000,"1st",'Annex 2.1. Outcome_UrbanDev'!$I$14:$I$1000,H11) -> 0 | I19: =COUNTIFS('Annex 2.1. Outcome_UrbanDev'!$K$14:$K$1000,"1st",'Annex 2.1. Outcome_UrbanDev'!$I$14:$I$1000,I11) -> 0 | J19: =COUNTIFS('Annex 2.1. Outcome_UrbanDev'!$K$14:$K$1000,"1st",'Annex 2.1. Outcome_UrbanDev'!$I$14:$I$1000,J11) -> 0 | K19: =COUNTIFS('Annex 2.1. Outcome_UrbanDev'!$K$14:$K$1000,"1st",'Annex 2.1. Outcome_UrbanDev'!$I$14:$I$1000,K11) -> 0 | L19: =COUNTIFS('Annex 2.1. Outcome_UrbanDev'!$K$14:$K$1000,"1st",'Annex 2.1. Outcome_UrbanDev'!$I$14:$I$1000,L11) -> 0 | M19: =COUNTIFS('Annex 2.1. Outcome_UrbanDev'!$K$14:$K$1000,"1st",'Annex 2.1. Outcome_UrbanDev'!$I$14:$I$1000,M11) -> 0 | ... Q19: =COUNTIFS('Annex 2.1. Outcome_UrbanDev'!$K$14:$K$1000,"1st",'Annex 2.1. Outcome_UrbanDev'!$I$14:$I$1000,Q11) -> 0 | R19: =SUM(F19:H19) -> 0 | S19: =SUM(G19:I19) -> 0 | T19: =SUM(H19:J19) -> 0 | U19: =SUM(I19:K19) -> 0 | V19: =SUM(F19:Q19) -> 0 | X19: Annex 2.1. Outcome_UrbanDev'!A1
A20: OUTPUT INDICATORS
B21: Technical Assistance
B22: 1 | C22: Technical assistance on the preparation of CLUPs and ZOs
C23: 1.1. No. of LGUs assisted on the preparation of CLUPs and ZOs (single counting) | E23: 12 | F23: =COUNTIFS('Annex 4.1 TA_CLUP'!$J$18:$J$1005,"1st",'Annex 4.1 TA_CLUP'!$H$18:$H$1005,"January") -> 1 | G23: =COUNTIFS('Annex 4.1 TA_CLUP'!$J$18:$J$1005,"1st",'Annex 4.1 TA_CLUP'!$H$18:$H$1005,"February") -> 3 | H23: =COUNTIFS('Annex 4.1 TA_CLUP'!$J$18:$J$1005,"1st",'Annex 4.1 TA_CLUP'!$H$18:$H$1005,"March") -> 0 | I23: =COUNTIFS('Annex 4.1 TA_CLUP'!$J$18:$J$1005,"1st",'Annex 4.1 TA_CLUP'!$H$18:$H$1005,"April") -> 0 | J23: =COUNTIFS('Annex 4.1 TA_CLUP'!$J$18:$J$1005,"1st",'Annex 4.1 TA_CLUP'!$H$18:$H$1005,"May") -> 0 | K23: =COUNTIFS('Annex 4.1 TA_CLUP'!$J$18:$J$1005,"1st",'Annex 4.1 TA_CLUP'!$H$18:$H$1005,"June") -> 0 | L23: =COUNTIFS('Annex 4.1 TA_CLUP'!$J$18:$J$1005,"1st",'Annex 4.1 TA_CLUP'!$H$18:$H$1005,"July") -> 0 | M23: =COUNTIFS('Annex 4.1 TA_CLUP'!$J$18:$J$1005,"1st",'Annex 4.1 TA_CLUP'!$H$18:$H$1005,"August") -> 0 | N23: =COUNTIFS('Annex 4.1 TA_CLUP'!$J$18:$J$1005,"1st",'Annex 4.1 TA_CLUP'!$H$18:$H$1005,"September") -> 0 | O23: =COUNTIFS('Annex 4.1 TA_CLUP'!$J$18:$J$1005,"1st",'Annex 4.1 TA_CLUP'!$H$18:$H$1005,"October") -> 0 | P23: =COUNTIFS('Annex 4.1 TA_CLUP'!$J$18:$J$1005,"1st",'Annex 4.1 TA_CLUP'!$H$18:$H$1005,"November") -> 0 | Q23: =COUNTIFS('Annex 4.1 TA_CLUP'!$J$18:$J$1005,"1st",'Annex 4.1 TA_CLUP'!$H$18:$H$1005,"December") -> 0 | R23: =SUM(F23:H23) -> 4 | S23: =SUM(I23:K23) -> 0 | T23: =SUM(L23:N23) -> 0 | U23: =SUM(O23:Q23) -> 0 | V23: =SUM(F23:Q23) -> 4 | X23: Annex 4.1 TA_CLUP'!A1
C24: 1.2. No. of assistance provided: | F24: =COUNTIFS('Annex 4.1 TA_CLUP'!$D$18:$D$1005, "<>", 'Annex 4.1 TA_CLUP'!$H$18:$H$1005, "January") -> 1 | G24: =COUNTIFS('Annex 4.1 TA_CLUP'!$D$18:$D$1005, "<>", 'Annex 4.1 TA_CLUP'!$H$18:$H$1005, "February") -> 5 | H24: =COUNTIFS('Annex 4.1 TA_CLUP'!$D$18:$D$1005, "<>", 'Annex 4.1 TA_CLUP'!$H$18:$H$1005, "March") -> 0 | I24: =COUNTIFS('Annex 4.1 TA_CLUP'!$D$18:$D$1005, "<>", 'Annex 4.1 TA_CLUP'!$H$18:$H$1005, "April") -> 0 | J24: =COUNTIFS('Annex 4.1 TA_CLUP'!$D$18:$D$1005, "<>", 'Annex 4.1 TA_CLUP'!$H$18:$H$1005, "May") -> 0 | K24: =COUNTIFS('Annex 4.1 TA_CLUP'!$D$18:$D$1005, "<>", 'Annex 4.1 TA_CLUP'!$H$18:$H$1005, "June") -> 0 | L24: =COUNTIFS('Annex 4.1 TA_CLUP'!$D$18:$D$1005, "<>", 'Annex 4.1 TA_CLUP'!$H$18:$H$1005, "July") -> 0 | M24: =COUNTIFS('Annex 4.1 TA_CLUP'!$D$18:$D$1005, "<>", 'Annex 4.1 TA_CLUP'!$H$18:$H$1005, "August") -> 0 | N24: =COUNTIFS('Annex 4.1 TA_CLUP'!$D$18:$D$1005, "<>", 'Annex 4.1 TA_CLUP'!$H$18:$H$1005, "September") -> 0 | O24: =COUNTIFS('Annex 4.1 TA_CLUP'!$D$18:$D$1005, "<>", 'Annex 4.1 TA_CLUP'!$H$18:$H$1005, "October") -> 0 | P24: =COUNTIFS('Annex 4.1 TA_CLUP'!$D$18:$D$1005, "<>", 'Annex 4.1 TA_CLUP'!$H$18:$H$1005, "November") -> 0 | Q24: =COUNTIFS('Annex 4.1 TA_CLUP'!$D$18:$D$1005, "<>", 'Annex 4.1 TA_CLUP'!$H$18:$H$1005, "December") -> 0 | R24: =SUM(F24:H24) -> 6 | S24: =SUM(I24:K24) -> 0 | T24: =SUM(L24:N24) -> 0 | U24: =SUM(O24:Q24) -> 0 | V24: =SUM(F24:Q24) -> 6
D25: 1.2.1. No. of planned assistance | F25: =COUNTIFS('Annex 4.1 TA_CLUP'!$F$18:$F$1005,"Planned",'Annex 4.1 TA_CLUP'!$H$18:$H$1005,"January") -> 0 | G25: =COUNTIFS('Annex 4.1 TA_CLUP'!$F$18:$F$1005,"Planned",'Annex 4.1 TA_CLUP'!$H$18:$H$1005,"February") -> 0 | H25: =COUNTIFS('Annex 4.1 TA_CLUP'!$F$18:$F$1005,"Planned",'Annex 4.1 TA_CLUP'!$H$18:$H$1005,"March") -> 0 | I25: =COUNTIFS('Annex 4.1 TA_CLUP'!$F$18:$F$1005,"Planned",'Annex 4.1 TA_CLUP'!$H$18:$H$1005,"April") -> 0 | J25: =COUNTIFS('Annex 4.1 TA_CLUP'!$F$18:$F$1005,"Planned",'Annex 4.1 TA_CLUP'!$H$18:$H$1005,"May") -> 0 | K25: =COUNTIFS('Annex 4.1 TA_CLUP'!$F$18:$F$1005,"Planned",'Annex 4.1 TA_CLUP'!$H$18:$H$1005,"June") -> 0 | L25: =COUNTIFS('Annex 4.1 TA_CLUP'!$F$18:$F$1005,"Planned",'Annex 4.1 TA_CLUP'!$H$18:$H$1005,"July") -> 0 | M25: =COUNTIFS('Annex 4.1 TA_CLUP'!$F$18:$F$1005,"Planned",'Annex 4.1 TA_CLUP'!$H$18:$H$1005,"August") -> 0 | N25: =COUNTIFS('Annex 4.1 TA_CLUP'!$F$18:$F$1005,"Planned",'Annex 4.1 TA_CLUP'!$H$18:$H$1005,"September") -> 0 | O25: =COUNTIFS('Annex 4.1 TA_CLUP'!$F$18:$F$1005,"Planned",'Annex 4.1 TA_CLUP'!$H$18:$H$1005,"October") -> 0 | P25: =COUNTIFS('Annex 4.1 TA_CLUP'!$F$18:$F$1005,"Planned",'Annex 4.1 TA_CLUP'!$H$18:$H$1005,"November") -> 0 | Q25: =COUNTIFS('Annex 4.1 TA_CLUP'!$F$18:$F$1005,"Planned",'Annex 4.1 TA_CLUP'!$H$18:$H$1005,"December") -> 0 | R25: =SUM(F25:H25) -> 0 | S25: =SUM(I25:K25) -> 0 | T25: =SUM(L25:N25) -> 0 | U25: =SUM(O25:Q25) -> 0 | V25: =SUM(F25:Q25) -> 0
D26: 1.2.2. No. of requested (by demand) assistance | F26: =COUNTIFS('Annex 4.1 TA_CLUP'!$F$18:$F$1005,"Requested",'Annex 4.1 TA_CLUP'!$H$18:$H$1005,F11) -> 1 | G26: =COUNTIFS('Annex 4.1 TA_CLUP'!$F$18:$F$1005,"Requested",'Annex 4.1 TA_CLUP'!$H$18:$H$1005,G11) -> 5 | H26: =COUNTIFS('Annex 4.1 TA_CLUP'!$F$18:$F$1005,"Requested",'Annex 4.1 TA_CLUP'!$H$18:$H$1005,H11) -> 0 | I26: =COUNTIFS('Annex 4.1 TA_CLUP'!$F$18:$F$1005,"Requested",'Annex 4.1 TA_CLUP'!$H$18:$H$1005,I11) -> 0 | J26: =COUNTIFS('Annex 4.1 TA_CLUP'!$F$18:$F$1005,"Requested",'Annex 4.1 TA_CLUP'!$H$18:$H$1005,J11) -> 0 | K26: =COUNTIFS('Annex 4.1 TA_CLUP'!$F$18:$F$1005,"Requested",'Annex 4.1 TA_CLUP'!$H$18:$H$1005,K11) -> 0 | L26: =COUNTIFS('Annex 4.1 TA_CLUP'!$F$18:$F$1005,"Requested",'Annex 4.1 TA_CLUP'!$H$18:$H$1005,L11) -> 0 | M26: =COUNTIFS('Annex 4.1 TA_CLUP'!$F$18:$F$1005,"Requested",'Annex 4.1 TA_CLUP'!$H$18:$H$1005,M11) -> 0 | ... Q26: =COUNTIFS('Annex 4.1 TA_CLUP'!$F$18:$F$1005,"Requested",'Annex 4.1 TA_CLUP'!$H$18:$H$1005,Q11) -> 0 | R26: =SUM(F26:H26) -> 6 | S26: =SUM(I26:K26) -> 0 | T26: =SUM(L26:N26) -> 0 | U26: =SUM(O26:Q26) -> 0 | V26: =SUM(F26:Q26) -> 6
B27: 2 | C27: Technical assistance on the preparation of PDPFPs/PPFPs
C28: 2.1. No. of LGUs assisted on the preparation of PDPFPs/PPFPs (single counting) | E28: 1 | F28: =COUNTIFS('Annex 4.2 TA_PDPFP'!$I$18:$I$1000,"1st",'Annex 4.2 TA_PDPFP'!$G$18:$G$1000,'Accomplishment 2026'!F11) -> 0 | G28: =COUNTIFS('Annex 4.2 TA_PDPFP'!$I$18:$I$1000,"1st",'Annex 4.2 TA_PDPFP'!$G$18:$G$1000,'Accomplishment 2026'!G11) -> 0 | H28: =COUNTIFS('Annex 4.2 TA_PDPFP'!$I$18:$I$1000,"1st",'Annex 4.2 TA_PDPFP'!$G$18:$G$1000,'Accomplishment 2026'!H11) -> 0 | I28: =COUNTIFS('Annex 4.2 TA_PDPFP'!$I$18:$I$1000,"1st",'Annex 4.2 TA_PDPFP'!$G$18:$G$1000,'Accomplishment 2026'!I11) -> 0 | J28: =COUNTIFS('Annex 4.2 TA_PDPFP'!$I$18:$I$1000,"1st",'Annex 4.2 TA_PDPFP'!$G$18:$G$1000,'Accomplishment 2026'!J11) -> 0 | K28: =COUNTIFS('Annex 4.2 TA_PDPFP'!$I$18:$I$1000,"1st",'Annex 4.2 TA_PDPFP'!$G$18:$G$1000,'Accomplishment 2026'!K11) -> 0 | L28: =COUNTIFS('Annex 4.2 TA_PDPFP'!$I$18:$I$1000,"1st",'Annex 4.2 TA_PDPFP'!$G$18:$G$1000,'Accomplishment 2026'!L11) -> 0 | M28: =COUNTIFS('Annex 4.2 TA_PDPFP'!$I$18:$I$1000,"1st",'Annex 4.2 TA_PDPFP'!$G$18:$G$1000,'Accomplishment 2026'!M11) -> 0 | ... Q28: =COUNTIFS('Annex 4.2 TA_PDPFP'!$I$18:$I$1000,"1st",'Annex 4.2 TA_PDPFP'!$G$18:$G$1000,'Accomplishment 2026'!Q11) -> 0 | R28: =SUM(F28:H28) -> 0 | S28: =SUM(I28:K28) -> 0 | T28: =SUM(L28:N28) -> 0 | U28: =SUM(O28:Q28) -> 0 | V28: =SUM(F28:Q28) -> 0 | X28: Annex 4.2 TA_PDPFP'!A1
C29: 2.2. No. of assistance provided: | F29: =COUNTIFS('Annex 4.2 TA_PDPFP'!$C$18:$C$1000,"<>",'Annex 4.2 TA_PDPFP'!$G$18:$G$1000,'Accomplishment 2026'!F11) -> 0 | G29: =COUNTIFS('Annex 4.2 TA_PDPFP'!$C$18:$C$1000,"<>",'Annex 4.2 TA_PDPFP'!$G$18:$G$1000,'Accomplishment 2026'!G11) -> 0 | H29: =COUNTIFS('Annex 4.2 TA_PDPFP'!$C$18:$C$1000,"<>",'Annex 4.2 TA_PDPFP'!$G$18:$G$1000,'Accomplishment 2026'!H11) -> 0 | I29: =COUNTIFS('Annex 4.2 TA_PDPFP'!$C$18:$C$1000,"<>",'Annex 4.2 TA_PDPFP'!$G$18:$G$1000,'Accomplishment 2026'!I11) -> 0 | J29: =COUNTIFS('Annex 4.2 TA_PDPFP'!$C$18:$C$1000,"<>",'Annex 4.2 TA_PDPFP'!$G$18:$G$1000,'Accomplishment 2026'!J11) -> 0 | K29: =COUNTIFS('Annex 4.2 TA_PDPFP'!$C$18:$C$1000,"<>",'Annex 4.2 TA_PDPFP'!$G$18:$G$1000,'Accomplishment 2026'!K11) -> 0 | L29: =COUNTIFS('Annex 4.2 TA_PDPFP'!$C$18:$C$1000,"<>",'Annex 4.2 TA_PDPFP'!$G$18:$G$1000,'Accomplishment 2026'!L11) -> 0 | M29: =COUNTIFS('Annex 4.2 TA_PDPFP'!$C$18:$C$1000,"<>",'Annex 4.2 TA_PDPFP'!$G$18:$G$1000,'Accomplishment 2026'!M11) -> 0 | ... Q29: =COUNTIFS('Annex 4.2 TA_PDPFP'!$C$18:$C$1000,"<>",'Annex 4.2 TA_PDPFP'!$G$18:$G$1000,'Accomplishment 2026'!Q11) -> 0 | R29: =SUM(F29:H29) -> 0 | S29: =SUM(I29:K29) -> 0 | T29: =SUM(L29:N29) -> 0 | U29: =SUM(O29:Q29) -> 0 | V29: =SUM(F29:Q29) -> 0
D30: 2.2.1. No. of planned assistance | F30: =COUNTIFS('Annex 4.2 TA_PDPFP'!$E$18:$E$1000,"Planned",'Annex 4.2 TA_PDPFP'!$G$18:$G$1000,F11) -> 0 | G30: =COUNTIFS('Annex 4.2 TA_PDPFP'!$E$18:$E$1000,"Planned",'Annex 4.2 TA_PDPFP'!$G$18:$G$1000,G11) -> 0 | H30: =COUNTIFS('Annex 4.2 TA_PDPFP'!$E$18:$E$1000,"Planned",'Annex 4.2 TA_PDPFP'!$G$18:$G$1000,H11) -> 0 | I30: =COUNTIFS('Annex 4.2 TA_PDPFP'!$E$18:$E$1000,"Planned",'Annex 4.2 TA_PDPFP'!$G$18:$G$1000,I11) -> 0 | J30: =COUNTIFS('Annex 4.2 TA_PDPFP'!$E$18:$E$1000,"Planned",'Annex 4.2 TA_PDPFP'!$G$18:$G$1000,J11) -> 0 | K30: =COUNTIFS('Annex 4.2 TA_PDPFP'!$E$18:$E$1000,"Planned",'Annex 4.2 TA_PDPFP'!$G$18:$G$1000,K11) -> 0 | L30: =COUNTIFS('Annex 4.2 TA_PDPFP'!$E$18:$E$1000,"Planned",'Annex 4.2 TA_PDPFP'!$G$18:$G$1000,L11) -> 0 | M30: =COUNTIFS('Annex 4.2 TA_PDPFP'!$E$18:$E$1000,"Planned",'Annex 4.2 TA_PDPFP'!$G$18:$G$1000,M11) -> 0 | ... Q30: =COUNTIFS('Annex 4.2 TA_PDPFP'!$E$18:$E$1000,"Planned",'Annex 4.2 TA_PDPFP'!$G$18:$G$1000,Q11) -> 0 | R30: =SUM(F30:H30) -> 0 | S30: =SUM(I30:K30) -> 0 | T30: =SUM(L30:N30) -> 0 | U30: =SUM(O30:Q30) -> 0 | V30: =SUM(F30:Q30) -> 0
D31: 2.2.2. No. of requested (by demand) assistance | F31: =COUNTIFS('Annex 4.2 TA_PDPFP'!$E$18:$E$1000,"Requested",'Annex 4.2 TA_PDPFP'!$G$18:$G$1000,F11) -> 0 | G31: =COUNTIFS('Annex 4.2 TA_PDPFP'!$E$18:$E$1000,"Requested",'Annex 4.2 TA_PDPFP'!$G$18:$G$1000,G11) -> 0 | H31: =COUNTIFS('Annex 4.2 TA_PDPFP'!$E$18:$E$1000,"Requested",'Annex 4.2 TA_PDPFP'!$G$18:$G$1000,H11) -> 0 | I31: =COUNTIFS('Annex 4.2 TA_PDPFP'!$E$18:$E$1000,"Requested",'Annex 4.2 TA_PDPFP'!$G$18:$G$1000,I11) -> 0 | J31: =COUNTIFS('Annex 4.2 TA_PDPFP'!$E$18:$E$1000,"Requested",'Annex 4.2 TA_PDPFP'!$G$18:$G$1000,J11) -> 0 | K31: =COUNTIFS('Annex 4.2 TA_PDPFP'!$E$18:$E$1000,"Requested",'Annex 4.2 TA_PDPFP'!$G$18:$G$1000,K11) -> 0 | L31: =COUNTIFS('Annex 4.2 TA_PDPFP'!$E$18:$E$1000,"Requested",'Annex 4.2 TA_PDPFP'!$G$18:$G$1000,L11) -> 0 | M31: =COUNTIFS('Annex 4.2 TA_PDPFP'!$E$18:$E$1000,"Requested",'Annex 4.2 TA_PDPFP'!$G$18:$G$1000,M11) -> 0 | ... Q31: =COUNTIFS('Annex 4.2 TA_PDPFP'!$E$18:$E$1000,"Requested",'Annex 4.2 TA_PDPFP'!$G$18:$G$1000,Q11) -> 0 | R31: =SUM(F31:H31) -> 0 | S31: =SUM(I31:K31) -> 0 | T31: =SUM(L31:N31) -> 0 | U31: =SUM(O31:Q31) -> 0 | V31: =SUM(F31:Q31) -> 0
B32: 3 | C32: Technical assistance on the preparation of enhanced housing sub-sector (LSP)
C33: 3.1. No. of LGUs assisted on preparation of enhanced housing sub-sector in preparation for integration to CLUP (single counting) | E33: 3 | F33: =COUNTIFS('Annex 4.3 TA_HouSub'!$J$18:$J$999,"1st",'Annex 4.3 TA_HouSub'!$H$18:$H$999,F11) -> 0 | G33: =COUNTIFS('Annex 4.3 TA_HouSub'!$J$18:$J$999,"1st",'Annex 4.3 TA_HouSub'!$H$18:$H$999,G11) -> 2 | H33: =COUNTIFS('Annex 4.3 TA_HouSub'!$J$18:$J$999,"1st",'Annex 4.3 TA_HouSub'!$H$18:$H$999,H11) -> 0 | I33: =COUNTIFS('Annex 4.3 TA_HouSub'!$J$18:$J$999,"1st",'Annex 4.3 TA_HouSub'!$H$18:$H$999,I11) -> 0 | J33: =COUNTIFS('Annex 4.3 TA_HouSub'!$J$18:$J$999,"1st",'Annex 4.3 TA_HouSub'!$H$18:$H$999,J11) -> 0 | K33: =COUNTIFS('Annex 4.3 TA_HouSub'!$J$18:$J$999,"1st",'Annex 4.3 TA_HouSub'!$H$18:$H$999,K11) -> 0 | L33: =COUNTIFS('Annex 4.3 TA_HouSub'!$J$18:$J$999,"1st",'Annex 4.3 TA_HouSub'!$H$18:$H$999,L11) -> 0 | M33: =COUNTIFS('Annex 4.3 TA_HouSub'!$J$18:$J$999,"1st",'Annex 4.3 TA_HouSub'!$H$18:$H$999,M11) -> 0 | ... Q33: =COUNTIFS('Annex 4.3 TA_HouSub'!$J$18:$J$999,"1st",'Annex 4.3 TA_HouSub'!$H$18:$H$999,Q11) -> 0 | R33: =SUM(F33:H33) -> 2 | S33: =SUM(I33:K33) -> 0 | T33: =SUM(L33:N33) -> 0 | U33: =SUM(O33:Q33) -> 0 | V33: =SUM(F33:Q33) -> 2 | X33: Annex 4.3 TA_HouSub'!A1
C34: 3.2. No. of assistance provided: | F34: =COUNTIFS('Annex 4.3 TA_HouSub'!$D$18:$D$999,"<>",'Annex 4.3 TA_HouSub'!$H$18:$H$999,F11) -> 0 | G34: =COUNTIFS('Annex 4.3 TA_HouSub'!$D$18:$D$999,"<>",'Annex 4.3 TA_HouSub'!$H$18:$H$999,G11) -> 2 | H34: =COUNTIFS('Annex 4.3 TA_HouSub'!$D$18:$D$999,"<>",'Annex 4.3 TA_HouSub'!$H$18:$H$999,H11) -> 0 | I34: =COUNTIFS('Annex 4.3 TA_HouSub'!$D$18:$D$999,"<>",'Annex 4.3 TA_HouSub'!$H$18:$H$999,I11) -> 0 | J34: =COUNTIFS('Annex 4.3 TA_HouSub'!$D$18:$D$999,"<>",'Annex 4.3 TA_HouSub'!$H$18:$H$999,J11) -> 0 | K34: =COUNTIFS('Annex 4.3 TA_HouSub'!$D$18:$D$999,"<>",'Annex 4.3 TA_HouSub'!$H$18:$H$999,K11) -> 0 | L34: =COUNTIFS('Annex 4.3 TA_HouSub'!$D$18:$D$999,"<>",'Annex 4.3 TA_HouSub'!$H$18:$H$999,L11) -> 0 | M34: =COUNTIFS('Annex 4.3 TA_HouSub'!$D$18:$D$999,"<>",'Annex 4.3 TA_HouSub'!$H$18:$H$999,M11) -> 0 | ... Q34: =COUNTIFS('Annex 4.3 TA_HouSub'!$D$18:$D$999,"<>",'Annex 4.3 TA_HouSub'!$H$18:$H$999,Q11) -> 0 | R34: =SUM(F34:H34) -> 2 | S34: =SUM(I34:K34) -> 0 | T34: =SUM(L34:N34) -> 0 | U34: =SUM(O34:Q34) -> 0 | V34: =SUM(F34:Q34) -> 2
D35: 3.2.1. No. of planned assistance | F35: =COUNTIFS('Annex 4.3 TA_HouSub'!$F$18:$F$999,"Planned",'Annex 4.3 TA_HouSub'!$H$18:$H$999,F11) -> 0 | G35: =COUNTIFS('Annex 4.3 TA_HouSub'!$F$18:$F$999,"Planned",'Annex 4.3 TA_HouSub'!$H$18:$H$999,G11) -> 0 | H35: =COUNTIFS('Annex 4.3 TA_HouSub'!$F$18:$F$999,"Planned",'Annex 4.3 TA_HouSub'!$H$18:$H$999,H11) -> 0 | I35: =COUNTIFS('Annex 4.3 TA_HouSub'!$F$18:$F$999,"Planned",'Annex 4.3 TA_HouSub'!$H$18:$H$999,I11) -> 0 | J35: =COUNTIFS('Annex 4.3 TA_HouSub'!$F$18:$F$999,"Planned",'Annex 4.3 TA_HouSub'!$H$18:$H$999,J11) -> 0 | K35: =COUNTIFS('Annex 4.3 TA_HouSub'!$F$18:$F$999,"Planned",'Annex 4.3 TA_HouSub'!$H$18:$H$999,K11) -> 0 | L35: =COUNTIFS('Annex 4.3 TA_HouSub'!$F$18:$F$999,"Planned",'Annex 4.3 TA_HouSub'!$H$18:$H$999,L11) -> 0 | M35: =COUNTIFS('Annex 4.3 TA_HouSub'!$F$18:$F$999,"Planned",'Annex 4.3 TA_HouSub'!$H$18:$H$999,M11) -> 0 | ... Q35: =COUNTIFS('Annex 4.3 TA_HouSub'!$F$18:$F$999,"Planned",'Annex 4.3 TA_HouSub'!$H$18:$H$999,Q11) -> 0 | R35: =SUM(F35:H35) -> 0 | S35: =SUM(I35:K35) -> 0 | T35: =SUM(L35:N35) -> 0 | U35: =SUM(O35:Q35) -> 0 | V35: =SUM(F35:Q35) -> 0
D36: 3.2.2. No. of requested (by demand) assistance | F36: =COUNTIFS('Annex 4.3 TA_HouSub'!$F$18:$F$999,"Requested",'Annex 4.3 TA_HouSub'!$H$18:$H$999,F11) -> 0 | G36: =COUNTIFS('Annex 4.3 TA_HouSub'!$F$18:$F$999,"Requested",'Annex 4.3 TA_HouSub'!$H$18:$H$999,G11) -> 2 | H36: =COUNTIFS('Annex 4.3 TA_HouSub'!$F$18:$F$999,"Requested",'Annex 4.3 TA_HouSub'!$H$18:$H$999,H11) -> 0 | I36: =COUNTIFS('Annex 4.3 TA_HouSub'!$F$18:$F$999,"Requested",'Annex 4.3 TA_HouSub'!$H$18:$H$999,I11) -> 0 | J36: =COUNTIFS('Annex 4.3 TA_HouSub'!$F$18:$F$999,"Requested",'Annex 4.3 TA_HouSub'!$H$18:$H$999,J11) -> 0 | K36: =COUNTIFS('Annex 4.3 TA_HouSub'!$F$18:$F$999,"Requested",'Annex 4.3 TA_HouSub'!$H$18:$H$999,K11) -> 0 | L36: =COUNTIFS('Annex 4.3 TA_HouSub'!$F$18:$F$999,"Requested",'Annex 4.3 TA_HouSub'!$H$18:$H$999,L11) -> 0 | M36: =COUNTIFS('Annex 4.3 TA_HouSub'!$F$18:$F$999,"Requested",'Annex 4.3 TA_HouSub'!$H$18:$H$999,M11) -> 0 | ... Q36: =COUNTIFS('Annex 4.3 TA_HouSub'!$F$18:$F$999,"Requested",'Annex 4.3 TA_HouSub'!$H$18:$H$999,Q11) -> 0 | R36: =SUM(F36:H36) -> 2 | S36: =SUM(I36:K36) -> 0 | T36: =SUM(L36:N36) -> 0 | U36: =SUM(O36:Q36) -> 0 | V36: =SUM(F36:Q36) -> 2
B37: 4 | C37: Technical assistance on the review and approval process of CLUPs/ZOs
C38: 4.1. Number of LGUs assisted/facilitated for review and approval of CLUPs/ZOs (single counting) | E38: 3 | F38: =COUNTIFS('Annex 4.4 TA_RA'!$L$18:$L$1000,"1st",'Annex 4.4 TA_RA'!$J$18:$J$1000,F11) -> 2 | G38: =COUNTIFS('Annex 4.4 TA_RA'!$L$18:$L$1000,"1st",'Annex 4.4 TA_RA'!$J$18:$J$1000,G11) -> 3 | H38: =COUNTIFS('Annex 4.4 TA_RA'!$L$18:$L$1000,"1st",'Annex 4.4 TA_RA'!$J$18:$J$1000,H11) -> 0 | I38: =COUNTIFS('Annex 4.4 TA_RA'!$L$18:$L$1000,"1st",'Annex 4.4 TA_RA'!$J$18:$J$1000,I11) -> 0 | J38: =COUNTIFS('Annex 4.4 TA_RA'!$L$18:$L$1000,"1st",'Annex 4.4 TA_RA'!$J$18:$J$1000,J11) -> 0 | K38: =COUNTIFS('Annex 4.4 TA_RA'!$L$18:$L$1000,"1st",'Annex 4.4 TA_RA'!$J$18:$J$1000,K11) -> 0 | L38: =COUNTIFS('Annex 4.4 TA_RA'!$L$18:$L$1000,"1st",'Annex 4.4 TA_RA'!$J$18:$J$1000,L11) -> 0 | M38: =COUNTIFS('Annex 4.4 TA_RA'!$L$18:$L$1000,"1st",'Annex 4.4 TA_RA'!$J$18:$J$1000,M11) -> 0 | ... Q38: =COUNTIFS('Annex 4.4 TA_RA'!$L$18:$L$1000,"1st",'Annex 4.4 TA_RA'!$J$18:$J$1000,Q11) -> 0 | R38: =SUM(F38:H38) -> 5 | S38: =SUM(I38:K38) -> 0 | T38: =SUM(L38:N38) -> 0 | U38: =SUM(O38:Q38) -> 0 | V38: =SUM(F38:Q38) -> 5 | X38: Annex 4.4 TA_RA'!A1
C39: 4.2. No. of assistance provided: | F39: =COUNTIFS('Annex 4.4 TA_RA'!$F$18:$F$1000,"<>",'Annex 4.4 TA_RA'!$J$18:$J$1000,F11) -> 2 | G39: =COUNTIFS('Annex 4.4 TA_RA'!$F$18:$F$1000,"<>",'Annex 4.4 TA_RA'!$J$18:$J$1000,G11) -> 3 | H39: =COUNTIFS('Annex 4.4 TA_RA'!$F$18:$F$1000,"<>",'Annex 4.4 TA_RA'!$J$18:$J$1000,H11) -> 0 | I39: =COUNTIFS('Annex 4.4 TA_RA'!$F$18:$F$1000,"<>",'Annex 4.4 TA_RA'!$J$18:$J$1000,I11) -> 0 | J39: =COUNTIFS('Annex 4.4 TA_RA'!$F$18:$F$1000,"<>",'Annex 4.4 TA_RA'!$J$18:$J$1000,J11) -> 0 | K39: =COUNTIFS('Annex 4.4 TA_RA'!$F$18:$F$1000,"<>",'Annex 4.4 TA_RA'!$J$18:$J$1000,K11) -> 0 | L39: =COUNTIFS('Annex 4.4 TA_RA'!$F$18:$F$1000,"<>",'Annex 4.4 TA_RA'!$J$18:$J$1000,L11) -> 0 | M39: =COUNTIFS('Annex 4.4 TA_RA'!$F$18:$F$1000,"<>",'Annex 4.4 TA_RA'!$J$18:$J$1000,M11) -> 0 | ... Q39: =COUNTIFS('Annex 4.4 TA_RA'!$F$18:$F$1000,"<>",'Annex 4.4 TA_RA'!$J$18:$J$1000,Q11) -> 0 | R39: =SUM(F39:H39) -> 5 | S39: =SUM(I39:K39) -> 0 | T39: =SUM(L39:N39) -> 0 | U39: =SUM(O39:Q39) -> 0 | V39: =SUM(F39:Q39) -> 5
D40: 4.2.1. No. of planned assistance | F40: =COUNTIFS('Annex 4.4 TA_RA'!$H$18:$H$1000,"Planned",'Annex 4.4 TA_RA'!$J$18:$J$1000,F11) -> 0 | G40: =COUNTIFS('Annex 4.4 TA_RA'!$H$18:$H$1000,"Planned",'Annex 4.4 TA_RA'!$J$18:$J$1000,G11) -> 0 | H40: =COUNTIFS('Annex 4.4 TA_RA'!$H$18:$H$1000,"Planned",'Annex 4.4 TA_RA'!$J$18:$J$1000,H11) -> 0 | I40: =COUNTIFS('Annex 4.4 TA_RA'!$H$18:$H$1000,"Planned",'Annex 4.4 TA_RA'!$J$18:$J$1000,I11) -> 0 | J40: =COUNTIFS('Annex 4.4 TA_RA'!$H$18:$H$1000,"Planned",'Annex 4.4 TA_RA'!$J$18:$J$1000,J11) -> 0 | K40: =COUNTIFS('Annex 4.4 TA_RA'!$H$18:$H$1000,"Planned",'Annex 4.4 TA_RA'!$J$18:$J$1000,K11) -> 0 | L40: =COUNTIFS('Annex 4.4 TA_RA'!$H$18:$H$1000,"Planned",'Annex 4.4 TA_RA'!$J$18:$J$1000,L11) -> 0 | M40: =COUNTIFS('Annex 4.4 TA_RA'!$H$18:$H$1000,"Planned",'Annex 4.4 TA_RA'!$J$18:$J$1000,M11) -> 0 | ... Q40: =COUNTIFS('Annex 4.4 TA_RA'!$H$18:$H$1000,"Planned",'Annex 4.4 TA_RA'!$J$18:$J$1000,Q11) -> 0 | R40: =SUM(F40:H40) -> 0 | S40: =SUM(I40:K40) -> 0 | T40: =SUM(L40:N40) -> 0 | U40: =SUM(O40:Q40) -> 0 | V40: =SUM(F40:Q40) -> 0
D41: 4.2.2. No. of requested (by demand) assistance | F41: =COUNTIFS('Annex 4.4 TA_RA'!$H$18:$H$1000,"Requested",'Annex 4.4 TA_RA'!$J$18:$J$1000,F11) -> 2 | G41: =COUNTIFS('Annex 4.4 TA_RA'!$H$18:$H$1000,"Requested",'Annex 4.4 TA_RA'!$J$18:$J$1000,G11) -> 3 | H41: =COUNTIFS('Annex 4.4 TA_RA'!$H$18:$H$1000,"Requested",'Annex 4.4 TA_RA'!$J$18:$J$1000,H11) -> 0 | I41: =COUNTIFS('Annex 4.4 TA_RA'!$H$18:$H$1000,"Requested",'Annex 4.4 TA_RA'!$J$18:$J$1000,I11) -> 0 | J41: =COUNTIFS('Annex 4.4 TA_RA'!$H$18:$H$1000,"Requested",'Annex 4.4 TA_RA'!$J$18:$J$1000,J11) -> 0 | K41: =COUNTIFS('Annex 4.4 TA_RA'!$H$18:$H$1000,"Requested",'Annex 4.4 TA_RA'!$J$18:$J$1000,K11) -> 0 | L41: =COUNTIFS('Annex 4.4 TA_RA'!$H$18:$H$1000,"Requested",'Annex 4.4 TA_RA'!$J$18:$J$1000,L11) -> 0 | M41: =COUNTIFS('Annex 4.4 TA_RA'!$H$18:$H$1000,"Requested",'Annex 4.4 TA_RA'!$J$18:$J$1000,M11) -> 0 | ... Q41: =COUNTIFS('Annex 4.4 TA_RA'!$H$18:$H$1000,"Requested",'Annex 4.4 TA_RA'!$J$18:$J$1000,Q11) -> 0 | R41: =SUM(F41:H41) -> 5 | S41: =SUM(I41:K41) -> 0 | T41: =SUM(L41:N41) -> 0 | U41: =SUM(O41:Q41) -> 0 | V41: =SUM(F41:Q41) -> 5
B42: 5 | C42: Technical assistance on the implementation of CLUPs/ZOs
C43: 5.1. No. of LGUs assisted on the implementation of CLUPs/ZOs | E43: 10 | F43: =COUNTIFS('Annex 4.5 TA_Imp'!$L$18:$L$1000,"1st",'Annex 4.5 TA_Imp'!$J$18:$J$1000,F11) -> 4 | G43: =COUNTIFS('Annex 4.5 TA_Imp'!$L$18:$L$1000,"1st",'Annex 4.5 TA_Imp'!$J$18:$J$1000,G11) -> 1 | H43: =COUNTIFS('Annex 4.5 TA_Imp'!$L$18:$L$1000,"1st",'Annex 4.5 TA_Imp'!$J$18:$J$1000,H11) -> 0 | I43: =COUNTIFS('Annex 4.5 TA_Imp'!$L$18:$L$1000,"1st",'Annex 4.5 TA_Imp'!$J$18:$J$1000,I11) -> 0 | J43: =COUNTIFS('Annex 4.5 TA_Imp'!$L$18:$L$1000,"1st",'Annex 4.5 TA_Imp'!$J$18:$J$1000,J11) -> 0 | K43: =COUNTIFS('Annex 4.5 TA_Imp'!$L$18:$L$1000,"1st",'Annex 4.5 TA_Imp'!$J$18:$J$1000,K11) -> 0 | L43: =COUNTIFS('Annex 4.5 TA_Imp'!$L$18:$L$1000,"1st",'Annex 4.5 TA_Imp'!$J$18:$J$1000,L11) -> 0 | M43: =COUNTIFS('Annex 4.5 TA_Imp'!$L$18:$L$1000,"1st",'Annex 4.5 TA_Imp'!$J$18:$J$1000,M11) -> 0 | ... Q43: =COUNTIFS('Annex 4.5 TA_Imp'!$L$18:$L$1000,"1st",'Annex 4.5 TA_Imp'!$J$18:$J$1000,Q11) -> 0 | R43: =SUM(F43:H43) -> 5 | S43: =SUM(I43:K43) -> 0 | T43: =SUM(L43:N43) -> 0 | U43: =SUM(O43:Q43) -> 0 | V43: =SUM(F43:Q43) -> 5 | X43: Annex 4.5 TA_Imp'!A1
C44: 5.2. No. of assistance provided: | F44: =COUNTIFS('Annex 4.5 TA_Imp'!$F$18:$F$1000,"<>",'Annex 4.5 TA_Imp'!$J$18:$J$1000,F11) -> 4 | G44: =COUNTIFS('Annex 4.5 TA_Imp'!$F$18:$F$1000,"<>",'Annex 4.5 TA_Imp'!$J$18:$J$1000,G11) -> 2 | H44: =COUNTIFS('Annex 4.5 TA_Imp'!$F$18:$F$1000,"<>",'Annex 4.5 TA_Imp'!$J$18:$J$1000,H11) -> 0 | I44: =COUNTIFS('Annex 4.5 TA_Imp'!$F$18:$F$1000,"<>",'Annex 4.5 TA_Imp'!$J$18:$J$1000,I11) -> 0 | J44: =COUNTIFS('Annex 4.5 TA_Imp'!$F$18:$F$1000,"<>",'Annex 4.5 TA_Imp'!$J$18:$J$1000,J11) -> 0 | K44: =COUNTIFS('Annex 4.5 TA_Imp'!$F$18:$F$1000,"<>",'Annex 4.5 TA_Imp'!$J$18:$J$1000,K11) -> 0 | L44: =COUNTIFS('Annex 4.5 TA_Imp'!$F$18:$F$1000,"<>",'Annex 4.5 TA_Imp'!$J$18:$J$1000,L11) -> 0 | M44: =COUNTIFS('Annex 4.5 TA_Imp'!$F$18:$F$1000,"<>",'Annex 4.5 TA_Imp'!$J$18:$J$1000,M11) -> 0 | ... Q44: =COUNTIFS('Annex 4.5 TA_Imp'!$F$18:$F$1000,"<>",'Annex 4.5 TA_Imp'!$J$18:$J$1000,Q11) -> 0 | R44: =SUM(F44:H44) -> 6 | S44: =SUM(I44:K44) -> 0 | T44: =SUM(L44:N44) -> 0 | U44: =SUM(O44:Q44) -> 0 | V44: =SUM(F44:Q44) -> 6
D45: 5.2.1. No. of planned assistance | F45: =COUNTIFS('Annex 4.5 TA_Imp'!$H$18:$H$1000,"Planned",'Annex 4.5 TA_Imp'!$J$18:$J$1000,F11) -> 0 | G45: =COUNTIFS('Annex 4.5 TA_Imp'!$H$18:$H$1000,"Planned",'Annex 4.5 TA_Imp'!$J$18:$J$1000,G11) -> 0 | H45: =COUNTIFS('Annex 4.5 TA_Imp'!$H$18:$H$1000,"Planned",'Annex 4.5 TA_Imp'!$J$18:$J$1000,H11) -> 0 | I45: =COUNTIFS('Annex 4.5 TA_Imp'!$H$18:$H$1000,"Planned",'Annex 4.5 TA_Imp'!$J$18:$J$1000,I11) -> 0 | J45: =COUNTIFS('Annex 4.5 TA_Imp'!$H$18:$H$1000,"Planned",'Annex 4.5 TA_Imp'!$J$18:$J$1000,J11) -> 0 | K45: =COUNTIFS('Annex 4.5 TA_Imp'!$H$18:$H$1000,"Planned",'Annex 4.5 TA_Imp'!$J$18:$J$1000,K11) -> 0 | L45: =COUNTIFS('Annex 4.5 TA_Imp'!$H$18:$H$1000,"Planned",'Annex 4.5 TA_Imp'!$J$18:$J$1000,L11) -> 0 | M45: =COUNTIFS('Annex 4.5 TA_Imp'!$H$18:$H$1000,"Planned",'Annex 4.5 TA_Imp'!$J$18:$J$1000,M11) -> 0 | ... Q45: =COUNTIFS('Annex 4.5 TA_Imp'!$H$18:$H$1000,"Planned",'Annex 4.5 TA_Imp'!$J$18:$J$1000,Q11) -> 0 | R45: =SUM(F45:H45) -> 0 | S45: =SUM(I45:K45) -> 0 | T45: =SUM(L45:N45) -> 0 | U45: =SUM(O45:Q45) -> 0 | V45: =SUM(F45:Q45) -> 0
D46: 5.2.2. No. of requested (by demand) assistance | F46: =COUNTIFS('Annex 4.5 TA_Imp'!$H$18:$H$1000,"Requested",'Annex 4.5 TA_Imp'!$J$18:$J$1000,F11) -> 4 | G46: =COUNTIFS('Annex 4.5 TA_Imp'!$H$18:$H$1000,"Requested",'Annex 4.5 TA_Imp'!$J$18:$J$1000,G11) -> 2 | H46: =COUNTIFS('Annex 4.5 TA_Imp'!$H$18:$H$1000,"Requested",'Annex 4.5 TA_Imp'!$J$18:$J$1000,H11) -> 0 | I46: =COUNTIFS('Annex 4.5 TA_Imp'!$H$18:$H$1000,"Requested",'Annex 4.5 TA_Imp'!$J$18:$J$1000,I11) -> 0 | J46: =COUNTIFS('Annex 4.5 TA_Imp'!$H$18:$H$1000,"Requested",'Annex 4.5 TA_Imp'!$J$18:$J$1000,J11) -> 0 | K46: =COUNTIFS('Annex 4.5 TA_Imp'!$H$18:$H$1000,"Requested",'Annex 4.5 TA_Imp'!$J$18:$J$1000,K11) -> 0 | L46: =COUNTIFS('Annex 4.5 TA_Imp'!$H$18:$H$1000,"Requested",'Annex 4.5 TA_Imp'!$J$18:$J$1000,L11) -> 0 | M46: =COUNTIFS('Annex 4.5 TA_Imp'!$H$18:$H$1000,"Requested",'Annex 4.5 TA_Imp'!$J$18:$J$1000,M11) -> 0 | ... Q46: =COUNTIFS('Annex 4.5 TA_Imp'!$H$18:$H$1000,"Requested",'Annex 4.5 TA_Imp'!$J$18:$J$1000,Q11) -> 0 | R46: =SUM(F46:H46) -> 6 | S46: =SUM(I46:K46) -> 0 | T46: =SUM(L46:N46) -> 0 | U46: =SUM(O46:Q46) -> 0 | V46: =SUM(F46:Q46) -> 6
B47: 6 | C47: Technical assistance on the formulation of urban development plans, frameworks, strategies, and projects
C48: 6.1. No. of LGUs and stakeholders assisted in the formulation of urban development plans/frameworks/strategies/projects (single counting) | E48: 1 | F48: =COUNTIFS('Annex 4.6 TA_UD'!$L$19:$L$1001,"1st",'Annex 4.6 TA_UD'!$J$19:$J$1001,F11) -> 2 | G48: =COUNTIFS('Annex 4.6 TA_UD'!$L$19:$L$1001,"1st",'Annex 4.6 TA_UD'!$J$19:$J$1001,G11) -> 1 | H48: =COUNTIFS('Annex 4.6 TA_UD'!$L$19:$L$1001,"1st",'Annex 4.6 TA_UD'!$J$19:$J$1001,H11) -> 0 | I48: =COUNTIFS('Annex 4.6 TA_UD'!$L$19:$L$1001,"1st",'Annex 4.6 TA_UD'!$J$19:$J$1001,I11) -> 0 | J48: =COUNTIFS('Annex 4.6 TA_UD'!$L$19:$L$1001,"1st",'Annex 4.6 TA_UD'!$J$19:$J$1001,J11) -> 0 | K48: =COUNTIFS('Annex 4.6 TA_UD'!$L$19:$L$1001,"1st",'Annex 4.6 TA_UD'!$J$19:$J$1001,K11) -> 0 | L48: =COUNTIFS('Annex 4.6 TA_UD'!$L$19:$L$1001,"1st",'Annex 4.6 TA_UD'!$J$19:$J$1001,L11) -> 0 | M48: =COUNTIFS('Annex 4.6 TA_UD'!$L$19:$L$1001,"1st",'Annex 4.6 TA_UD'!$J$19:$J$1001,M11) -> 0 | ... Q48: =COUNTIFS('Annex 4.6 TA_UD'!$L$19:$L$1001,"1st",'Annex 4.6 TA_UD'!$J$19:$J$1001,Q11) -> 0 | R48: =SUM(F48:H48) -> 3 | S48: =SUM(I48:K48) -> 0 | T48: =SUM(L48:N48) -> 0 | U48: =SUM(O48:Q48) -> 0 | V48: =SUM(F48:Q48) -> 3 | X48: Annex 4.6 TA_UD'!A1
D49: 6.1.1. No. of LGUs assisted (single counting): | E49: 1 | F49: =COUNTIFS('Annex 4.6 TA_UD'!$L$19:$L$1001,"1st",'Annex 4.6 TA_UD'!$C$19:$C$1001,"LGU",'Annex 4.6 TA_UD'!$J$19:$J$1001,F11) -> 2 | G49: =COUNTIFS('Annex 4.6 TA_UD'!$L$19:$L$1001,"1st",'Annex 4.6 TA_UD'!$C$19:$C$1001,"LGU",'Annex 4.6 TA_UD'!$J$19:$J$1001,G11) -> 1 | H49: =COUNTIFS('Annex 4.6 TA_UD'!$L$19:$L$1001,"1st",'Annex 4.6 TA_UD'!$C$19:$C$1001,"LGU",'Annex 4.6 TA_UD'!$J$19:$J$1001,H11) -> 0 | I49: =COUNTIFS('Annex 4.6 TA_UD'!$L$19:$L$1001,"1st",'Annex 4.6 TA_UD'!$C$19:$C$1001,"LGU",'Annex 4.6 TA_UD'!$J$19:$J$1001,I11) -> 0 | J49: =COUNTIFS('Annex 4.6 TA_UD'!$L$19:$L$1001,"1st",'Annex 4.6 TA_UD'!$C$19:$C$1001,"LGU",'Annex 4.6 TA_UD'!$J$19:$J$1001,J11) -> 0 | K49: =COUNTIFS('Annex 4.6 TA_UD'!$L$19:$L$1001,"1st",'Annex 4.6 TA_UD'!$C$19:$C$1001,"LGU",'Annex 4.6 TA_UD'!$J$19:$J$1001,K11) -> 0 | L49: =COUNTIFS('Annex 4.6 TA_UD'!$L$19:$L$1001,"1st",'Annex 4.6 TA_UD'!$C$19:$C$1001,"LGU",'Annex 4.6 TA_UD'!$J$19:$J$1001,L11) -> 0 | M49: =COUNTIFS('Annex 4.6 TA_UD'!$L$19:$L$1001,"1st",'Annex 4.6 TA_UD'!$C$19:$C$1001,"LGU",'Annex 4.6 TA_UD'!$J$19:$J$1001,M11) -> 0 | ... Q49: =COUNTIFS('Annex 4.6 TA_UD'!$L$19:$L$1001,"1st",'Annex 4.6 TA_UD'!$C$19:$C$1001,"LGU",'Annex 4.6 TA_UD'!$J$19:$J$1001,Q11) -> 0 | R49: =SUM(F49:H49) -> 3 | S49: =SUM(I49:K49) -> 0 | T49: =SUM(L49:N49) -> 0 | U49: =SUM(O49:Q49) -> 0 | V49: =SUM(F49:Q49) -> 3
C50: 6.2. No. of assistance provided: | F50: =COUNTIFS('Annex 4.6 TA_UD'!$F$19:$F$1001,"<>",'Annex 4.6 TA_UD'!$J$19:$J$1001, F11) -> 3 | G50: =COUNTIFS('Annex 4.6 TA_UD'!$F$19:$F$1001,"<>",'Annex 4.6 TA_UD'!$J$19:$J$1001, G11) -> 2 | H50: =COUNTIFS('Annex 4.6 TA_UD'!$F$19:$F$1001,"<>",'Annex 4.6 TA_UD'!$J$19:$J$1001, H11) -> 0 | I50: =COUNTIFS('Annex 4.6 TA_UD'!$F$19:$F$1001,"<>",'Annex 4.6 TA_UD'!$J$19:$J$1001, I11) -> 0 | J50: =COUNTIFS('Annex 4.6 TA_UD'!$F$19:$F$1001,"<>",'Annex 4.6 TA_UD'!$J$19:$J$1001, J11) -> 0 | K50: =COUNTIFS('Annex 4.6 TA_UD'!$F$19:$F$1001,"<>",'Annex 4.6 TA_UD'!$J$19:$J$1001, K11) -> 0 | L50: =COUNTIFS('Annex 4.6 TA_UD'!$F$19:$F$1001,"<>",'Annex 4.6 TA_UD'!$J$19:$J$1001, L11) -> 0 | M50: =COUNTIFS('Annex 4.6 TA_UD'!$F$19:$F$1001,"<>",'Annex 4.6 TA_UD'!$J$19:$J$1001, M11) -> 0 | ... Q50: =COUNTIFS('Annex 4.6 TA_UD'!$F$19:$F$1001,"<>",'Annex 4.6 TA_UD'!$J$19:$J$1001, Q11) -> 0 | R50: =SUM(F50:H50) -> 5 | S50: =SUM(I50:K50) -> 0 | T50: =SUM(L50:N50) -> 0 | U50: =SUM(O50:Q50) -> 0 | V50: =SUM(F50:Q50) -> 5
D51: 6.2.1. No. of planned assistance | F51: =COUNTIFS('Annex 4.6 TA_UD'!$H$19:$H$1001,"Planned",'Annex 4.6 TA_UD'!$J$19:$J$1001,F11) -> 1 | G51: =COUNTIFS('Annex 4.6 TA_UD'!$H$19:$H$1001,"Planned",'Annex 4.6 TA_UD'!$J$19:$J$1001,G11) -> 2 | H51: =COUNTIFS('Annex 4.6 TA_UD'!$H$19:$H$1001,"Planned",'Annex 4.6 TA_UD'!$J$19:$J$1001,H11) -> 0 | I51: =COUNTIFS('Annex 4.6 TA_UD'!$H$19:$H$1001,"Planned",'Annex 4.6 TA_UD'!$J$19:$J$1001,I11) -> 0 | J51: =COUNTIFS('Annex 4.6 TA_UD'!$H$19:$H$1001,"Planned",'Annex 4.6 TA_UD'!$J$19:$J$1001,J11) -> 0 | K51: =COUNTIFS('Annex 4.6 TA_UD'!$H$19:$H$1001,"Planned",'Annex 4.6 TA_UD'!$J$19:$J$1001,K11) -> 0 | L51: =COUNTIFS('Annex 4.6 TA_UD'!$H$19:$H$1001,"Planned",'Annex 4.6 TA_UD'!$J$19:$J$1001,L11) -> 0 | M51: =COUNTIFS('Annex 4.6 TA_UD'!$H$19:$H$1001,"Planned",'Annex 4.6 TA_UD'!$J$19:$J$1001,M11) -> 0 | ... Q51: =COUNTIFS('Annex 4.6 TA_UD'!$H$19:$H$1001,"Planned",'Annex 4.6 TA_UD'!$J$19:$J$1001,Q11) -> 0 | R51: =SUM(F51:H51) -> 3 | S51: =SUM(I51:K51) -> 0 | T51: =SUM(L51:N51) -> 0 | U51: =SUM(O51:Q51) -> 0 | V51: =SUM(F51:Q51) -> 3
D52: 6.2.2. No. of requested (by demand) assistance | F52: =COUNTIFS('Annex 4.6 TA_UD'!$H$19:$H$1001,"Requested",'Annex 4.6 TA_UD'!$J$19:$J$1001,F11) -> 2 | G52: =COUNTIFS('Annex 4.6 TA_UD'!$H$19:$H$1001,"Requested",'Annex 4.6 TA_UD'!$J$19:$J$1001,G11) -> 0 | H52: =COUNTIFS('Annex 4.6 TA_UD'!$H$19:$H$1001,"Requested",'Annex 4.6 TA_UD'!$J$19:$J$1001,H11) -> 0 | I52: =COUNTIFS('Annex 4.6 TA_UD'!$H$19:$H$1001,"Requested",'Annex 4.6 TA_UD'!$J$19:$J$1001,I11) -> 0 | J52: =COUNTIFS('Annex 4.6 TA_UD'!$H$19:$H$1001,"Requested",'Annex 4.6 TA_UD'!$J$19:$J$1001,J11) -> 0 | K52: =COUNTIFS('Annex 4.6 TA_UD'!$H$19:$H$1001,"Requested",'Annex 4.6 TA_UD'!$J$19:$J$1001,K11) -> 0 | L52: =COUNTIFS('Annex 4.6 TA_UD'!$H$19:$H$1001,"Requested",'Annex 4.6 TA_UD'!$J$19:$J$1001,L11) -> 0 | M52: =COUNTIFS('Annex 4.6 TA_UD'!$H$19:$H$1001,"Requested",'Annex 4.6 TA_UD'!$J$19:$J$1001,M11) -> 0 | ... Q52: =COUNTIFS('Annex 4.6 TA_UD'!$H$19:$H$1001,"Requested",'Annex 4.6 TA_UD'!$J$19:$J$1001,Q11) -> 0 | R52: =SUM(F52:H52) -> 2 | S52: =SUM(I52:K52) -> 0 | T52: =SUM(L52:N52) -> 0 | U52: =SUM(O52:Q52) -> 0 | V52: =SUM(F52:Q52) -> 2
B53: 7 | C53: Technical assistance on other topics related to environmental, land use and urban planning and development (e.g. EO34, LUDIP, post-disaster activities, etc.)
C54: 7.1. No. of LGUs/NGAs/NGOs/Academe assisted (single counting) | E54: 1 | F54: =COUNTIFS('Annex 4.7 TA_Others'!$J$18:$J$1007,"1st",'Annex 4.7 TA_Others'!$H$18:$H$1007,F11) -> 1 | G54: =COUNTIFS('Annex 4.7 TA_Others'!$J$18:$J$1007,"1st",'Annex 4.7 TA_Others'!$H$18:$H$1007,G11) -> 3 | H54: =COUNTIFS('Annex 4.7 TA_Others'!$J$18:$J$1007,"1st",'Annex 4.7 TA_Others'!$H$18:$H$1007,H11) -> 0 | I54: =COUNTIFS('Annex 4.7 TA_Others'!$J$18:$J$1007,"1st",'Annex 4.7 TA_Others'!$H$18:$H$1007,I11) -> 0 | J54: =COUNTIFS('Annex 4.7 TA_Others'!$J$18:$J$1007,"1st",'Annex 4.7 TA_Others'!$H$18:$H$1007,J11) -> 0 | K54: =COUNTIFS('Annex 4.7 TA_Others'!$J$18:$J$1007,"1st",'Annex 4.7 TA_Others'!$H$18:$H$1007,K11) -> 0 | L54: =COUNTIFS('Annex 4.7 TA_Others'!$J$18:$J$1007,"1st",'Annex 4.7 TA_Others'!$H$18:$H$1007,L11) -> 0 | M54: =COUNTIFS('Annex 4.7 TA_Others'!$J$18:$J$1007,"1st",'Annex 4.7 TA_Others'!$H$18:$H$1007,M11) -> 0 | ... Q54: =COUNTIFS('Annex 4.7 TA_Others'!$J$18:$J$1007,"1st",'Annex 4.7 TA_Others'!$H$18:$H$1007,Q11) -> 0 | R54: =SUM(F54:H54) -> 4 | S54: =SUM(I54:K54) -> 0 | T54: =SUM(L54:N54) -> 0 | U54: =SUM(O54:Q54) -> 0 | V54: =SUM(F54:Q54) -> 4 | X54: Annex 4.7 TA_Others'!A1
C55: 7.2. No. of assistance provided: | F55: =COUNTIFS('Annex 4.7 TA_Others'!$D$18:$D$1007,"<>",'Annex 4.7 TA_Others'!$H$18:$H$1007,F11) -> 1 | G55: =COUNTIFS('Annex 4.7 TA_Others'!$D$18:$D$1007,"<>",'Annex 4.7 TA_Others'!$H$18:$H$1007,G11) -> 3 | H55: =COUNTIFS('Annex 4.7 TA_Others'!$D$18:$D$1007,"<>",'Annex 4.7 TA_Others'!$H$18:$H$1007,H11) -> 0 | I55: =COUNTIFS('Annex 4.7 TA_Others'!$D$18:$D$1007,"<>",'Annex 4.7 TA_Others'!$H$18:$H$1007,I11) -> 0 | J55: =COUNTIFS('Annex 4.7 TA_Others'!$D$18:$D$1007,"<>",'Annex 4.7 TA_Others'!$H$18:$H$1007,J11) -> 0 | K55: =COUNTIFS('Annex 4.7 TA_Others'!$D$18:$D$1007,"<>",'Annex 4.7 TA_Others'!$H$18:$H$1007,K11) -> 0 | L55: =COUNTIFS('Annex 4.7 TA_Others'!$D$18:$D$1007,"<>",'Annex 4.7 TA_Others'!$H$18:$H$1007,L11) -> 0 | M55: =COUNTIFS('Annex 4.7 TA_Others'!$D$18:$D$1007,"<>",'Annex 4.7 TA_Others'!$H$18:$H$1007,M11) -> 0 | ... Q55: =COUNTIFS('Annex 4.7 TA_Others'!$D$18:$D$1007,"<>",'Annex 4.7 TA_Others'!$H$18:$H$1007,Q11) -> 0 | R55: =SUM(F55:H55) -> 4 | S55: =SUM(I55:K55) -> 0 | T55: =SUM(L55:N55) -> 0 | U55: =SUM(O55:Q55) -> 0 | V55: =SUM(F55:Q55) -> 4
D56: 7.2.1. No. of planned assistance | F56: =COUNTIFS('Annex 4.7 TA_Others'!$F$18:$F$1007,"Planned",'Annex 4.7 TA_Others'!$H$18:$H$1007,F11) -> 0 | G56: =COUNTIFS('Annex 4.7 TA_Others'!$F$18:$F$1007,"Planned",'Annex 4.7 TA_Others'!$H$18:$H$1007,G11) -> 0 | H56: =COUNTIFS('Annex 4.7 TA_Others'!$F$18:$F$1007,"Planned",'Annex 4.7 TA_Others'!$H$18:$H$1007,H11) -> 0 | I56: =COUNTIFS('Annex 4.7 TA_Others'!$F$18:$F$1007,"Planned",'Annex 4.7 TA_Others'!$H$18:$H$1007,I11) -> 0 | J56: =COUNTIFS('Annex 4.7 TA_Others'!$F$18:$F$1007,"Planned",'Annex 4.7 TA_Others'!$H$18:$H$1007,J11) -> 0 | K56: =COUNTIFS('Annex 4.7 TA_Others'!$F$18:$F$1007,"Planned",'Annex 4.7 TA_Others'!$H$18:$H$1007,K11) -> 0 | L56: =COUNTIFS('Annex 4.7 TA_Others'!$F$18:$F$1007,"Planned",'Annex 4.7 TA_Others'!$H$18:$H$1007,L11) -> 0 | M56: =COUNTIFS('Annex 4.7 TA_Others'!$F$18:$F$1007,"Planned",'Annex 4.7 TA_Others'!$H$18:$H$1007,M11) -> 0 | ... Q56: =COUNTIFS('Annex 4.7 TA_Others'!$F$18:$F$1007,"Planned",'Annex 4.7 TA_Others'!$H$18:$H$1007,Q11) -> 0 | R56: =SUM(F56:H56) -> 0 | S56: =SUM(I56:K56) -> 0 | T56: =SUM(L56:N56) -> 0 | U56: =SUM(O56:Q56) -> 0 | V56: =SUM(F56:Q56) -> 0
D57: 7.2.2. No. of requested (by demand) assistance | F57: =COUNTIFS('Annex 4.7 TA_Others'!$F$18:$F$1007,"Requested",'Annex 4.7 TA_Others'!$H$18:$H$1007,F11) -> 1 | G57: =COUNTIFS('Annex 4.7 TA_Others'!$F$18:$F$1007,"Requested",'Annex 4.7 TA_Others'!$H$18:$H$1007,G11) -> 3 | H57: =COUNTIFS('Annex 4.7 TA_Others'!$F$18:$F$1007,"Requested",'Annex 4.7 TA_Others'!$H$18:$H$1007,H11) -> 0 | I57: =COUNTIFS('Annex 4.7 TA_Others'!$F$18:$F$1007,"Requested",'Annex 4.7 TA_Others'!$H$18:$H$1007,I11) -> 0 | J57: =COUNTIFS('Annex 4.7 TA_Others'!$F$18:$F$1007,"Requested",'Annex 4.7 TA_Others'!$H$18:$H$1007,J11) -> 0 | K57: =COUNTIFS('Annex 4.7 TA_Others'!$F$18:$F$1007,"Requested",'Annex 4.7 TA_Others'!$H$18:$H$1007,K11) -> 0 | L57: =COUNTIFS('Annex 4.7 TA_Others'!$F$18:$F$1007,"Requested",'Annex 4.7 TA_Others'!$H$18:$H$1007,L11) -> 0 | M57: =COUNTIFS('Annex 4.7 TA_Others'!$F$18:$F$1007,"Requested",'Annex 4.7 TA_Others'!$H$18:$H$1007,M11) -> 0 | ... Q57: =COUNTIFS('Annex 4.7 TA_Others'!$F$18:$F$1007,"Requested",'Annex 4.7 TA_Others'!$H$18:$H$1007,Q11) -> 0 | R57: =SUM(F57:H57) -> 4 | S57: =SUM(I57:K57) -> 0 | T57: =SUM(L57:N57) -> 0 | U57: =SUM(O57:Q57) -> 0 | V57: =SUM(F57:Q57) -> 4
B58: Training and Capability Programs
B59: 8 | C59: Training on the preparation of CLUP and ZO
C60: (orientation, ecosystem analysis, sectoral studies, special area studies, CLUP 12-steps)
C61: 7.1. No. of LGUs trained on the preparation of CLUPs and ZOs (single counting) | E61: 10 | F61: =COUNTIFS('Annex 5.1 TR_CLUP-ZO'!$N$18:$N$1000,"1st",'Annex 5.1 TR_CLUP-ZO'!$L$18:$L$1000,F11) -> 0 | G61: =COUNTIFS('Annex 5.1 TR_CLUP-ZO'!$N$18:$N$1000,"1st",'Annex 5.1 TR_CLUP-ZO'!$L$18:$L$1000,G11) -> 2 | H61: =COUNTIFS('Annex 5.1 TR_CLUP-ZO'!$N$18:$N$1000,"1st",'Annex 5.1 TR_CLUP-ZO'!$L$18:$L$1000,H11) -> 0 | I61: =COUNTIFS('Annex 5.1 TR_CLUP-ZO'!$N$18:$N$1000,"1st",'Annex 5.1 TR_CLUP-ZO'!$L$18:$L$1000,I11) -> 0 | J61: =COUNTIFS('Annex 5.1 TR_CLUP-ZO'!$N$18:$N$1000,"1st",'Annex 5.1 TR_CLUP-ZO'!$L$18:$L$1000,J11) -> 0 | K61: =COUNTIFS('Annex 5.1 TR_CLUP-ZO'!$N$18:$N$1000,"1st",'Annex 5.1 TR_CLUP-ZO'!$L$18:$L$1000,K11) -> 0 | L61: =COUNTIFS('Annex 5.1 TR_CLUP-ZO'!$N$18:$N$1000,"1st",'Annex 5.1 TR_CLUP-ZO'!$L$18:$L$1000,L11) -> 0 | M61: =COUNTIFS('Annex 5.1 TR_CLUP-ZO'!$N$18:$N$1000,"1st",'Annex 5.1 TR_CLUP-ZO'!$L$18:$L$1000,M11) -> 0 | ... Q61: =COUNTIFS('Annex 5.1 TR_CLUP-ZO'!$N$18:$N$1000,"1st",'Annex 5.1 TR_CLUP-ZO'!$L$18:$L$1000,Q11) -> 0 | R61: =SUM(F61:H61) -> 2 | S61: =SUM(I61:K61) -> 0 | T61: =SUM(L61:N61) -> 0 | U61: =SUM(O61:Q61) -> 0 | V61: =SUM(F61:Q61) -> 2 | X61: Annex 5.1 TR_CLUP-ZO'!A1
C62: 7.2. No. of trainings on preparation of CLUPs and ZOs conducted | E62: 5 | F62: =COUNTIFS('Annex 5.1 TR_CLUP-ZO'!$D$18:$D$1000,"<>",'Annex 5.1 TR_CLUP-ZO'!$L$18:$L$1000,F11) -> 0 | G62: =COUNTIFS('Annex 5.1 TR_CLUP-ZO'!$D$18:$D$1000,"<>",'Annex 5.1 TR_CLUP-ZO'!$L$18:$L$1000,G11) -> 2 | H62: =COUNTIFS('Annex 5.1 TR_CLUP-ZO'!$D$18:$D$1000,"<>",'Annex 5.1 TR_CLUP-ZO'!$L$18:$L$1000,H11) -> 0 | I62: =COUNTIFS('Annex 5.1 TR_CLUP-ZO'!$D$18:$D$1000,"<>",'Annex 5.1 TR_CLUP-ZO'!$L$18:$L$1000,I11) -> 0 | J62: =COUNTIFS('Annex 5.1 TR_CLUP-ZO'!$D$18:$D$1000,"<>",'Annex 5.1 TR_CLUP-ZO'!$L$18:$L$1000,J11) -> 0 | K62: =COUNTIFS('Annex 5.1 TR_CLUP-ZO'!$D$18:$D$1000,"<>",'Annex 5.1 TR_CLUP-ZO'!$L$18:$L$1000,K11) -> 0 | L62: =COUNTIFS('Annex 5.1 TR_CLUP-ZO'!$D$18:$D$1000,"<>",'Annex 5.1 TR_CLUP-ZO'!$L$18:$L$1000,L11) -> 0 | M62: =COUNTIFS('Annex 5.1 TR_CLUP-ZO'!$D$18:$D$1000,"<>",'Annex 5.1 TR_CLUP-ZO'!$L$18:$L$1000,M11) -> 0 | ... Q62: =COUNTIFS('Annex 5.1 TR_CLUP-ZO'!$D$18:$D$1000,"<>",'Annex 5.1 TR_CLUP-ZO'!$L$18:$L$1000,Q11) -> 0 | R62: =SUM(F62:H62) -> 2 | S62: =SUM(I62:K62) -> 0 | T62: =SUM(L62:N62) -> 0 | U62: =SUM(O62:Q62) -> 0 | V62: =SUM(F62:Q62) -> 2
B63: 9 | C63: Training on GIS
C64: 9.1. No. of LGUs trained on GIS (single counting) | E64: 5 | F64: =COUNTIFS('Annex 5.2 TR_GIS'!$N$18:$N$996,"1st",'Annex 5.2 TR_GIS'!$L$18:$L$996,F11) -> 0 | G64: =COUNTIFS('Annex 5.2 TR_GIS'!$N$18:$N$996,"1st",'Annex 5.2 TR_GIS'!$L$18:$L$996,G11) -> 0 | H64: =COUNTIFS('Annex 5.2 TR_GIS'!$N$18:$N$996,"1st",'Annex 5.2 TR_GIS'!$L$18:$L$996,H11) -> 0 | I64: =COUNTIFS('Annex 5.2 TR_GIS'!$N$18:$N$996,"1st",'Annex 5.2 TR_GIS'!$L$18:$L$996,I11) -> 0 | J64: =COUNTIFS('Annex 5.2 TR_GIS'!$N$18:$N$996,"1st",'Annex 5.2 TR_GIS'!$L$18:$L$996,J11) -> 0 | K64: =COUNTIFS('Annex 5.2 TR_GIS'!$N$18:$N$996,"1st",'Annex 5.2 TR_GIS'!$L$18:$L$996,K11) -> 0 | L64: =COUNTIFS('Annex 5.2 TR_GIS'!$N$18:$N$996,"1st",'Annex 5.2 TR_GIS'!$L$18:$L$996,L11) -> 0 | M64: =COUNTIFS('Annex 5.2 TR_GIS'!$N$18:$N$996,"1st",'Annex 5.2 TR_GIS'!$L$18:$L$996,M11) -> 0 | ... Q64: =COUNTIFS('Annex 5.2 TR_GIS'!$N$18:$N$996,"1st",'Annex 5.2 TR_GIS'!$L$18:$L$996,Q11) -> 0 | R64: =SUM(F64:H64) -> 0 | S64: =SUM(I64:K64) -> 0 | T64: =SUM(L64:N64) -> 0 | U64: =SUM(O64:Q64) -> 0 | V64: =SUM(F64:Q64) -> 0 | X64: Annex 5.2 TR_GIS'!A1
C65: 9.2. No. of trainings on GIS conducted | E65: 1 | F65: =COUNTIFS('Annex 5.2 TR_GIS'!$D$18:$D$996,"<>",'Annex 5.2 TR_GIS'!$L$18:$L$996,F11) -> 0 | G65: =COUNTIFS('Annex 5.2 TR_GIS'!$D$18:$D$996,"<>",'Annex 5.2 TR_GIS'!$L$18:$L$996,G11) -> 0 | H65: =COUNTIFS('Annex 5.2 TR_GIS'!$D$18:$D$996,"<>",'Annex 5.2 TR_GIS'!$L$18:$L$996,H11) -> 0 | I65: =COUNTIFS('Annex 5.2 TR_GIS'!$D$18:$D$996,"<>",'Annex 5.2 TR_GIS'!$L$18:$L$996,I11) -> 0 | J65: =COUNTIFS('Annex 5.2 TR_GIS'!$D$18:$D$996,"<>",'Annex 5.2 TR_GIS'!$L$18:$L$996,J11) -> 0 | K65: =COUNTIFS('Annex 5.2 TR_GIS'!$D$18:$D$996,"<>",'Annex 5.2 TR_GIS'!$L$18:$L$996,K11) -> 0 | L65: =COUNTIFS('Annex 5.2 TR_GIS'!$D$18:$D$996,"<>",'Annex 5.2 TR_GIS'!$L$18:$L$996,L11) -> 0 | M65: =COUNTIFS('Annex 5.2 TR_GIS'!$D$18:$D$996,"<>",'Annex 5.2 TR_GIS'!$L$18:$L$996,M11) -> 0 | ... Q65: =COUNTIFS('Annex 5.2 TR_GIS'!$D$18:$D$996,"<>",'Annex 5.2 TR_GIS'!$L$18:$L$996,Q11) -> 0 | R65: =SUM(F65:H65) -> 0 | S65: =SUM(I65:K65) -> 0 | T65: =SUM(L65:N65) -> 0 | U65: =SUM(O65:Q65) -> 0 | V65: =SUM(F65:Q65) -> 0
B66: 10 | C66: Training on CDRA
C67: 10.1. No. of LGUs trained on CDRA (single counting) | E67: 5 | F67: =COUNTIFS('Annex 5.3 TR_CDRA'!$N$18:$N$998,"1st",'Annex 5.3 TR_CDRA'!$L$18:$L$998,F11) -> 0 | G67: =COUNTIFS('Annex 5.3 TR_CDRA'!$N$18:$N$998,"1st",'Annex 5.3 TR_CDRA'!$L$18:$L$998,G11) -> 0 | H67: =COUNTIFS('Annex 5.3 TR_CDRA'!$N$18:$N$998,"1st",'Annex 5.3 TR_CDRA'!$L$18:$L$998,H11) -> 0 | I67: =COUNTIFS('Annex 5.3 TR_CDRA'!$N$18:$N$998,"1st",'Annex 5.3 TR_CDRA'!$L$18:$L$998,I11) -> 0 | J67: =COUNTIFS('Annex 5.3 TR_CDRA'!$N$18:$N$998,"1st",'Annex 5.3 TR_CDRA'!$L$18:$L$998,J11) -> 0 | K67: =COUNTIFS('Annex 5.3 TR_CDRA'!$N$18:$N$998,"1st",'Annex 5.3 TR_CDRA'!$L$18:$L$998,K11) -> 0 | L67: =COUNTIFS('Annex 5.3 TR_CDRA'!$N$18:$N$998,"1st",'Annex 5.3 TR_CDRA'!$L$18:$L$998,L11) -> 0 | M67: =COUNTIFS('Annex 5.3 TR_CDRA'!$N$18:$N$998,"1st",'Annex 5.3 TR_CDRA'!$L$18:$L$998,M11) -> 0 | ... Q67: =COUNTIFS('Annex 5.3 TR_CDRA'!$N$18:$N$998,"1st",'Annex 5.3 TR_CDRA'!$L$18:$L$998,Q11) -> 0 | R67: =SUM(F67:H67) -> 0 | S67: =SUM(I67:K67) -> 0 | T67: =SUM(L67:N67) -> 0 | U67: =SUM(O67:Q67) -> 0 | V67: =SUM(F67:Q67) -> 0 | X67: Annex 5.3 TR_CDRA'!A1
C68: 10.2. No. of trainings on CDRA conducted | E68: 1 | F68: =COUNTIFS('Annex 5.3 TR_CDRA'!$D$18:$D$998,"<>",'Annex 5.3 TR_CDRA'!$L$18:$L$998,F11) -> 0 | G68: =COUNTIFS('Annex 5.3 TR_CDRA'!$D$18:$D$998,"<>",'Annex 5.3 TR_CDRA'!$L$18:$L$998,G11) -> 0 | H68: =COUNTIFS('Annex 5.3 TR_CDRA'!$D$18:$D$998,"<>",'Annex 5.3 TR_CDRA'!$L$18:$L$998,H11) -> 0 | I68: =COUNTIFS('Annex 5.3 TR_CDRA'!$D$18:$D$998,"<>",'Annex 5.3 TR_CDRA'!$L$18:$L$998,I11) -> 0 | J68: =COUNTIFS('Annex 5.3 TR_CDRA'!$D$18:$D$998,"<>",'Annex 5.3 TR_CDRA'!$L$18:$L$998,J11) -> 0 | K68: =COUNTIFS('Annex 5.3 TR_CDRA'!$D$18:$D$998,"<>",'Annex 5.3 TR_CDRA'!$L$18:$L$998,K11) -> 0 | L68: =COUNTIFS('Annex 5.3 TR_CDRA'!$D$18:$D$998,"<>",'Annex 5.3 TR_CDRA'!$L$18:$L$998,L11) -> 0 | M68: =COUNTIFS('Annex 5.3 TR_CDRA'!$D$18:$D$998,"<>",'Annex 5.3 TR_CDRA'!$L$18:$L$998,M11) -> 0 | ... Q68: =COUNTIFS('Annex 5.3 TR_CDRA'!$D$18:$D$998,"<>",'Annex 5.3 TR_CDRA'!$L$18:$L$998,Q11) -> 0 | R68: =SUM(F68:H68) -> 0 | S68: =SUM(I68:K68) -> 0 | T68: =SUM(L68:N68) -> 0 | U68: =SUM(O68:Q68) -> 0 | V68: =SUM(F68:Q68) -> 0
B69: 11 | C69: Training on CLUP Implementation, Zoning Enforcement and Monitoring
C70: 11.1. No. of LGUs trained on CLUP Implementation, Zoning Enforcement and Monitoring (single counting) | E70: 10 | F70: =COUNTIFS('Annex 5.4 TR_Imp'!$N$18:$N$1000,"1st",'Annex 5.4 TR_Imp'!$L$18:$L$1000,F11) -> 0 | G70: =COUNTIFS('Annex 5.4 TR_Imp'!$N$18:$N$1000,"1st",'Annex 5.4 TR_Imp'!$L$18:$L$1000,G11) -> 0 | H70: =COUNTIFS('Annex 5.4 TR_Imp'!$N$18:$N$1000,"1st",'Annex 5.4 TR_Imp'!$L$18:$L$1000,H11) -> 0 | I70: =COUNTIFS('Annex 5.4 TR_Imp'!$N$18:$N$1000,"1st",'Annex 5.4 TR_Imp'!$L$18:$L$1000,I11) -> 0 | J70: =COUNTIFS('Annex 5.4 TR_Imp'!$N$18:$N$1000,"1st",'Annex 5.4 TR_Imp'!$L$18:$L$1000,J11) -> 0 | K70: =COUNTIFS('Annex 5.4 TR_Imp'!$N$18:$N$1000,"1st",'Annex 5.4 TR_Imp'!$L$18:$L$1000,K11) -> 0 | L70: =COUNTIFS('Annex 5.4 TR_Imp'!$N$18:$N$1000,"1st",'Annex 5.4 TR_Imp'!$L$18:$L$1000,L11) -> 0 | M70: =COUNTIFS('Annex 5.4 TR_Imp'!$N$18:$N$1000,"1st",'Annex 5.4 TR_Imp'!$L$18:$L$1000,M11) -> 0 | ... Q70: =COUNTIFS('Annex 5.4 TR_Imp'!$N$18:$N$1000,"1st",'Annex 5.4 TR_Imp'!$L$18:$L$1000,Q11) -> 0 | R70: =SUM(F70:H70) -> 0 | S70: =SUM(I70:K70) -> 0 | T70: =SUM(L70:N70) -> 0 | U70: =SUM(O70:Q70) -> 0 | V70: =SUM(F70:Q70) -> 0 | X70: Annex 5.4 TR_Imp'!A1
C71: 11.2. No. of trainings on CLUP Implementation, Zoning Enforcement and Monitoring conducted | E71: 1 | F71: =COUNTIFS('Annex 5.4 TR_Imp'!$D$18:$D$1000,"<>",'Annex 5.4 TR_Imp'!$L$18:$L$1000,F11) -> 0 | G71: =COUNTIFS('Annex 5.4 TR_Imp'!$D$18:$D$1000,"<>",'Annex 5.4 TR_Imp'!$L$18:$L$1000,G11) -> 0 | H71: =COUNTIFS('Annex 5.4 TR_Imp'!$D$18:$D$1000,"<>",'Annex 5.4 TR_Imp'!$L$18:$L$1000,H11) -> 0 | I71: =COUNTIFS('Annex 5.4 TR_Imp'!$D$18:$D$1000,"<>",'Annex 5.4 TR_Imp'!$L$18:$L$1000,I11) -> 0 | J71: =COUNTIFS('Annex 5.4 TR_Imp'!$D$18:$D$1000,"<>",'Annex 5.4 TR_Imp'!$L$18:$L$1000,J11) -> 0 | K71: =COUNTIFS('Annex 5.4 TR_Imp'!$D$18:$D$1000,"<>",'Annex 5.4 TR_Imp'!$L$18:$L$1000,K11) -> 0 | L71: =COUNTIFS('Annex 5.4 TR_Imp'!$D$18:$D$1000,"<>",'Annex 5.4 TR_Imp'!$L$18:$L$1000,L11) -> 0 | M71: =COUNTIFS('Annex 5.4 TR_Imp'!$D$18:$D$1000,"<>",'Annex 5.4 TR_Imp'!$L$18:$L$1000,M11) -> 0 | ... Q71: =COUNTIFS('Annex 5.4 TR_Imp'!$D$18:$D$1000,"<>",'Annex 5.4 TR_Imp'!$L$18:$L$1000,Q11) -> 0 | R71: =SUM(F71:H71) -> 0 | S71: =SUM(I71:K71) -> 0 | T71: =SUM(L71:N71) -> 0 | U71: =SUM(O71:Q71) -> 0 | V71: =SUM(F71:Q71) -> 0
B72: 12 | C72: Training on CLUP Housing Sub-sector preparation
C73: 11.1. No. of LGUs trained on CLUP Housing Sub-Sector (LSP) in preparation for integration to CLUP (single counting) | E73: 3 | F73: =COUNTIFS('Annex 5.5 TR_HouSub'!$N$18:$N$999,"1st",'Annex 5.5 TR_HouSub'!$L$18:$L$999,F11) -> 0 | G73: =COUNTIFS('Annex 5.5 TR_HouSub'!$N$18:$N$999,"1st",'Annex 5.5 TR_HouSub'!$L$18:$L$999,G11) -> 0 | H73: =COUNTIFS('Annex 5.5 TR_HouSub'!$N$18:$N$999,"1st",'Annex 5.5 TR_HouSub'!$L$18:$L$999,H11) -> 0 | I73: =COUNTIFS('Annex 5.5 TR_HouSub'!$N$18:$N$999,"1st",'Annex 5.5 TR_HouSub'!$L$18:$L$999,I11) -> 0 | J73: =COUNTIFS('Annex 5.5 TR_HouSub'!$N$18:$N$999,"1st",'Annex 5.5 TR_HouSub'!$L$18:$L$999,J11) -> 0 | K73: =COUNTIFS('Annex 5.5 TR_HouSub'!$N$18:$N$999,"1st",'Annex 5.5 TR_HouSub'!$L$18:$L$999,K11) -> 0 | L73: =COUNTIFS('Annex 5.5 TR_HouSub'!$N$18:$N$999,"1st",'Annex 5.5 TR_HouSub'!$L$18:$L$999,L11) -> 0 | M73: =COUNTIFS('Annex 5.5 TR_HouSub'!$N$18:$N$999,"1st",'Annex 5.5 TR_HouSub'!$L$18:$L$999,M11) -> 0 | ... Q73: =COUNTIFS('Annex 5.5 TR_HouSub'!$N$18:$N$999,"1st",'Annex 5.5 TR_HouSub'!$L$18:$L$999,Q11) -> 0 | R73: =SUM(F73:H73) -> 0 | S73: =SUM(I73:K73) -> 0 | T73: =SUM(L73:N73) -> 0 | U73: =SUM(O73:Q73) -> 0 | V73: =SUM(F73:Q73) -> 0 | X73: Annex 5.5 TR_HouSub'!A1
C74: 11.2. No. of trainings on CLUP housing sub-sector preparation conducted | E74: 1 | F74: =COUNTIFS('Annex 5.5 TR_HouSub'!$D$18:$D$999,"<>",'Annex 5.5 TR_HouSub'!$L$18:$L$999,F11) -> 0 | G74: =COUNTIFS('Annex 5.5 TR_HouSub'!$D$18:$D$999,"<>",'Annex 5.5 TR_HouSub'!$L$18:$L$999,G11) -> 0 | H74: =COUNTIFS('Annex 5.5 TR_HouSub'!$D$18:$D$999,"<>",'Annex 5.5 TR_HouSub'!$L$18:$L$999,H11) -> 0 | I74: =COUNTIFS('Annex 5.5 TR_HouSub'!$D$18:$D$999,"<>",'Annex 5.5 TR_HouSub'!$L$18:$L$999,I11) -> 0 | J74: =COUNTIFS('Annex 5.5 TR_HouSub'!$D$18:$D$999,"<>",'Annex 5.5 TR_HouSub'!$L$18:$L$999,J11) -> 0 | K74: =COUNTIFS('Annex 5.5 TR_HouSub'!$D$18:$D$999,"<>",'Annex 5.5 TR_HouSub'!$L$18:$L$999,K11) -> 0 | L74: =COUNTIFS('Annex 5.5 TR_HouSub'!$D$18:$D$999,"<>",'Annex 5.5 TR_HouSub'!$L$18:$L$999,L11) -> 0 | M74: =COUNTIFS('Annex 5.5 TR_HouSub'!$D$18:$D$999,"<>",'Annex 5.5 TR_HouSub'!$L$18:$L$999,M11) -> 0 | ... Q74: =COUNTIFS('Annex 5.5 TR_HouSub'!$D$18:$D$999,"<>",'Annex 5.5 TR_HouSub'!$L$18:$L$999,Q11) -> 0 | R74: =SUM(F74:H74) -> 0 | S74: =SUM(I74:K74) -> 0 | T74: =SUM(L74:N74) -> 0 | U74: =SUM(O74:Q74) -> 0 | V74: =SUM(F74:Q74) -> 0
B75: 13 | C75: Training on the formulation of urban development plans, frameworks, strategies, and projects
C76: 13.1. No. of LGUs and other stakeholders trained in the formulation of urban development plans/frameworks/strategies/projects (single counting) | E76: 1 | F76: =COUNTIFS('Annex 5.6 TR_UD'!$N$19:$N$1001,"1st",'Annex 5.6 TR_UD'!$L$19:$L$1001,F11) -> 0 | G76: =COUNTIFS('Annex 5.6 TR_UD'!$N$19:$N$1001,"1st",'Annex 5.6 TR_UD'!$L$19:$L$1001,G11) -> 0 | H76: =COUNTIFS('Annex 5.6 TR_UD'!$N$19:$N$1001,"1st",'Annex 5.6 TR_UD'!$L$19:$L$1001,H11) -> 0 | I76: =COUNTIFS('Annex 5.6 TR_UD'!$N$19:$N$1001,"1st",'Annex 5.6 TR_UD'!$L$19:$L$1001,I11) -> 0 | J76: =COUNTIFS('Annex 5.6 TR_UD'!$N$19:$N$1001,"1st",'Annex 5.6 TR_UD'!$L$19:$L$1001,J11) -> 0 | K76: =COUNTIFS('Annex 5.6 TR_UD'!$N$19:$N$1001,"1st",'Annex 5.6 TR_UD'!$L$19:$L$1001,K11) -> 0 | L76: =COUNTIFS('Annex 5.6 TR_UD'!$N$19:$N$1001,"1st",'Annex 5.6 TR_UD'!$L$19:$L$1001,L11) -> 0 | M76: =COUNTIFS('Annex 5.6 TR_UD'!$N$19:$N$1001,"1st",'Annex 5.6 TR_UD'!$L$19:$L$1001,M11) -> 0 | ... Q76: =COUNTIFS('Annex 5.6 TR_UD'!$N$19:$N$1001,"1st",'Annex 5.6 TR_UD'!$L$19:$L$1001,Q11) -> 0 | R76: =SUM(F76:H76) -> 0 | S76: =SUM(I76:K76) -> 0 | T76: =SUM(L76:N76) -> 0 | U76: =SUM(O76:Q76) -> 0 | V76: =SUM(F76:Q76) -> 0 | X76: Annex 5.6 TR_UD'!A1
D77: 13.1.1. No. of LGUs trained (single counting): | E77: 1 | F77: =COUNTIFS('Annex 5.6 TR_UD'!$N$19:$N$1001,"1st",'Annex 5.6 TR_UD'!$C$19:$C$1001,"LGU",'Annex 5.6 TR_UD'!$L$19:$L$1001,F11) -> 0 | G77: =COUNTIFS('Annex 5.6 TR_UD'!$N$19:$N$1001,"1st",'Annex 5.6 TR_UD'!$C$19:$C$1001,"LGU",'Annex 5.6 TR_UD'!$L$19:$L$1001,G11) -> 0 | H77: =COUNTIFS('Annex 5.6 TR_UD'!$N$19:$N$1001,"1st",'Annex 5.6 TR_UD'!$C$19:$C$1001,"LGU",'Annex 5.6 TR_UD'!$L$19:$L$1001,H11) -> 0 | I77: =COUNTIFS('Annex 5.6 TR_UD'!$N$19:$N$1001,"1st",'Annex 5.6 TR_UD'!$C$19:$C$1001,"LGU",'Annex 5.6 TR_UD'!$L$19:$L$1001,I11) -> 0 | J77: =COUNTIFS('Annex 5.6 TR_UD'!$N$19:$N$1001,"1st",'Annex 5.6 TR_UD'!$C$19:$C$1001,"LGU",'Annex 5.6 TR_UD'!$L$19:$L$1001,J11) -> 0 | K77: =COUNTIFS('Annex 5.6 TR_UD'!$N$19:$N$1001,"1st",'Annex 5.6 TR_UD'!$C$19:$C$1001,"LGU",'Annex 5.6 TR_UD'!$L$19:$L$1001,K11) -> 0 | L77: =COUNTIFS('Annex 5.6 TR_UD'!$N$19:$N$1001,"1st",'Annex 5.6 TR_UD'!$C$19:$C$1001,"LGU",'Annex 5.6 TR_UD'!$L$19:$L$1001,L11) -> 0 | M77: =COUNTIFS('Annex 5.6 TR_UD'!$N$19:$N$1001,"1st",'Annex 5.6 TR_UD'!$C$19:$C$1001,"LGU",'Annex 5.6 TR_UD'!$L$19:$L$1001,M11) -> 0 | ... Q77: =COUNTIFS('Annex 5.6 TR_UD'!$N$19:$N$1001,"1st",'Annex 5.6 TR_UD'!$C$19:$C$1001,"LGU",'Annex 5.6 TR_UD'!$L$19:$L$1001,Q11) -> 0 | R77: =SUM(F77:H77) -> 0 | S77: =SUM(I77:K77) -> 0 | T77: =SUM(L77:N77) -> 0 | U77: =SUM(O77:Q77) -> 0 | V77: =SUM(F77:Q77) -> 0
C78: 13.2. No. of trainings on the formulation of urban development plans/frameworks/strategies/projects conducted | E78: 1 | F78: =COUNTIFS('Annex 5.6 TR_UD'!$D$19:$D$1001,"<>",'Annex 5.6 TR_UD'!$L$19:$L$1001,F11) -> 0 | G78: =COUNTIFS('Annex 5.6 TR_UD'!$D$19:$D$1001,"<>",'Annex 5.6 TR_UD'!$L$19:$L$1001,G11) -> 0 | H78: =COUNTIFS('Annex 5.6 TR_UD'!$D$19:$D$1001,"<>",'Annex 5.6 TR_UD'!$L$19:$L$1001,H11) -> 0 | I78: =COUNTIFS('Annex 5.6 TR_UD'!$D$19:$D$1001,"<>",'Annex 5.6 TR_UD'!$L$19:$L$1001,I11) -> 0 | J78: =COUNTIFS('Annex 5.6 TR_UD'!$D$19:$D$1001,"<>",'Annex 5.6 TR_UD'!$L$19:$L$1001,J11) -> 0 | K78: =COUNTIFS('Annex 5.6 TR_UD'!$D$19:$D$1001,"<>",'Annex 5.6 TR_UD'!$L$19:$L$1001,K11) -> 0 | L78: =COUNTIFS('Annex 5.6 TR_UD'!$D$19:$D$1001,"<>",'Annex 5.6 TR_UD'!$L$19:$L$1001,L11) -> 0 | M78: =COUNTIFS('Annex 5.6 TR_UD'!$D$19:$D$1001,"<>",'Annex 5.6 TR_UD'!$L$19:$L$1001,M11) -> 0 | ... Q78: =COUNTIFS('Annex 5.6 TR_UD'!$D$19:$D$1001,"<>",'Annex 5.6 TR_UD'!$L$19:$L$1001,Q11) -> 0 | R78: =SUM(F78:H78) -> 0 | S78: =SUM(I78:K78) -> 0 | T78: =SUM(L78:N78) -> 0 | U78: =SUM(O78:Q78) -> 0 | V78: =SUM(F78:Q78) -> 0
B79: 14 | C79: Other trainings (e.g. P/RLUC Review and Approval, PDPFP/PPFP Preparation, LUDIP, etc.)
C80: 14.1. No. of LGUs/NGAs/NGOs/Academe trained (single counting) | E80: 1 | F80: =COUNTIFS('Annex 5.7 TR_Others'!$N$18:$N$1000,"1st",'Annex 5.7 TR_Others'!$L$18:$L$1000,F11) -> 0 | G80: =COUNTIFS('Annex 5.7 TR_Others'!$N$18:$N$1000,"1st",'Annex 5.7 TR_Others'!$L$18:$L$1000,G11) -> 0 | H80: =COUNTIFS('Annex 5.7 TR_Others'!$N$18:$N$1000,"1st",'Annex 5.7 TR_Others'!$L$18:$L$1000,H11) -> 0 | I80: =COUNTIFS('Annex 5.7 TR_Others'!$N$18:$N$1000,"1st",'Annex 5.7 TR_Others'!$L$18:$L$1000,I11) -> 0 | J80: =COUNTIFS('Annex 5.7 TR_Others'!$N$18:$N$1000,"1st",'Annex 5.7 TR_Others'!$L$18:$L$1000,J11) -> 0 | K80: =COUNTIFS('Annex 5.7 TR_Others'!$N$18:$N$1000,"1st",'Annex 5.7 TR_Others'!$L$18:$L$1000,K11) -> 0 | L80: =COUNTIFS('Annex 5.7 TR_Others'!$N$18:$N$1000,"1st",'Annex 5.7 TR_Others'!$L$18:$L$1000,L11) -> 0 | M80: =COUNTIFS('Annex 5.7 TR_Others'!$N$18:$N$1000,"1st",'Annex 5.7 TR_Others'!$L$18:$L$1000,M11) -> 0 | ... Q80: =COUNTIFS('Annex 5.7 TR_Others'!$N$18:$N$1000,"1st",'Annex 5.7 TR_Others'!$L$18:$L$1000,Q11) -> 0 | R80: =SUM(F80:H80) -> 0 | S80: =SUM(I80:K80) -> 0 | T80: =SUM(L80:N80) -> 0 | U80: =SUM(O80:Q80) -> 0 | V80: =SUM(F80:Q80) -> 0 | X80: Annex 5.7 TR_Others'!A1
C81: 14.2. No. of other trainings conducted | E81: 1 | F81: =COUNTIFS('Annex 5.7 TR_Others'!$D$18:$D$1000,"<>",'Annex 5.7 TR_Others'!$L$18:$L$1000,F11) -> 0 | G81: =COUNTIFS('Annex 5.7 TR_Others'!$D$18:$D$1000,"<>",'Annex 5.7 TR_Others'!$L$18:$L$1000,G11) -> 0 | H81: =COUNTIFS('Annex 5.7 TR_Others'!$D$18:$D$1000,"<>",'Annex 5.7 TR_Others'!$L$18:$L$1000,H11) -> 0 | I81: =COUNTIFS('Annex 5.7 TR_Others'!$D$18:$D$1000,"<>",'Annex 5.7 TR_Others'!$L$18:$L$1000,I11) -> 0 | J81: =COUNTIFS('Annex 5.7 TR_Others'!$D$18:$D$1000,"<>",'Annex 5.7 TR_Others'!$L$18:$L$1000,J11) -> 0 | K81: =COUNTIFS('Annex 5.7 TR_Others'!$D$18:$D$1000,"<>",'Annex 5.7 TR_Others'!$L$18:$L$1000,K11) -> 0 | L81: =COUNTIFS('Annex 5.7 TR_Others'!$D$18:$D$1000,"<>",'Annex 5.7 TR_Others'!$L$18:$L$1000,L11) -> 0 | M81: =COUNTIFS('Annex 5.7 TR_Others'!$D$18:$D$1000,"<>",'Annex 5.7 TR_Others'!$L$18:$L$1000,M11) -> 0 | ... Q81: =COUNTIFS('Annex 5.7 TR_Others'!$D$18:$D$1000,"<>",'Annex 5.7 TR_Others'!$L$18:$L$1000,Q11) -> 0 | R81: =SUM(F81:H81) -> 0 | S81: =SUM(I81:K81) -> 0 | T81: =SUM(L81:N81) -> 0 | U81: =SUM(O81:Q81) -> 0 | V81: =SUM(F81:Q81) -> 0
B82: Prototyping of Urban Development Programs
B83: 15 | C83: Urban Development Programs proposal
C84: 15.1. No. of LGU and stakeholder plans for urban development, strategies, and prototypes formulated/reviewed/facilitated (through MOU/MOA) | E84: 1 | F84: =COUNTIFS('Annex 6.1 UD_FormReview'!$B$13:$B$1000,"<>",'Annex 6.1 UD_FormReview'!$G$13:$G$1000,F11) -> 0 | G84: =COUNTIFS('Annex 6.1 UD_FormReview'!$B$13:$B$1000,"<>",'Annex 6.1 UD_FormReview'!$G$13:$G$1000,G11) -> 0 | H84: =COUNTIFS('Annex 6.1 UD_FormReview'!$B$13:$B$1000,"<>",'Annex 6.1 UD_FormReview'!$G$13:$G$1000,H11) -> 0 | I84: =COUNTIFS('Annex 6.1 UD_FormReview'!$B$13:$B$1000,"<>",'Annex 6.1 UD_FormReview'!$G$13:$G$1000,I11) -> 0 | J84: =COUNTIFS('Annex 6.1 UD_FormReview'!$B$13:$B$1000,"<>",'Annex 6.1 UD_FormReview'!$G$13:$G$1000,J11) -> 0 | K84: =COUNTIFS('Annex 6.1 UD_FormReview'!$B$13:$B$1000,"<>",'Annex 6.1 UD_FormReview'!$G$13:$G$1000,K11) -> 0 | L84: =COUNTIFS('Annex 6.1 UD_FormReview'!$B$13:$B$1000,"<>",'Annex 6.1 UD_FormReview'!$G$13:$G$1000,L11) -> 0 | M84: =COUNTIFS('Annex 6.1 UD_FormReview'!$B$13:$B$1000,"<>",'Annex 6.1 UD_FormReview'!$G$13:$G$1000,M11) -> 0 | ... Q84: =COUNTIFS('Annex 6.1 UD_FormReview'!$B$13:$B$1000,"<>",'Annex 6.1 UD_FormReview'!$G$13:$G$1000,Q11) -> 0 | R84: =SUM(F84:H84) -> 0 | S84: =SUM(I84:K84) -> 0 | T84: =SUM(L84:N84) -> 0 | U84: =SUM(O84:Q84) -> 0 | V84: =SUM(F84:Q84) -> 0 | X84: Annex 6.3 UD_FormReview'!A1
D85: 15.1.1. Number of LGU and stakeholder plans facilitated (MOU/MOA) | E85: 1 | F85: =COUNTIFS('Annex 6.1 UD_FormReview'!$E$13:$E$1000,"Facilitated (MOU/MOA)", 'Annex 6.1 UD_FormReview'!$G$13:$G$1000, F11) -> 0 | G85: =COUNTIFS('Annex 6.1 UD_FormReview'!$E$13:$E$1000,"Facilitated (MOU/MOA)", 'Annex 6.1 UD_FormReview'!$G$13:$G$1000, G11) -> 0 | H85: =COUNTIFS('Annex 6.1 UD_FormReview'!$E$13:$E$1000,"Facilitated (MOU/MOA)", 'Annex 6.1 UD_FormReview'!$G$13:$G$1000, H11) -> 0 | I85: =COUNTIFS('Annex 6.1 UD_FormReview'!$E$13:$E$1000,"Facilitated (MOU/MOA)", 'Annex 6.1 UD_FormReview'!$G$13:$G$1000, I11) -> 0 | J85: =COUNTIFS('Annex 6.1 UD_FormReview'!$E$13:$E$1000,"Facilitated (MOU/MOA)", 'Annex 6.1 UD_FormReview'!$G$13:$G$1000, J11) -> 0 | K85: =COUNTIFS('Annex 6.1 UD_FormReview'!$E$13:$E$1000,"Facilitated (MOU/MOA)", 'Annex 6.1 UD_FormReview'!$G$13:$G$1000, K11) -> 0 | L85: =COUNTIFS('Annex 6.1 UD_FormReview'!$E$13:$E$1000,"Facilitated (MOU/MOA)", 'Annex 6.1 UD_FormReview'!$G$13:$G$1000, L11) -> 0 | M85: =COUNTIFS('Annex 6.1 UD_FormReview'!$E$13:$E$1000,"Facilitated (MOU/MOA)", 'Annex 6.1 UD_FormReview'!$G$13:$G$1000, M11) -> 0 | ... Q85: =COUNTIFS('Annex 6.1 UD_FormReview'!$E$13:$E$1000,"Facilitated (MOU/MOA)", 'Annex 6.1 UD_FormReview'!$G$13:$G$1000, Q11) -> 0 | R85: =SUM(F85:H85) -> 0 | S85: =SUM(I85:K85) -> 0 | T85: =SUM(L85:N85) -> 0 | U85: =SUM(O85:Q85) -> 0 | V85: =SUM(F85:Q85) -> 0
D86: 15.1.2. Number of LGU and stakeholder plans reviewed/assessed | E86: 1 | F86: =COUNTIFS('Annex 6.1 UD_FormReview'!$E$13:$E$1000,"Plan Review/Assessment", 'Annex 6.1 UD_FormReview'!$G$13:$G$1000, F11) -> 0 | G86: =COUNTIFS('Annex 6.1 UD_FormReview'!$E$13:$E$1000,"Plan Review/Assessment", 'Annex 6.1 UD_FormReview'!$G$13:$G$1000, G11) -> 0 | H86: =COUNTIFS('Annex 6.1 UD_FormReview'!$E$13:$E$1000,"Plan Review/Assessment", 'Annex 6.1 UD_FormReview'!$G$13:$G$1000, H11) -> 0 | I86: =COUNTIFS('Annex 6.1 UD_FormReview'!$E$13:$E$1000,"Plan Review/Assessment", 'Annex 6.1 UD_FormReview'!$G$13:$G$1000, I11) -> 0 | J86: =COUNTIFS('Annex 6.1 UD_FormReview'!$E$13:$E$1000,"Plan Review/Assessment", 'Annex 6.1 UD_FormReview'!$G$13:$G$1000, J11) -> 0 | K86: =COUNTIFS('Annex 6.1 UD_FormReview'!$E$13:$E$1000,"Plan Review/Assessment", 'Annex 6.1 UD_FormReview'!$G$13:$G$1000, K11) -> 0 | L86: =COUNTIFS('Annex 6.1 UD_FormReview'!$E$13:$E$1000,"Plan Review/Assessment", 'Annex 6.1 UD_FormReview'!$G$13:$G$1000, L11) -> 0 | M86: =COUNTIFS('Annex 6.1 UD_FormReview'!$E$13:$E$1000,"Plan Review/Assessment", 'Annex 6.1 UD_FormReview'!$G$13:$G$1000, M11) -> 0 | ... Q86: =COUNTIFS('Annex 6.1 UD_FormReview'!$E$13:$E$1000,"Plan Review/Assessment", 'Annex 6.1 UD_FormReview'!$G$13:$G$1000, Q11) -> 0 | R86: =SUM(F86:H86) -> 0 | S86: =SUM(I86:K86) -> 0 | T86: =SUM(L86:N86) -> 0 | U86: =SUM(O86:Q86) -> 0 | V86: =SUM(F86:Q86) -> 0
D87: 15.1.3. Number of LGU and stakeholder plans formulated | E87: 1 | F87: =COUNTIFS('Annex 6.1 UD_FormReview'!$E$13:$E$1000,"Plan Formulated", 'Annex 6.1 UD_FormReview'!$G$13:$G$1000, F11) -> 0 | G87: =COUNTIFS('Annex 6.1 UD_FormReview'!$E$13:$E$1000,"Plan Formulated", 'Annex 6.1 UD_FormReview'!$G$13:$G$1000, G11) -> 0 | H87: =COUNTIFS('Annex 6.1 UD_FormReview'!$E$13:$E$1000,"Plan Formulated", 'Annex 6.1 UD_FormReview'!$G$13:$G$1000, H11) -> 0 | I87: =COUNTIFS('Annex 6.1 UD_FormReview'!$E$13:$E$1000,"Plan Formulated", 'Annex 6.1 UD_FormReview'!$G$13:$G$1000, I11) -> 0 | J87: =COUNTIFS('Annex 6.1 UD_FormReview'!$E$13:$E$1000,"Plan Formulated", 'Annex 6.1 UD_FormReview'!$G$13:$G$1000, J11) -> 0 | K87: =COUNTIFS('Annex 6.1 UD_FormReview'!$E$13:$E$1000,"Plan Formulated", 'Annex 6.1 UD_FormReview'!$G$13:$G$1000, K11) -> 0 | L87: =COUNTIFS('Annex 6.1 UD_FormReview'!$E$13:$E$1000,"Plan Formulated", 'Annex 6.1 UD_FormReview'!$G$13:$G$1000, L11) -> 0 | M87: =COUNTIFS('Annex 6.1 UD_FormReview'!$E$13:$E$1000,"Plan Formulated", 'Annex 6.1 UD_FormReview'!$G$13:$G$1000, M11) -> 0 | ... Q87: =COUNTIFS('Annex 6.1 UD_FormReview'!$E$13:$E$1000,"Plan Formulated", 'Annex 6.1 UD_FormReview'!$G$13:$G$1000, Q11) -> 0 | R87: =SUM(F87:H87) -> 0 | S87: =SUM(I87:K87) -> 0 | T87: =SUM(L87:N87) -> 0 | U87: =SUM(O87:Q87) -> 0 | V87: =SUM(F87:Q87) -> 0
B88: Review of CLUP & ZO/PPFP
B89: 16 | C89: Completeness checking | X89: Annex 7.1 Review_CChk'!A1
C90: 16.1. No. of CLUPs checked in compliance to the documentary requirements per land-use planning standards and guidelines | E90: 5 | F90: =COUNTIFS('Annex 7.1 Review_CChk'!$D$21:$D$1004,"City / Municipality",'Annex 7.1 Review_CChk'!$L$21:$L$1004,"1st",'Annex 7.1 Review_CChk'!$J$21:$J$1004,F11) -> 0 | G90: =COUNTIFS('Annex 7.1 Review_CChk'!$D$21:$D$1004,"City / Municipality",'Annex 7.1 Review_CChk'!$L$21:$L$1004,"1st",'Annex 7.1 Review_CChk'!$J$21:$J$1004,G11) -> 1 | H90: =COUNTIFS('Annex 7.1 Review_CChk'!$D$21:$D$1004,"City / Municipality",'Annex 7.1 Review_CChk'!$L$21:$L$1004,"1st",'Annex 7.1 Review_CChk'!$J$21:$J$1004,H11) -> 0 | I90: =COUNTIFS('Annex 7.1 Review_CChk'!$D$21:$D$1004,"City / Municipality",'Annex 7.1 Review_CChk'!$L$21:$L$1004,"1st",'Annex 7.1 Review_CChk'!$J$21:$J$1004,I11) -> 0 | J90: =COUNTIFS('Annex 7.1 Review_CChk'!$D$21:$D$1004,"City / Municipality",'Annex 7.1 Review_CChk'!$L$21:$L$1004,"1st",'Annex 7.1 Review_CChk'!$J$21:$J$1004,J11) -> 0 | K90: =COUNTIFS('Annex 7.1 Review_CChk'!$D$21:$D$1004,"City / Municipality",'Annex 7.1 Review_CChk'!$L$21:$L$1004,"1st",'Annex 7.1 Review_CChk'!$J$21:$J$1004,K11) -> 0 | L90: =COUNTIFS('Annex 7.1 Review_CChk'!$D$21:$D$1004,"City / Municipality",'Annex 7.1 Review_CChk'!$L$21:$L$1004,"1st",'Annex 7.1 Review_CChk'!$J$21:$J$1004,L11) -> 0 | M90: =COUNTIFS('Annex 7.1 Review_CChk'!$D$21:$D$1004,"City / Municipality",'Annex 7.1 Review_CChk'!$L$21:$L$1004,"1st",'Annex 7.1 Review_CChk'!$J$21:$J$1004,M11) -> 0 | ... Q90: =COUNTIFS('Annex 7.1 Review_CChk'!$D$21:$D$1004,"City / Municipality",'Annex 7.1 Review_CChk'!$L$21:$L$1004,"1st",'Annex 7.1 Review_CChk'!$J$21:$J$1004,Q11) -> 0 | R90: =SUM(F90:H90) -> 1 | S90: =SUM(I90:K90) -> 0 | T90: =SUM(L90:N90) -> 0 | U90: =SUM(O90:Q90) -> 0 | V90: =SUM(F90:Q90) -> 1
C91: 16.2. No. of PDPFPs checked in compliance to the documentary requirements per land-use planning standards and guidelines | E91: 1 | F91: =COUNTIFS('Annex 7.1 Review_CChk'!$D$21:$D$1004,"PLGU",'Annex 7.1 Review_CChk'!$L$21:$L$1004,"1st",'Annex 7.1 Review_CChk'!$J$21:$J$1004,F11) -> 0 | G91: =COUNTIFS('Annex 7.1 Review_CChk'!$D$21:$D$1004,"PLGU",'Annex 7.1 Review_CChk'!$L$21:$L$1004,"1st",'Annex 7.1 Review_CChk'!$J$21:$J$1004,G11) -> 0 | H91: =COUNTIFS('Annex 7.1 Review_CChk'!$D$21:$D$1004,"PLGU",'Annex 7.1 Review_CChk'!$L$21:$L$1004,"1st",'Annex 7.1 Review_CChk'!$J$21:$J$1004,H11) -> 0 | I91: =COUNTIFS('Annex 7.1 Review_CChk'!$D$21:$D$1004,"PLGU",'Annex 7.1 Review_CChk'!$L$21:$L$1004,"1st",'Annex 7.1 Review_CChk'!$J$21:$J$1004,I11) -> 0 | J91: =COUNTIFS('Annex 7.1 Review_CChk'!$D$21:$D$1004,"PLGU",'Annex 7.1 Review_CChk'!$L$21:$L$1004,"1st",'Annex 7.1 Review_CChk'!$J$21:$J$1004,J11) -> 0 | K91: =COUNTIFS('Annex 7.1 Review_CChk'!$D$21:$D$1004,"PLGU",'Annex 7.1 Review_CChk'!$L$21:$L$1004,"1st",'Annex 7.1 Review_CChk'!$J$21:$J$1004,K11) -> 0 | L91: =COUNTIFS('Annex 7.1 Review_CChk'!$D$21:$D$1004,"PLGU",'Annex 7.1 Review_CChk'!$L$21:$L$1004,"1st",'Annex 7.1 Review_CChk'!$J$21:$J$1004,L11) -> 0 | M91: =COUNTIFS('Annex 7.1 Review_CChk'!$D$21:$D$1004,"PLGU",'Annex 7.1 Review_CChk'!$L$21:$L$1004,"1st",'Annex 7.1 Review_CChk'!$J$21:$J$1004,M11) -> 0 | ... Q91: =COUNTIFS('Annex 7.1 Review_CChk'!$D$21:$D$1004,"PLGU",'Annex 7.1 Review_CChk'!$L$21:$L$1004,"1st",'Annex 7.1 Review_CChk'!$J$21:$J$1004,Q11) -> 0 | R91: =SUM(F91:H91) -> 0 | S91: =SUM(I91:K91) -> 0 | T91: =SUM(L91:N91) -> 0 | U91: =SUM(O91:Q91) -> 0 | V91: =SUM(F91:Q91) -> 0
B92: 17 | C92: Review of CLUP and ZO
C93: 17.1. No. of CLUPs reviewed as compliant to land use planning standards and guidelines (single counting) | E93: 5 | F93: =COUNTIFS('Annex 7.2 Review_CLUP-PDPFP'!$J$23:$J$1005,"1st",'Annex 7.2 Review_CLUP-PDPFP'!$D$23:$D$1005,"CLUP",'Annex 7.2 Review_CLUP-PDPFP'!$H$23:$H$1005,F11) -> 0 | G93: =COUNTIFS('Annex 7.2 Review_CLUP-PDPFP'!$J$23:$J$1005,"1st",'Annex 7.2 Review_CLUP-PDPFP'!$D$23:$D$1005,"CLUP",'Annex 7.2 Review_CLUP-PDPFP'!$H$23:$H$1005,G11) -> 0 | H93: =COUNTIFS('Annex 7.2 Review_CLUP-PDPFP'!$J$23:$J$1005,"1st",'Annex 7.2 Review_CLUP-PDPFP'!$D$23:$D$1005,"CLUP",'Annex 7.2 Review_CLUP-PDPFP'!$H$23:$H$1005,H11) -> 0 | I93: =COUNTIFS('Annex 7.2 Review_CLUP-PDPFP'!$J$23:$J$1005,"1st",'Annex 7.2 Review_CLUP-PDPFP'!$D$23:$D$1005,"CLUP",'Annex 7.2 Review_CLUP-PDPFP'!$H$23:$H$1005,I11) -> 0 | J93: =COUNTIFS('Annex 7.2 Review_CLUP-PDPFP'!$J$23:$J$1005,"1st",'Annex 7.2 Review_CLUP-PDPFP'!$D$23:$D$1005,"CLUP",'Annex 7.2 Review_CLUP-PDPFP'!$H$23:$H$1005,J11) -> 0 | K93: =COUNTIFS('Annex 7.2 Review_CLUP-PDPFP'!$J$23:$J$1005,"1st",'Annex 7.2 Review_CLUP-PDPFP'!$D$23:$D$1005,"CLUP",'Annex 7.2 Review_CLUP-PDPFP'!$H$23:$H$1005,K11) -> 0 | L93: =COUNTIFS('Annex 7.2 Review_CLUP-PDPFP'!$J$23:$J$1005,"1st",'Annex 7.2 Review_CLUP-PDPFP'!$D$23:$D$1005,"CLUP",'Annex 7.2 Review_CLUP-PDPFP'!$H$23:$H$1005,L11) -> 0 | M93: =COUNTIFS('Annex 7.2 Review_CLUP-PDPFP'!$J$23:$J$1005,"1st",'Annex 7.2 Review_CLUP-PDPFP'!$D$23:$D$1005,"CLUP",'Annex 7.2 Review_CLUP-PDPFP'!$H$23:$H$1005,M11) -> 0 | ... Q93: =COUNTIFS('Annex 7.2 Review_CLUP-PDPFP'!$J$23:$J$1005,"1st",'Annex 7.2 Review_CLUP-PDPFP'!$D$23:$D$1005,"CLUP",'Annex 7.2 Review_CLUP-PDPFP'!$H$23:$H$1005,Q11) -> 0 | R93: =SUM(F93:H93) -> 0 | S93: =SUM(I93:K93) -> 0 | T93: =SUM(L93:N93) -> 0 | U93: =SUM(O93:Q93) -> 0 | V93: =SUM(F93:Q93) -> 0 | X93: Annex 7.2 Review_CLUP-PDPFP'!A1
C94: 17.2. No. of review reports prepared for the review of CLUP/ZO (double counting) | E94: 5 | F94: =COUNTIFS('Annex 7.3 Review_Reports'!$D$23:$D$1005,"CLUP",'Annex 7.3 Review_Reports'!$H$23:$H$1005,F11) -> 0 | G94: =COUNTIFS('Annex 7.3 Review_Reports'!$D$23:$D$1005,"CLUP",'Annex 7.3 Review_Reports'!$H$23:$H$1005,G11) -> 0 | H94: =COUNTIFS('Annex 7.3 Review_Reports'!$D$23:$D$1005,"CLUP",'Annex 7.3 Review_Reports'!$H$23:$H$1005,H11) -> 0 | I94: =COUNTIFS('Annex 7.3 Review_Reports'!$D$23:$D$1005,"CLUP",'Annex 7.3 Review_Reports'!$H$23:$H$1005,I11) -> 0 | J94: =COUNTIFS('Annex 7.3 Review_Reports'!$D$23:$D$1005,"CLUP",'Annex 7.3 Review_Reports'!$H$23:$H$1005,J11) -> 0 | K94: =COUNTIFS('Annex 7.3 Review_Reports'!$D$23:$D$1005,"CLUP",'Annex 7.3 Review_Reports'!$H$23:$H$1005,K11) -> 0 | L94: =COUNTIFS('Annex 7.3 Review_Reports'!$D$23:$D$1005,"CLUP",'Annex 7.3 Review_Reports'!$H$23:$H$1005,L11) -> 0 | M94: =COUNTIFS('Annex 7.3 Review_Reports'!$D$23:$D$1005,"CLUP",'Annex 7.3 Review_Reports'!$H$23:$H$1005,M11) -> 0 | ... Q94: =COUNTIFS('Annex 7.3 Review_Reports'!$D$23:$D$1005,"CLUP",'Annex 7.3 Review_Reports'!$H$23:$H$1005,Q11) -> 0 | R94: =SUM(F94:H94) -> 0 | S94: =SUM(I94:K94) -> 0 | T94: =SUM(L94:N94) -> 0 | U94: =SUM(O94:Q94) -> 0 | V94: =SUM(F94:Q94) -> 0 | X94: Annex 7.3 Review_Reports'!A1
C95: 17.3. No. of CLUP/ZO review meetings or sessions attended as a member of the reviewing body (double counting) | E95: VARIABLE | F95: =COUNTIFS('Annex 7.4 Review_Sessions'!$D$23:$D$1006,"CLUP",'Annex 7.4 Review_Sessions'!$H$23:$H$1006,F11) -> 0 | G95: =COUNTIFS('Annex 7.4 Review_Sessions'!$D$23:$D$1006,"CLUP",'Annex 7.4 Review_Sessions'!$H$23:$H$1006,G11) -> 0 | H95: =COUNTIFS('Annex 7.4 Review_Sessions'!$D$23:$D$1006,"CLUP",'Annex 7.4 Review_Sessions'!$H$23:$H$1006,H11) -> 0 | I95: =COUNTIFS('Annex 7.4 Review_Sessions'!$D$23:$D$1006,"CLUP",'Annex 7.4 Review_Sessions'!$H$23:$H$1006,I11) -> 0 | J95: =COUNTIFS('Annex 7.4 Review_Sessions'!$D$23:$D$1006,"CLUP",'Annex 7.4 Review_Sessions'!$H$23:$H$1006,J11) -> 0 | K95: =COUNTIFS('Annex 7.4 Review_Sessions'!$D$23:$D$1006,"CLUP",'Annex 7.4 Review_Sessions'!$H$23:$H$1006,K11) -> 0 | L95: =COUNTIFS('Annex 7.4 Review_Sessions'!$D$23:$D$1006,"CLUP",'Annex 7.4 Review_Sessions'!$H$23:$H$1006,L11) -> 0 | M95: =COUNTIFS('Annex 7.4 Review_Sessions'!$D$23:$D$1006,"CLUP",'Annex 7.4 Review_Sessions'!$H$23:$H$1006,M11) -> 0 | ... Q95: =COUNTIFS('Annex 7.4 Review_Sessions'!$D$23:$D$1006,"CLUP",'Annex 7.4 Review_Sessions'!$H$23:$H$1006,Q11) -> 0 | R95: =SUM(F95:H95) -> 0 | S95: =SUM(I95:K95) -> 0 | T95: =SUM(L95:N95) -> 0 | U95: =SUM(O95:Q95) -> 0 | V95: =SUM(F95:Q95) -> 0 | X95: Annex 7.4 Review_Sessions'!A1
B96: 18 | C96: Review of PDPFPs/PPFPs
C97: 18.1. No. of PDPFPs/PPFPs reviewed as compliant to land use planning standards and guidelines (single counting) | E97: 1 | F97: =COUNTIFS('Annex 7.2 Review_CLUP-PDPFP'!$J$23:$J$1005,"1st",'Annex 7.2 Review_CLUP-PDPFP'!$D$23:$D$1005,"PDPFP",'Annex 7.2 Review_CLUP-PDPFP'!$H$23:$H$1005,F11) -> 0 | G97: =COUNTIFS('Annex 7.2 Review_CLUP-PDPFP'!$J$23:$J$1005,"1st",'Annex 7.2 Review_CLUP-PDPFP'!$D$23:$D$1005,"PDPFP",'Annex 7.2 Review_CLUP-PDPFP'!$H$23:$H$1005,G11) -> 0 | H97: =COUNTIFS('Annex 7.2 Review_CLUP-PDPFP'!$J$23:$J$1005,"1st",'Annex 7.2 Review_CLUP-PDPFP'!$D$23:$D$1005,"PDPFP",'Annex 7.2 Review_CLUP-PDPFP'!$H$23:$H$1005,H11) -> 0 | I97: =COUNTIFS('Annex 7.2 Review_CLUP-PDPFP'!$J$23:$J$1005,"1st",'Annex 7.2 Review_CLUP-PDPFP'!$D$23:$D$1005,"PDPFP",'Annex 7.2 Review_CLUP-PDPFP'!$H$23:$H$1005,I11) -> 0 | J97: =COUNTIFS('Annex 7.2 Review_CLUP-PDPFP'!$J$23:$J$1005,"1st",'Annex 7.2 Review_CLUP-PDPFP'!$D$23:$D$1005,"PDPFP",'Annex 7.2 Review_CLUP-PDPFP'!$H$23:$H$1005,J11) -> 0 | K97: =COUNTIFS('Annex 7.2 Review_CLUP-PDPFP'!$J$23:$J$1005,"1st",'Annex 7.2 Review_CLUP-PDPFP'!$D$23:$D$1005,"PDPFP",'Annex 7.2 Review_CLUP-PDPFP'!$H$23:$H$1005,K11) -> 0 | L97: =COUNTIFS('Annex 7.2 Review_CLUP-PDPFP'!$J$23:$J$1005,"1st",'Annex 7.2 Review_CLUP-PDPFP'!$D$23:$D$1005,"PDPFP",'Annex 7.2 Review_CLUP-PDPFP'!$H$23:$H$1005,L11) -> 0 | M97: =COUNTIFS('Annex 7.2 Review_CLUP-PDPFP'!$J$23:$J$1005,"1st",'Annex 7.2 Review_CLUP-PDPFP'!$D$23:$D$1005,"PDPFP",'Annex 7.2 Review_CLUP-PDPFP'!$H$23:$H$1005,M11) -> 0 | ... Q97: =COUNTIFS('Annex 7.2 Review_CLUP-PDPFP'!$J$23:$J$1005,"1st",'Annex 7.2 Review_CLUP-PDPFP'!$D$23:$D$1005,"PDPFP",'Annex 7.2 Review_CLUP-PDPFP'!$H$23:$H$1005,Q11) -> 0 | R97: =SUM(F97:H97) -> 0 | S97: =SUM(I97:K97) -> 0 | T97: =SUM(L97:N97) -> 0 | U97: =SUM(O97:Q97) -> 0 | V97: =SUM(F97:Q97) -> 0 | X97: Annex 7.2 Review_CLUP-PDPFP'!A1
C98: 18.2. No.of review reports prepared for the review of PDPFP (double counting) | E98: 1 | F98: =COUNTIFS('Annex 7.3 Review_Reports'!$D$23:$D$1005,"PDPFP",'Annex 7.3 Review_Reports'!$H$23:$H$1005,F11) -> 0 | G98: =COUNTIFS('Annex 7.3 Review_Reports'!$D$23:$D$1005,"PDPFP",'Annex 7.3 Review_Reports'!$H$23:$H$1005,G11) -> 0 | H98: =COUNTIFS('Annex 7.3 Review_Reports'!$D$23:$D$1005,"PDPFP",'Annex 7.3 Review_Reports'!$H$23:$H$1005,H11) -> 0 | I98: =COUNTIFS('Annex 7.3 Review_Reports'!$D$23:$D$1005,"PDPFP",'Annex 7.3 Review_Reports'!$H$23:$H$1005,I11) -> 0 | J98: =COUNTIFS('Annex 7.3 Review_Reports'!$D$23:$D$1005,"PDPFP",'Annex 7.3 Review_Reports'!$H$23:$H$1005,J11) -> 0 | K98: =COUNTIFS('Annex 7.3 Review_Reports'!$D$23:$D$1005,"PDPFP",'Annex 7.3 Review_Reports'!$H$23:$H$1005,K11) -> 0 | L98: =COUNTIFS('Annex 7.3 Review_Reports'!$D$23:$D$1005,"PDPFP",'Annex 7.3 Review_Reports'!$H$23:$H$1005,L11) -> 0 | M98: =COUNTIFS('Annex 7.3 Review_Reports'!$D$23:$D$1005,"PDPFP",'Annex 7.3 Review_Reports'!$H$23:$H$1005,M11) -> 0 | ... Q98: =COUNTIFS('Annex 7.3 Review_Reports'!$D$23:$D$1005,"PDPFP",'Annex 7.3 Review_Reports'!$H$23:$H$1005,Q11) -> 0 | R98: =SUM(F98:H98) -> 0 | S98: =SUM(I98:K98) -> 0 | T98: =SUM(L98:N98) -> 0 | U98: =SUM(O98:Q98) -> 0 | V98: =SUM(F98:Q98) -> 0 | X98: Annex 7.3 Review_Reports'!A1
C99: 18.3. Number of PDPFP review meetings or sessions attended as a member of the reviewing body (double counting) | E99: 1 | F99: =COUNTIFS('Annex 7.4 Review_Sessions'!$D$23:$D$1006,"PDPFP",'Annex 7.4 Review_Sessions'!$H$23:$H$1006,F11) -> 0 | G99: =COUNTIFS('Annex 7.4 Review_Sessions'!$D$23:$D$1006,"PDPFP",'Annex 7.4 Review_Sessions'!$H$23:$H$1006,G11) -> 0 | H99: =COUNTIFS('Annex 7.4 Review_Sessions'!$D$23:$D$1006,"PDPFP",'Annex 7.4 Review_Sessions'!$H$23:$H$1006,H11) -> 0 | I99: =COUNTIFS('Annex 7.4 Review_Sessions'!$D$23:$D$1006,"PDPFP",'Annex 7.4 Review_Sessions'!$H$23:$H$1006,I11) -> 0 | J99: =COUNTIFS('Annex 7.4 Review_Sessions'!$D$23:$D$1006,"PDPFP",'Annex 7.4 Review_Sessions'!$H$23:$H$1006,J11) -> 0 | K99: =COUNTIFS('Annex 7.4 Review_Sessions'!$D$23:$D$1006,"PDPFP",'Annex 7.4 Review_Sessions'!$H$23:$H$1006,K11) -> 0 | L99: =COUNTIFS('Annex 7.4 Review_Sessions'!$D$23:$D$1006,"PDPFP",'Annex 7.4 Review_Sessions'!$H$23:$H$1006,L11) -> 0 | M99: =COUNTIFS('Annex 7.4 Review_Sessions'!$D$23:$D$1006,"PDPFP",'Annex 7.4 Review_Sessions'!$H$23:$H$1006,M11) -> 0 | ... Q99: =COUNTIFS('Annex 7.4 Review_Sessions'!$D$23:$D$1006,"PDPFP",'Annex 7.4 Review_Sessions'!$H$23:$H$1006,Q11) -> 0 | R99: =SUM(F99:H99) -> 0 | S99: =SUM(I99:K99) -> 0 | T99: =SUM(L99:N99) -> 0 | U99: =SUM(O99:Q99) -> 0 | V99: =SUM(F99:Q99) -> 0 | X99: Annex 7.4 Review_Sessions'!A1
B100: Monitoring Activities
B101: 19 | C101: CLUP & ZO/PDPFP/PPFP/LSP Preparation Status Monitoring
C102: 19.1. No. of LGUs monitored | E102: 46 | F102: =COUNTIFS('Annex 8 Plan Monitoring'!$J$21:$J$90,"1st",'Annex 8 Plan Monitoring'!$H$21:$H$90,F11) -> 0 | G102: =COUNTIFS('Annex 8 Plan Monitoring'!$J$21:$J$90,"1st",'Annex 8 Plan Monitoring'!$H$21:$H$90,G11) -> 0 | H102: =COUNTIFS('Annex 8 Plan Monitoring'!$J$21:$J$90,"1st",'Annex 8 Plan Monitoring'!$H$21:$H$90,H11) -> 0 | I102: =COUNTIFS('Annex 8 Plan Monitoring'!$J$21:$J$90,"1st",'Annex 8 Plan Monitoring'!$H$21:$H$90,I11) -> 0 | J102: =COUNTIFS('Annex 8 Plan Monitoring'!$J$21:$J$90,"1st",'Annex 8 Plan Monitoring'!$H$21:$H$90,J11) -> 0 | K102: =COUNTIFS('Annex 8 Plan Monitoring'!$J$21:$J$90,"1st",'Annex 8 Plan Monitoring'!$H$21:$H$90,K11) -> 0 | L102: =COUNTIFS('Annex 8 Plan Monitoring'!$J$21:$J$90,"1st",'Annex 8 Plan Monitoring'!$H$21:$H$90,L11) -> 0 | M102: =COUNTIFS('Annex 8 Plan Monitoring'!$J$21:$J$90,"1st",'Annex 8 Plan Monitoring'!$H$21:$H$90,M11) -> 0 | ... Q102: =COUNTIFS('Annex 8 Plan Monitoring'!$J$21:$J$90,"1st",'Annex 8 Plan Monitoring'!$H$21:$H$90,Q11) -> 0 | R102: =SUM(F102:H102) -> 0 | S102: =SUM(I102:K102) -> 0 | T102: =SUM(L102:N102) -> 0 | U102: =SUM(O102:Q102) -> 0 | V102: =SUM(F102:Q102) -> 0 | X102: Annex 8 Plan Monitoring'!A1
D103: 19.1.1. No. of table monitoring conducted | F103: =COUNTIFS('Annex 8 Plan Monitoring'!$D$21:$D$90,"Table",'Annex 8 Plan Monitoring'!$H$21:$H$90,F11) -> 14 | G103: =COUNTIFS('Annex 8 Plan Monitoring'!$D$21:$D$90,"Table",'Annex 8 Plan Monitoring'!$H$21:$H$90,G11) -> 16 | H103: =COUNTIFS('Annex 8 Plan Monitoring'!$D$21:$D$90,"Table",'Annex 8 Plan Monitoring'!$H$21:$H$90,H11) -> 0 | I103: =COUNTIFS('Annex 8 Plan Monitoring'!$D$21:$D$90,"Table",'Annex 8 Plan Monitoring'!$H$21:$H$90,I11) -> 0 | J103: =COUNTIFS('Annex 8 Plan Monitoring'!$D$21:$D$90,"Table",'Annex 8 Plan Monitoring'!$H$21:$H$90,J11) -> 0 | K103: =COUNTIFS('Annex 8 Plan Monitoring'!$D$21:$D$90,"Table",'Annex 8 Plan Monitoring'!$H$21:$H$90,K11) -> 0 | L103: =COUNTIFS('Annex 8 Plan Monitoring'!$D$21:$D$90,"Table",'Annex 8 Plan Monitoring'!$H$21:$H$90,L11) -> 0 | M103: =COUNTIFS('Annex 8 Plan Monitoring'!$D$21:$D$90,"Table",'Annex 8 Plan Monitoring'!$H$21:$H$90,M11) -> 0 | ... Q103: =COUNTIFS('Annex 8 Plan Monitoring'!$D$21:$D$90,"Table",'Annex 8 Plan Monitoring'!$H$21:$H$90,Q11) -> 0 | R103: =SUM(F103:H103) -> 30 | S103: =SUM(I103:K103) -> 0 | T103: =SUM(L103:N103) -> 0 | U103: =SUM(O103:Q103) -> 0 | V103: =SUM(F103:Q103) -> 30
D104: 19.1.2. No. of field monitoring conducted | F104: =COUNTIFS('Annex 8 Plan Monitoring'!$D$21:$D$90,"Field",'Annex 8 Plan Monitoring'!$H$21:$H$90,F11) -> 2 | G104: =COUNTIFS('Annex 8 Plan Monitoring'!$D$21:$D$90,"Field",'Annex 8 Plan Monitoring'!$H$21:$H$90,G11) -> 7 | H104: =COUNTIFS('Annex 8 Plan Monitoring'!$D$21:$D$90,"Field",'Annex 8 Plan Monitoring'!$H$21:$H$90,H11) -> 0 | I104: =COUNTIFS('Annex 8 Plan Monitoring'!$D$21:$D$90,"Field",'Annex 8 Plan Monitoring'!$H$21:$H$90,I11) -> 0 | J104: =COUNTIFS('Annex 8 Plan Monitoring'!$D$21:$D$90,"Field",'Annex 8 Plan Monitoring'!$H$21:$H$90,J11) -> 0 | K104: =COUNTIFS('Annex 8 Plan Monitoring'!$D$21:$D$90,"Field",'Annex 8 Plan Monitoring'!$H$21:$H$90,K11) -> 0 | L104: =COUNTIFS('Annex 8 Plan Monitoring'!$D$21:$D$90,"Field",'Annex 8 Plan Monitoring'!$H$21:$H$90,L11) -> 0 | M104: =COUNTIFS('Annex 8 Plan Monitoring'!$D$21:$D$90,"Field",'Annex 8 Plan Monitoring'!$H$21:$H$90,M11) -> 0 | ... Q104: =COUNTIFS('Annex 8 Plan Monitoring'!$D$21:$D$90,"Field",'Annex 8 Plan Monitoring'!$H$21:$H$90,Q11) -> 0 | R104: =SUM(F104:H104) -> 9 | S104: =SUM(I104:K104) -> 0 | T104: =SUM(L104:N104) -> 0 | U104: =SUM(O104:Q104) -> 0 | V104: =SUM(F104:Q104) -> 9
...

Sheet Annex 1.1. Outcome_CLUP
A1: OUTCOME INDICATORS | D1: Back to Summary of Accomplishments 2025
A3: 1 | B3: Formulation of sustainable and resilient human settlements plans
B4: 1.1. Number of LGUs with approved CLUPs within the year
B5: Description: Number of LGUs with Comprehensive Land Use Plans (CLUPs) officially approved by the Sangguniang Panlalawigan (SP) or DHSUD. Note: Only CLUPs approved within the year--through an SP Resolution or DHSUD Department Circular, or any other documented proof of approval as specified in the Means of Verification (MOV)--will be counted for this indicator. For CLUPs that were considered as deemed approved, resolution approving the plan will be the SB resolution endorsing/approving their CLUP and ZO. Indicate whether it is deemed approved in the remarks. Deemed approved plans should have proper documentation and justification on its status.
B6: MOVs: HUCs and ICCs - Department Circular as issued by the DHSUD CCMs - SP Resolution approving the plan or any documents (i.e., letter informing about the approval of plan from the SP, minutes of the meeting) indicating that the plan is already approved and indicating the planning period and approval date of plan
B7: Measure: Total number of LGUs with approved CLUPs within the year
B9: Total No. of Approved CLUPs: | D9: =COUNTIFS(C14:C1048576,"<>",H14:H1048576,"<>Late Reporting (previous year/s)") -> 0
A13: Region | B13: Province | C13: City/Municipality | D13: Planning Period (Start Year) | E13: Planning Period (End Year) | F13: Resolution Approving the Plan | G13: Date of Approval (MM/DD/YYYY) | H13: Reporting Month | I13: Remarks

Sheet Annex 1.1.1 Outcome_CommPlan
A1: OUTCOME INDICATORS | F1: Back to Summary of Accomplishments 2025
A3: 1 | B3: Formulation of sustainable and resilient human settlements plans
B4: 1.1.1 Number of LGUs with Comprehensive Land Use Plans (CLUPs) officially approved by the Sangguniang Panlalawigan (SP) or DHSUD, with an integrated or separately prepared CLUP Communications Plan
B5: Description: Number of LGUs with Comprehensive Land Use Plans (CLUPs) officially approved by the Sangguniang Panlalawigan (SP) or DHSUD, with an integrated or separately prepared CLUP Communications Plan
B6: MOVs: Resolution/issuance approving the plan, together with the additional section to or integrated into the approved CLUP or a separate document dedicated to the CLUP Communications Plan, ensuring the inclusion of all necessary elements, information, and content as prescribed in DHSUD D.O. No. 2022-004
B7: Measure: Total number of LGUs with approved CLUPs within the year that include an integrated, additional section, or a separate document for the CLUP Communications Plan
B9: Total No. of LGUs with Communications Plan: | D9: =COUNTA(C14:C1048576) -> 0
A13: Region | B13: Province | C13: City/Municipality | D13: Planning Period (Start Year) | E13: Planning Period (End Year) | F13: Resolution Approving the Plan | G13: Date of Approval (MM/DD/YYYY) | H13: Reporting Month | I13: Remarks

Sheet Annex 1.1.2 Outcome_Housing
A1: OUTCOME INDICATORS | J1: Back to Summary of Accomplishments 2025
A3: 1 | B3: Formulation of sustainable and resilient human settlements plans
B4: 1.1.2 Number of LGUs with approved Comprehensive Land Use Plans (CLUPs) within the year with integrated enhanced housing sub-sector (LSP)
B5: Description: Number of LGUs with enhanced housing sub-sector (LSP) integrated in their approved CLUPs within the year
B6: MOVs: Resolution or issuance approving the plan, with an enhanced housing sub-sector section with complete content based on the prescribed revised outline in Section 4 of DHSUD D.O. No. 2022-005, along with other required data and elements as stipulated in DHSUD D.C. No. 2024-011
B7: Measure: Total number of LGUs with approved CLUPs within the year with enhanced housing sub-sector or integrated LSP
B9: Total No. of LGUs with Enhanced Housing Sub-sector: | D9: =COUNTA(C14:C1048576) -> 0
A13: Region | B13: Province | C13: City/Municipality | D13: Planning Period (Start Year) | E13: Planning Period (End Year) | F13: Resolution Approving the Plan | G13: Date of Approval (MM/DD/YYYY) | H13: Reporting Month | I13: Remarks

Sheet Annex 1.2. Outcome_PDPFP
A1: OUTCOME INDICATORS | E1: Back to Summary of Accomplishments 2025
A3: 1 | B3: Formulation of sustainable and resilient human settlements plans
B4: 1.2. Number of provinces with approved PDPFPs within the year
B5: Description: Number of provinces with Provincial Development and Physical Framework Plan (PDPFPs) officially approved by the DHSUD. Note: Only PDPFPs approved within the year through the DHSUD Department Circular
B6: MOVs: DHSUD Department Circular approving the PDPFP
B7: Measure: Total number of provinces with approved PDPFPs within the year
B9: Total No. of Approved PDPFPs: | C9: =COUNTA(B14:B1048576) -> 0
A13: Region | B13: Province | C13: Planning Period (Start Year) | D13: Planning Period (End Year) | E13: Resolution Approving the Plan | F13: Date of Approval (MM/DD/YYYY) | G13: Reporting Month | H13: Remarks

Sheet Annex 2.1. Outcome_UrbanDev
A1: OUTCOME INDICATORS | C1: Back to Summary of Accomplishments 2025
A3: 2 | B3: Implementation of inclusive, safe, resilient, and sustainable urban development programs
B4: 2.1 Number of LGUs and stakeholders with approved proposals and/or budgeted programs/projects for inclusive, safe, resilient, and sustainable urban development, demonstrating adherence to DHSUD policies, standards, and guidelines
B5: Description: Number of LGUs and stakeholders with approved proposals and/or budgeted programs/projects for inclusive, safe, resilient, and sustainable urban development. This may also include EO 34 sites that has already been programmed for acquisition and/or development and those that were approved under the Green, Green, Green program of DBM.
B6: MOVs: - Issuance, resolutions, or any official documents approving the urban development program or proposals, accompanied by the corresponding proposal document. - PIP/ LDIP /AIP/annual budget of LGU indicating the budgeted urban development-related programs/projects as priority programs/project - project progress/status reports/inspection report - For EO 34 sites: MOA with LGU, groundbreaking, joint venture agreements, endorsement for presidential proclamation, documents submitted for transfer of ownership. - Status of 4PH projects involvement of ELUPDD: suitability of sites only; sites are already pre-determined (not included) - Universe: LGUs assisted in the formulation of urban development projects/plans
B7: Measure: Total number of LGUs with urban development programs or projects officially approved and allocated a budget within the year for implementation
B8: Note: Kindly merge the cells under "Program/Project Title", "Proponents, "Program Term","Approving Issuance", "Date of Approval", "Funding Agency" for LGUs under one (1) project/program.
B10: Total No. of LGUs and Stakeholders with Urban Development Programs/Projects: | C10: =COUNTIF(K14:K1000,"1st") -> 0
B13: LGU /Stakeholder (Format for LGU: Province_LGU-Name / Province of [LGU]) | C13: Program/Project Title | D13: Proponents | E13: Program Term (Timeline) | F13: Approving Issuance | G13: Date of Approval (MM/DD/YYYY) | H13: Funding Agency | I13: Reporting Month | J13: Remarks | K13: LGU Occurrence (do not edit)
K14: =IFERROR(COUNTIF($B$14:B14,B14)&CHOOSE(MIN(4,COUNTIF($B$14:B14,B14)),"st","nd","rd","th"),"")
K15: =IFERROR(COUNTIF($B$14:B15,B15)&CHOOSE(MIN(4,COUNTIF($B$14:B15,B15)),"st","nd","rd","th"),"")
K16: =IFERROR(COUNTIF($B$14:B16,B16)&CHOOSE(MIN(4,COUNTIF($B$14:B16,B16)),"st","nd","rd","th"),"")
K17: =IFERROR(COUNTIF($B$14:B17,B17)&CHOOSE(MIN(4,COUNTIF($B$14:B17,B17)),"st","nd","rd","th"),"")
K18: =IFERROR(COUNTIF($B$14:B18,B18)&CHOOSE(MIN(4,COUNTIF($B$14:B18,B18)),"st","nd","rd","th"),"")
K19: =IFERROR(COUNTIF($B$14:B19,B19)&CHOOSE(MIN(4,COUNTIF($B$14:B19,B19)),"st","nd","rd","th"),"")
K20: =IFERROR(COUNTIF($B$14:B20,B20)&CHOOSE(MIN(4,COUNTIF($B$14:B20,B20)),"st","nd","rd","th"),"")
K21: =IFERROR(COUNTIF($B$14:B21,B21)&CHOOSE(MIN(4,COUNTIF($B$14:B21,B21)),"st","nd","rd","th"),"")
K22: =IFERROR(COUNTIF($B$14:B22,B22)&CHOOSE(MIN(4,COUNTIF($B$14:B22,B22)),"st","nd","rd","th"),"")
K23: =IFERROR(COUNTIF($B$14:B23,B23)&CHOOSE(MIN(4,COUNTIF($B$14:B23,B23)),"st","nd","rd","th"),"")
K24: =IFERROR(COUNTIF($B$14:B24,B24)&CHOOSE(MIN(4,COUNTIF($B$14:B24,B24)),"st","nd","rd","th"),"")
K25: =IFERROR(COUNTIF($B$14:B25,B25)&CHOOSE(MIN(4,COUNTIF($B$14:B25,B25)),"st","nd","rd","th"),"")
... K1000: =IFERROR(COUNTIF($B$14:B1000,B1000)&CHOOSE(MIN(4,COUNTIF($B$14:B1000,B1000)),"st","nd","rd","th"),"")

Sheet Annex 3.1_CLUP Status
A1: CLUP Status | C1: Back to Summary of Accomplishments 2025
J2: Instructions: | L2: Do not edit the formula in this column
A3: Note: Please highlight LGUs with status changes for the month. | L3: Editable Column
H6: Planning Period of the Latest Approved Plan | P6: Preparation/Updating Status please put 1 | W6: Review and Approval Status please put 1
A7: PSGC | B7: City/Municipality | C7: Province | D7: Region | E7: Hierarchy of Settlements | F7: City/Municipality Class | G7: Income Classification | H7: Start Year | I7: End Year | J7: Resolution Number of the Latest Plan | K7: Day | L7: Month | M7: Year | N7: Approval date of the Latest plan MM/DD/YYYY) | O7: CLUP Status (do not edit the formula) | P7: Pre-phase | Q7: Phase 1 | R7: Phase 2 | S7: Phase 3 | T7: Phase 4 | U7: Phase 5 | V7: Preparation Status | W7: RA 1 | X7: RA 2 | Y7: RA 3 | Z7: RA 4 | AA7: RA 5 | AB7: RA 6 | AC7: RA 7 | AD7: Review and Approval Status | AE7: Technical Assistance Provided please select from drop-down list | AF7: Support from Other Institutions please select from drop-down list | AG7: LGU with Local Shelter Plan please select from drop-down list | AH7: If with Support from other institutions, Name/s of Institutions | AI7: Remarks
B8: City of Bago | C8: Negros Occidental | D8: 2013 | E8: 2023 | F8: SP R-0623 s 2014 | H8: 2013 | I8: 2023 | J8: SP R-0623 s 2014 | K8: =DAY(N8) -> 0 | L8: =MONTH(N8) -> 1 | M8: =YEAR(N8) -> 1900 | O8: =IF((I8="")=TRUE(),IF((N8="")=TRUE(),"No CLUP",IF(YEAR(NOW())-YEAR(N8)<=10,"Updated","For Updating")),IF(YEAR(NOW())-I8<=0,"Updated","For Updating")) -> For Updating | P8: 1 | Q8: 1 | R8: 1 | V8: =IF(SUM(P8:U8)=6,"Phase 5",IF(SUM(P8:U8)=5,"Phase 4",IF(SUM(P8:U8)=4,"Phase 3",IF(SUM(P8:U8)=3,"Phase 2",IF(SUM(P8:U8)=2,"Phase 1",IF(SUM(P8:U8)=1,"Prephase","None Indicated")))))) -> Phase 2 | AD8: =IF(SUM(W8:AC8)=7,"RA7",IF(SUM(W8:AC8)=6,"RA 6",IF(SUM(W8:AC8)=5,"RA 5",IF(SUM(W8:AC8)=4,"RA 4",IF(SUM(W8:AC8)=3,"RA3",IF(SUM(W8:AC8)=2,"RA 2",IF(SUM(W8:AC8)=1,"RA1","None Indicated"))))))) -> None Indicated | AE8: Trained and assisted
B9: Binalbagan | C9: Negros Occidental | D9: 2014 | E9: 2023 | F9: SP R-0045 s 2015 | H9: 2014 | I9: 2023 | J9: SP R-0045 s 2015 | K9: =DAY(N9) -> 0 | L9: =MONTH(N9) -> 1 | M9: =YEAR(N9) -> 1900 | O9: =IF((I9="")=TRUE(),IF((N9="")=TRUE(),"No CLUP",IF(YEAR(NOW())-YEAR(N9)<=10,"Updated","For Updating")),IF(YEAR(NOW())-I9<=0,"Updated","For Updating")) -> For Updating | P9: 1 | V9: =IF(SUM(P9:U9)=6,"Phase 5",IF(SUM(P9:U9)=5,"Phase 4",IF(SUM(P9:U9)=4,"Phase 3",IF(SUM(P9:U9)=3,"Phase 2",IF(SUM(P9:U9)=2,"Phase 1",IF(SUM(P9:U9)=1,"Prephase","None Indicated")))))) -> Prephase | AD9: =IF(SUM(W9:AC9)=7,"RA7",IF(SUM(W9:AC9)=6,"RA 6",IF(SUM(W9:AC9)=5,"RA 5",IF(SUM(W9:AC9)=4,"RA 4",IF(SUM(W9:AC9)=3,"RA3",IF(SUM(W9:AC9)=2,"RA 2",IF(SUM(W9:AC9)=1,"RA1","None Indicated"))))))) -> None Indicated | AE9: Trained and assisted
B10: City of Cadiz | C10: Negros Occidental | D10: 2022 | E10: 2031 | F10: SP R-0740 s. 2024 | H10: 2022 | I10: 2031 | J10: SP R-0740 s. 2024 | K10: =DAY(N10) -> 0 | L10: =MONTH(N10) -> 1 | M10: =YEAR(N10) -> 1900 | O10: =IF((I10="")=TRUE(),IF((N10="")=TRUE(),"No CLUP",IF(YEAR(NOW())-YEAR(N10)<=10,"Updated","For Updating")),IF(YEAR(NOW())-I10<=0,"Updated","For Updating")) -> Updated | V10: =IF(SUM(P10:U10)=6,"Phase 5",IF(SUM(P10:U10)=5,"Phase 4",IF(SUM(P10:U10)=4,"Phase 3",IF(SUM(P10:U10)=3,"Phase 2",IF(SUM(P10:U10)=2,"Phase 1",IF(SUM(P10:U10)=1,"Prephase","None Indicated")))))) -> None Indicated | AD10: =IF(SUM(W10:AC10)=7,"RA7",IF(SUM(W10:AC10)=6,"RA 6",IF(SUM(W10:AC10)=5,"RA 5",IF(SUM(W10:AC10)=4,"RA 4",IF(SUM(W10:AC10)=3,"RA3",IF(SUM(W10:AC10)=2,"RA 2",IF(SUM(W10:AC10)=1,"RA1","None Indicated"))))))) -> None Indicated | AE10: Trained and assisted
B11: Calatrava | C11: Negros Occidental | D11: 2000 | E11: 2009 | F11: SP R-452 | H11: 2000 | I11: 2009 | J11: SP R-452 | K11: =DAY(N11) -> 0 | L11: =MONTH(N11) -> 1 | M11: =YEAR(N11) -> 1900 | O11: =IF((I11="")=TRUE(),IF((N11="")=TRUE(),"No CLUP",IF(YEAR(NOW())-YEAR(N11)<=10,"Updated","For Updating")),IF(YEAR(NOW())-I11<=0,"Updated","For Updating")) -> For Updating | P11: 1 | Q11: 1 | R11: 1 | S11: 1 | T11: 1 | U11: 1 | V11: =IF(SUM(P11:U11)=6,"Phase 5",IF(SUM(P11:U11)=5,"Phase 4",IF(SUM(P11:U11)=4,"Phase 3",IF(SUM(P11:U11)=3,"Phase 2",IF(SUM(P11:U11)=2,"Phase 1",IF(SUM(P11:U11)=1,"Prephase","None Indicated")))))) -> Phase 5 | AD11: =IF(SUM(W11:AC11)=7,"RA7",IF(SUM(W11:AC11)=6,"RA 6",IF(SUM(W11:AC11)=5,"RA 5",IF(SUM(W11:AC11)=4,"RA 4",IF(SUM(W11:AC11)=3,"RA3",IF(SUM(W11:AC11)=2,"RA 2",IF(SUM(W11:AC11)=1,"RA1","None Indicated"))))))) -> None Indicated | AE11: Trained and assisted
B12: Candoni | C12: Negros Occidental | D12: 2000 | E12: 2010 | F12: SP R-799 | H12: 2000 | I12: 2010 | J12: SP R-799 | K12: =DAY(N12) -> 0 | L12: =MONTH(N12) -> 1 | M12: =YEAR(N12) -> 1900 | O12: =IF((I12="")=TRUE(),IF((N12="")=TRUE(),"No CLUP",IF(YEAR(NOW())-YEAR(N12)<=10,"Updated","For Updating")),IF(YEAR(NOW())-I12<=0,"Updated","For Updating")) -> For Updating | P12: 1 | V12: =IF(SUM(P12:U12)=6,"Phase 5",IF(SUM(P12:U12)=5,"Phase 4",IF(SUM(P12:U12)=4,"Phase 3",IF(SUM(P12:U12)=3,"Phase 2",IF(SUM(P12:U12)=2,"Phase 1",IF(SUM(P12:U12)=1,"Prephase","None Indicated")))))) -> Prephase | AD12: =IF(SUM(W12:AC12)=7,"RA7",IF(SUM(W12:AC12)=6,"RA 6",IF(SUM(W12:AC12)=5,"RA 5",IF(SUM(W12:AC12)=4,"RA 4",IF(SUM(W12:AC12)=3,"RA3",IF(SUM(W12:AC12)=2,"RA 2",IF(SUM(W12:AC12)=1,"RA1","None Indicated"))))))) -> None Indicated | AE12: Trained and assisted
B13: Cauayan | C13: Negros Occidental | D13: 2000 | E13: 2009 | F13: SP R-455 | H13: 2000 | I13: 2009 | J13: SP R-455 | K13: =DAY(N13) -> 0 | L13: =MONTH(N13) -> 1 | M13: =YEAR(N13) -> 1900 | O13: =IF((I13="")=TRUE(),IF((N13="")=TRUE(),"No CLUP",IF(YEAR(NOW())-YEAR(N13)<=10,"Updated","For Updating")),IF(YEAR(NOW())-I13<=0,"Updated","For Updating")) -> For Updating | P13: 1 | V13: =IF(SUM(P13:U13)=6,"Phase 5",IF(SUM(P13:U13)=5,"Phase 4",IF(SUM(P13:U13)=4,"Phase 3",IF(SUM(P13:U13)=3,"Phase 2",IF(SUM(P13:U13)=2,"Phase 1",IF(SUM(P13:U13)=1,"Prephase","None Indicated")))))) -> Prephase | AD13: =IF(SUM(W13:AC13)=7,"RA7",IF(SUM(W13:AC13)=6,"RA 6",IF(SUM(W13:AC13)=5,"RA 5",IF(SUM(W13:AC13)=4,"RA 4",IF(SUM(W13:AC13)=3,"RA3",IF(SUM(W13:AC13)=2,"RA 2",IF(SUM(W13:AC13)=1,"RA1","None Indicated"))))))) -> None Indicated | AE13: Trained and assisted
B14: Enrique B. Magalona | C14: Negros Occidental | D14: 1997 | E14: 2010 | F14: SP R-458 | H14: 1997 | I14: 2010 | J14: SP R-458 | K14: =DAY(N14) -> 0 | L14: =MONTH(N14) -> 1 | M14: =YEAR(N14) -> 1900 | O14: =IF((I14="")=TRUE(),IF((N14="")=TRUE(),"No CLUP",IF(YEAR(NOW())-YEAR(N14)<=10,"Updated","For Updating")),IF(YEAR(NOW())-I14<=0,"Updated","For Updating")) -> For Updating | P14: 1 | V14: =IF(SUM(P14:U14)=6,"Phase 5",IF(SUM(P14:U14)=5,"Phase 4",IF(SUM(P14:U14)=4,"Phase 3",IF(SUM(P14:U14)=3,"Phase 2",IF(SUM(P14:U14)=2,"Phase 1",IF(SUM(P14:U14)=1,"Prephase","None Indicated")))))) -> Prephase | AD14: =IF(SUM(W14:AC14)=7,"RA7",IF(SUM(W14:AC14)=6,"RA 6",IF(SUM(W14:AC14)=5,"RA 5",IF(SUM(W14:AC14)=4,"RA 4",IF(SUM(W14:AC14)=3,"RA3",IF(SUM(W14:AC14)=2,"RA 2",IF(SUM(W14:AC14)=1,"RA1","None Indicated"))))))) -> None Indicated | AE14: Trained and assisted
B15: City of Escalante | C15: Negros Occidental | D15: 2000 | E15: 2009 | F15: SP R-912 | H15: 2000 | I15: 2009 | J15: SP R-912 | K15: =DAY(N15) -> 0 | L15: =MONTH(N15) -> 1 | M15: =YEAR(N15) -> 1900 | O15: =IF((I15="")=TRUE(),IF((N15="")=TRUE(),"No CLUP",IF(YEAR(NOW())-YEAR(N15)<=10,"Updated","For Updating")),IF(YEAR(NOW())-I15<=0,"Updated","For Updating")) -> For Updating | P15: 1 | V15: =IF(SUM(P15:U15)=6,"Phase 5",IF(SUM(P15:U15)=5,"Phase 4",IF(SUM(P15:U15)=4,"Phase 3",IF(SUM(P15:U15)=3,"Phase 2",IF(SUM(P15:U15)=2,"Phase 1",IF(SUM(P15:U15)=1,"Prephase","None Indicated")))))) -> Prephase | AD15: =IF(SUM(W15:AC15)=7,"RA7",IF(SUM(W15:AC15)=6,"RA 6",IF(SUM(W15:AC15)=5,"RA 5",IF(SUM(W15:AC15)=4,"RA 4",IF(SUM(W15:AC15)=3,"RA3",IF(SUM(W15:AC15)=2,"RA 2",IF(SUM(W15:AC15)=1,"RA1","None Indicated"))))))) -> None Indicated | AE15: Trained and assisted
B16: City of Himamaylan | C16: Negros Occidental | D16: 2022 | E16: 2032 | F16: SP R-0681 s. 2024 | H16: 2022 | I16: 2032 | J16: SP R-0681 s. 2024 | K16: =DAY(N16) -> 0 | L16: =MONTH(N16) -> 1 | M16: =YEAR(N16) -> 1900 | O16: =IF((I16="")=TRUE(),IF((N16="")=TRUE(),"No CLUP",IF(YEAR(NOW())-YEAR(N16)<=10,"Updated","For Updating")),IF(YEAR(NOW())-I16<=0,"Updated","For Updating")) -> Updated | V16: =IF(SUM(P16:U16)=6,"Phase 5",IF(SUM(P16:U16)=5,"Phase 4",IF(SUM(P16:U16)=4,"Phase 3",IF(SUM(P16:U16)=3,"Phase 2",IF(SUM(P16:U16)=2,"Phase 1",IF(SUM(P16:U16)=1,"Prephase","None Indicated")))))) -> None Indicated | AD16: =IF(SUM(W16:AC16)=7,"RA7",IF(SUM(W16:AC16)=6,"RA 6",IF(SUM(W16:AC16)=5,"RA 5",IF(SUM(W16:AC16)=4,"RA 4",IF(SUM(W16:AC16)=3,"RA3",IF(SUM(W16:AC16)=2,"RA 2",IF(SUM(W16:AC16)=1,"RA1","None Indicated"))))))) -> None Indicated | AE16: Assisted
B17: Hinigaran | C17: Negros Occidental | D17: 2000 | E17: 2009 | F17: SP R-823 | H17: 2000 | I17: 2009 | J17: SP R-823 | K17: =DAY(N17) -> 0 | L17: =MONTH(N17) -> 1 | M17: =YEAR(N17) -> 1900 | O17: =IF((I17="")=TRUE(),IF((N17="")=TRUE(),"No CLUP",IF(YEAR(NOW())-YEAR(N17)<=10,"Updated","For Updating")),IF(YEAR(NOW())-I17<=0,"Updated","For Updating")) -> For Updating | P17: 1 | Q17: 1 | R17: 1 | S17: 1 | T17: 1 | U17: 1 | V17: =IF(SUM(P17:U17)=6,"Phase 5",IF(SUM(P17:U17)=5,"Phase 4",IF(SUM(P17:U17)=4,"Phase 3",IF(SUM(P17:U17)=3,"Phase 2",IF(SUM(P17:U17)=2,"Phase 1",IF(SUM(P17:U17)=1,"Prephase","None Indicated")))))) -> Phase 5 | W17: 1 | X17: 1 | Y17: 1 | AD17: =IF(SUM(W17:AC17)=7,"RA7",IF(SUM(W17:AC17)=6,"RA 6",IF(SUM(W17:AC17)=5,"RA 5",IF(SUM(W17:AC17)=4,"RA 4",IF(SUM(W17:AC17)=3,"RA3",IF(SUM(W17:AC17)=2,"RA 2",IF(SUM(W17:AC17)=1,"RA1","None Indicated"))))))) -> RA3 | AE17: Trained and assisted
B18: Hinoba-an | C18: Negros Occidental | D18: 2020 | E18: 2030 | F18: SP R-0149 | H18: 2020 | I18: 2030 | J18: SP R-0149 | K18: =DAY(N18) -> 0 | L18: =MONTH(N18) -> 1 | M18: =YEAR(N18) -> 1900 | O18: =IF((I18="")=TRUE(),IF((N18="")=TRUE(),"No CLUP",IF(YEAR(NOW())-YEAR(N18)<=10,"Updated","For Updating")),IF(YEAR(NOW())-I18<=0,"Updated","For Updating")) -> Updated | V18: =IF(SUM(P18:U18)=6,"Phase 5",IF(SUM(P18:U18)=5,"Phase 4",IF(SUM(P18:U18)=4,"Phase 3",IF(SUM(P18:U18)=3,"Phase 2",IF(SUM(P18:U18)=2,"Phase 1",IF(SUM(P18:U18)=1,"Prephase","None Indicated")))))) -> None Indicated | AD18: =IF(SUM(W18:AC18)=7,"RA7",IF(SUM(W18:AC18)=6,"RA 6",IF(SUM(W18:AC18)=5,"RA 5",IF(SUM(W18:AC18)=4,"RA 4",IF(SUM(W18:AC18)=3,"RA3",IF(SUM(W18:AC18)=2,"RA 2",IF(SUM(W18:AC18)=1,"RA1","None Indicated"))))))) -> None Indicated | AE18: Trained and assisted
B19: Ilog | C19: Negros Occidental | D19: 2000 | E19: 2010 | F19: SP R-104 | H19: 2000 | I19: 2010 | J19: SP R-104 | K19: =DAY(N19) -> 0 | L19: =MONTH(N19) -> 1 | M19: =YEAR(N19) -> 1900 | O19: =IF((I19="")=TRUE(),IF((N19="")=TRUE(),"No CLUP",IF(YEAR(NOW())-YEAR(N19)<=10,"Updated","For Updating")),IF(YEAR(NOW())-I19<=0,"Updated","For Updating")) -> For Updating | P19: 1 | Q19: 1 | R19: 1 | S19: 1 | T19: 1 | U19: 1 | V19: =IF(SUM(P19:U19)=6,"Phase 5",IF(SUM(P19:U19)=5,"Phase 4",IF(SUM(P19:U19)=4,"Phase 3",IF(SUM(P19:U19)=3,"Phase 2",IF(SUM(P19:U19)=2,"Phase 1",IF(SUM(P19:U19)=1,"Prephase","None Indicated")))))) -> Phase 5 | W19: 1 | X19: 1 | Y19: 1 | AD19: =IF(SUM(W19:AC19)=7,"RA7",IF(SUM(W19:AC19)=6,"RA 6",IF(SUM(W19:AC19)=5,"RA 5",IF(SUM(W19:AC19)=4,"RA 4",IF(SUM(W19:AC19)=3,"RA3",IF(SUM(W19:AC19)=2,"RA 2",IF(SUM(W19:AC19)=1,"RA1","None Indicated"))))))) -> RA3 | AE19: Trained and assisted
B20: Isabela | C20: Negros Occidental | D20: 2005 | E20: 2010 | F20: SP R-0946 | H20: 2005 | I20: 2010 | J20: SP R-0946 | K20: =DAY(N20) -> 0 | L20: =MONTH(N20) -> 1 | M20: =YEAR(N20) -> 1900 | O20: =IF((I20="")=TRUE(),IF((N20="")=TRUE(),"No CLUP",IF(YEAR(NOW())-YEAR(N20)<=10,"Updated","For Updating")),IF(YEAR(NOW())-I20<=0,"Updated","For Updating")) -> For Updating | P20: 1 | V20: =IF(SUM(P20:U20)=6,"Phase 5",IF(SUM(P20:U20)=5,"Phase 4",IF(SUM(P20:U20)=4,"Phase 3",IF(SUM(P20:U20)=3,"Phase 2",IF(SUM(P20:U20)=2,"Phase 1",IF(SUM(P20:U20)=1,"Prephase","None Indicated")))))) -> Prephase | AD20: =IF(SUM(W20:AC20)=7,"RA7",IF(SUM(W20:AC20)=6,"RA 6",IF(SUM(W20:AC20)=5,"RA 5",IF(SUM(W20:AC20)=4,"RA 4",IF(SUM(W20:AC20)=3,"RA3",IF(SUM(W20:AC20)=2,"RA 2",IF(SUM(W20:AC20)=1,"RA1","None Indicated"))))))) -> None Indicated | AE20: Trained and assisted
B21: City of Kabankalan | C21: Negros Occidental | D21: 2018 | E21: 2027 | F21: SP R-1065 | H21: 2018 | I21: 2027 | J21: SP R-1065 | K21: =DAY(N21) -> 0 | L21: =MONTH(N21) -> 1 | M21: =YEAR(N21) -> 1900 | O21: =IF((I21="")=TRUE(),IF((N21="")=TRUE(),"No CLUP",IF(YEAR(NOW())-YEAR(N21)<=10,"Updated","For Updating")),IF(YEAR(NOW())-I21<=0,"Updated","For Updating")) -> Updated | V21: =IF(SUM(P21:U21)=6,"Phase 5",IF(SUM(P21:U21)=5,"Phase 4",IF(SUM(P21:U21)=4,"Phase 3",IF(SUM(P21:U21)=3,"Phase 2",IF(SUM(P21:U21)=2,"Phase 1",IF(SUM(P21:U21)=1,"Prephase","None Indicated")))))) -> None Indicated | AD21: =IF(SUM(W21:AC21)=7,"RA7",IF(SUM(W21:AC21)=6,"RA 6",IF(SUM(W21:AC21)=5,"RA 5",IF(SUM(W21:AC21)=4,"RA 4",IF(SUM(W21:AC21)=3,"RA3",IF(SUM(W21:AC21)=2,"RA 2",IF(SUM(W21:AC21)=1,"RA1","None Indicated"))))))) -> None Indicated | AE21: Trained and assisted
B22: City of La Carlota | C22: Negros Occidental | D22: 2013 | E22: 2022 | F22: SP R-0391 s 2013 | H22: 2013 | I22: 2022 | J22: SP R-0391 s 2013 | K22: =DAY(N22) -> 0 | L22: =MONTH(N22) -> 1 | M22: =YEAR(N22) -> 1900 | O22: =IF((I22="")=TRUE(),IF((N22="")=TRUE(),"No CLUP",IF(YEAR(NOW())-YEAR(N22)<=10,"Updated","For Updating")),IF(YEAR(NOW())-I22<=0,"Updated","For Updating")) -> For Updating | P22: 1 | V22: =IF(SUM(P22:U22)=6,"Phase 5",IF(SUM(P22:U22)=5,"Phase 4",IF(SUM(P22:U22)=4,"Phase 3",IF(SUM(P22:U22)=3,"Phase 2",IF(SUM(P22:U22)=2,"Phase 1",IF(SUM(P22:U22)=1,"Prephase","None Indicated")))))) -> Prephase | AD22: =IF(SUM(W22:AC22)=7,"RA7",IF(SUM(W22:AC22)=6,"RA 6",IF(SUM(W22:AC22)=5,"RA 5",IF(SUM(W22:AC22)=4,"RA 4",IF(SUM(W22:AC22)=3,"RA3",IF(SUM(W22:AC22)=2,"RA 2",IF(SUM(W22:AC22)=1,"RA1","None Indicated"))))))) -> None Indicated | AE22: Trained and assisted
B23: La Castellana | C23: Negros Occidental | D23: 1995 | E23: 2025 | F23: SP R-822 | H23: 1995 | I23: 2025 | J23: SP R-822 | K23: 13 | L23: 1 | M23: 2021 | O23: =IF((I23="")=TRUE(),IF((N23="")=TRUE(),"No CLUP",IF(YEAR(NOW())-YEAR(N23)<=10,"Updated","For Updating")),IF(YEAR(NOW())-I23<=0,"Updated","For Updating")) -> For Updating | P23: 1 | V23: =IF(SUM(P23:U23)=6,"Phase 5",IF(SUM(P23:U23)=5,"Phase 4",IF(SUM(P23:U23)=4,"Phase 3",IF(SUM(P23:U23)=3,"Phase 2",IF(SUM(P23:U23)=2,"Phase 1",IF(SUM(P23:U23)=1,"Prephase","None Indicated")))))) -> Prephase | AD23: =IF(SUM(W23:AC23)=7,"RA7",IF(SUM(W23:AC23)=6,"RA 6",IF(SUM(W23:AC23)=5,"RA 5",IF(SUM(W23:AC23)=4,"RA 4",IF(SUM(W23:AC23)=3,"RA3",IF(SUM(W23:AC23)=2,"RA 2",IF(SUM(W23:AC23)=1,"RA1","None Indicated"))))))) -> None Indicated | AE23: Trained and assisted
B24: Manapla | C24: Negros Occidental | D24: 2013 | E24: 2022 | F24: SP R-0718 s 2014 | H24: 2013 | I24: 2022 | J24: SP R-0718 s 2014 | K24: =DAY(N24) -> 0 | L24: =MONTH(N24) -> 1 | M24: =YEAR(N24) -> 1900 | O24: =IF((I24="")=TRUE(),IF((N24="")=TRUE(),"No CLUP",IF(YEAR(NOW())-YEAR(N24)<=10,"Updated","For Updating")),IF(YEAR(NOW())-I24<=0,"Updated","For Updating")) -> For Updating | P24: 1 | Q24: 1 | V24: =IF(SUM(P24:U24)=6,"Phase 5",IF(SUM(P24:U24)=5,"Phase 4",IF(SUM(P24:U24)=4,"Phase 3",IF(SUM(P24:U24)=3,"Phase 2",IF(SUM(P24:U24)=2,"Phase 1",IF(SUM(P24:U24)=1,"Prephase","None Indicated")))))) -> Phase 1 | AD24: =IF(SUM(W24:AC24)=7,"RA7",IF(SUM(W24:AC24)=6,"RA 6",IF(SUM(W24:AC24)=5,"RA 5",IF(SUM(W24:AC24)=4,"RA 4",IF(SUM(W24:AC24)=3,"RA3",IF(SUM(W24:AC24)=2,"RA 2",IF(SUM(W24:AC24)=1,"RA1","None Indicated"))))))) -> None Indicated | AE24: Trained and assisted
B25: Moises Padilla | C25: Negros Occidental | D25: 2000 | E25: 2010 | F25: SP R-960 | H25: 2000 | I25: 2010 | J25: SP R-960 | K25: =DAY(N25) -> 0 | L25: =MONTH(N25) -> 1 | M25: =YEAR(N25) -> 1900 | O25: =IF((I25="")=TRUE(),IF((N25="")=TRUE(),"No CLUP",IF(YEAR(NOW())-YEAR(N25)<=10,"Updated","For Updating")),IF(YEAR(NOW())-I25<=0,"Updated","For Updating")) -> For Updating | P25: 1 | Q25: 1 | V25: =IF(SUM(P25:U25)=6,"Phase 5",IF(SUM(P25:U25)=5,"Phase 4",IF(SUM(P25:U25)=4,"Phase 3",IF(SUM(P25:U25)=3,"Phase 2",IF(SUM(P25:U25)=2,"Phase 1",IF(SUM(P25:U25)=1,"Prephase","None Indicated")))))) -> Phase 1 | AD25: =IF(SUM(W25:AC25)=7,"RA7",IF(SUM(W25:AC25)=6,"RA 6",IF(SUM(W25:AC25)=5,"RA 5",IF(SUM(W25:AC25)=4,"RA 4",IF(SUM(W25:AC25)=3,"RA3",IF(SUM(W25:AC25)=2,"RA 2",IF(SUM(W25:AC25)=1,"RA1","None Indicated"))))))) -> None Indicated | AE25: Trained and assisted
B26: Murcia | C26: Negros Occidental | D26: 2001 | E26: 2010 | F26: SP R-671 | H26: 2001 | I26: 2010 | J26: SP R-671 | K26: =DAY(N26) -> 0 | L26: =MONTH(N26) -> 1 | M26: =YEAR(N26) -> 1900 | O26: =IF((I26="")=TRUE(),IF((N26="")=TRUE(),"No CLUP",IF(YEAR(NOW())-YEAR(N26)<=10,"Updated","For Updating")),IF(YEAR(NOW())-I26<=0,"Updated","For Updating")) -> For Updating | P26: 1 | Q26: 1 | R26: 1 | S26: 1 | T26: 1 | U26: 1 | V26: =IF(SUM(P26:U26)=6,"Phase 5",IF(SUM(P26:U26)=5,"Phase 4",IF(SUM(P26:U26)=4,"Phase 3",IF(SUM(P26:U26)=3,"Phase 2",IF(SUM(P26:U26)=2,"Phase 1",IF(SUM(P26:U26)=1,"Prephase","None Indicated")))))) -> Phase 5 | W26: 1 | X26: 1 | Y26: 1 | AD26: =IF(SUM(W26:AC26)=7,"RA7",IF(SUM(W26:AC26)=6,"RA 6",IF(SUM(W26:AC26)=5,"RA 5",IF(SUM(W26:AC26)=4,"RA 4",IF(SUM(W26:AC26)=3,"RA3",IF(SUM(W26:AC26)=2,"RA 2",IF(SUM(W26:AC26)=1,"RA1","None Indicated"))))))) -> RA3 | AE26: Trained and assisted
B27: Pontevedra | C27: Negros Occidental | D27: 1999 | E27: 2009 | F27: SP R-918 | H27: 1999 | I27: 2009 | J27: SP R-918 | K27: =DAY(N27) -> 0 | L27: =MONTH(N27) -> 1 | M27: =YEAR(N27) -> 1900 | O27: =IF((I27="")=TRUE(),IF((N27="")=TRUE(),"No CLUP",IF(YEAR(NOW())-YEAR(N27)<=10,"Updated","For Updating")),IF(YEAR(NOW())-I27<=0,"Updated","For Updating")) -> For Updating | P27: 1 | V27: =IF(SUM(P27:U27)=6,"Phase 5",IF(SUM(P27:U27)=5,"Phase 4",IF(SUM(P27:U27)=4,"Phase 3",IF(SUM(P27:U27)=3,"Phase 2",IF(SUM(P27:U27)=2,"Phase 1",IF(SUM(P27:U27)=1,"Prephase","None Indicated")))))) -> Prephase | AD27: =IF(SUM(W27:AC27)=7,"RA7",IF(SUM(W27:AC27)=6,"RA 6",IF(SUM(W27:AC27)=5,"RA 5",IF(SUM(W27:AC27)=4,"RA 4",IF(SUM(W27:AC27)=3,"RA3",IF(SUM(W27:AC27)=2,"RA 2",IF(SUM(W27:AC27)=1,"RA1","None Indicated"))))))) -> None Indicated | AE27: Trained and assisted
B28: Pulupandan | C28: Negros Occidental | D28: 2000 | E28: 2010 | F28: SP R-75 | H28: 2000 | I28: 2010 | J28: SP R-75 | K28: =DAY(N28) -> 0 | L28: =MONTH(N28) -> 1 | M28: =YEAR(N28) -> 1900 | O28: =IF((I28="")=TRUE(),IF((N28="")=TRUE(),"No CLUP",IF(YEAR(NOW())-YEAR(N28)<=10,"Updated","For Updating")),IF(YEAR(NOW())-I28<=0,"Updated","For Updating")) -> For Updating | P28: 1 | Q28: 1 | R28: 1 | S28: 1 | V28: =IF(SUM(P28:U28)=6,"Phase 5",IF(SUM(P28:U28)=5,"Phase 4",IF(SUM(P28:U28)=4,"Phase 3",IF(SUM(P28:U28)=3,"Phase 2",IF(SUM(P28:U28)=2,"Phase 1",IF(SUM(P28:U28)=1,"Prephase","None Indicated")))))) -> Phase 3 | AD28: =IF(SUM(W28:AC28)=7,"RA7",IF(SUM(W28:AC28)=6,"RA 6",IF(SUM(W28:AC28)=5,"RA 5",IF(SUM(W28:AC28)=4,"RA 4",IF(SUM(W28:AC28)=3,"RA3",IF(SUM(W28:AC28)=2,"RA 2",IF(SUM(W28:AC28)=1,"RA1","None Indicated"))))))) -> None Indicated | AE28: Trained and assisted
B29: City of Sagay | C29: Negros Occidental | D29: 2021 | E29: 2030 | F29: SP R-1081 s 2022 | H29: 2021 | I29: 2030 | J29: SP R-1081 s 2022 | K29: =DAY(N29) -> 0 | L29: =MONTH(N29) -> 1 | M29: =YEAR(N29) -> 1900 | O29: =IF((I29="")=TRUE(),IF((N29="")=TRUE(),"No CLUP",IF(YEAR(NOW())-YEAR(N29)<=10,"Updated","For Updating")),IF(YEAR(NOW())-I29<=0,"Updated","For Updating")) -> Updated | V29: =IF(SUM(P29:U29)=6,"Phase 5",IF(SUM(P29:U29)=5,"Phase 4",IF(SUM(P29:U29)=4,"Phase 3",IF(SUM(P29:U29)=3,"Phase 2",IF(SUM(P29:U29)=2,"Phase 1",IF(SUM(P29:U29)=1,"Prephase","None Indicated")))))) -> None Indicated | AD29: =IF(SUM(W29:AC29)=7,"RA7",IF(SUM(W29:AC29)=6,"RA 6",IF(SUM(W29:AC29)=5,"RA 5",IF(SUM(W29:AC29)=4,"RA 4",IF(SUM(W29:AC29)=3,"RA3",IF(SUM(W29:AC29)=2,"RA 2",IF(SUM(W29:AC29)=1,"RA1","None Indicated"))))))) -> None Indicated | AE29: Trained and assisted
B30: City of San Carlos | C30: Negros Occidental | D30: 2014 | E30: 2023 | F30: SP R-0737 s 2015 | H30: 2014 | I30: 2023 | J30: SP R-0737 s 2015 | K30: =DAY(N30) -> 0 | L30: =MONTH(N30) -> 1 | M30: =YEAR(N30) -> 1900 | O30: =IF((I30="")=TRUE(),IF((N30="")=TRUE(),"No CLUP",IF(YEAR(NOW())-YEAR(N30)<=10,"Updated","For Updating")),IF(YEAR(NOW())-I30<=0,"Updated","For Updating")) -> For Updating | P30: 1 | V30: =IF(SUM(P30:U30)=6,"Phase 5",IF(SUM(P30:U30)=5,"Phase 4",IF(SUM(P30:U30)=4,"Phase 3",IF(SUM(P30:U30)=3,"Phase 2",IF(SUM(P30:U30)=2,"Phase 1",IF(SUM(P30:U30)=1,"Prephase","None Indicated")))))) -> Prephase | AD30: =IF(SUM(W30:AC30)=7,"RA7",IF(SUM(W30:AC30)=6,"RA 6",IF(SUM(W30:AC30)=5,"RA 5",IF(SUM(W30:AC30)=4,"RA 4",IF(SUM(W30:AC30)=3,"RA3",IF(SUM(W30:AC30)=2,"RA 2",IF(SUM(W30:AC30)=1,"RA1","None Indicated"))))))) -> None Indicated | AE30: Trained and assisted
B31: San Enrique | C31: Negros Occidental | D31: 2013 | E31: 2023 | F31: SP R-0859 s 2015 | H31: 2013 | I31: 2023 | J31: SP R-0859 s 2015 | K31: =DAY(N31) -> 0 | L31: =MONTH(N31) -> 1 | M31: =YEAR(N31) -> 1900 | O31: =IF((I31="")=TRUE(),IF((N31="")=TRUE(),"No CLUP",IF(YEAR(NOW())-YEAR(N31)<=10,"Updated","For Updating")),IF(YEAR(NOW())-I31<=0,"Updated","For Updating")) -> For Updating | P31: 1 | V31: =IF(SUM(P31:U31)=6,"Phase 5",IF(SUM(P31:U31)=5,"Phase 4",IF(SUM(P31:U31)=4,"Phase 3",IF(SUM(P31:U31)=3,"Phase 2",IF(SUM(P31:U31)=2,"Phase 1",IF(SUM(P31:U31)=1,"Prephase","None Indicated")))))) -> Prephase | AD31: =IF(SUM(W31:AC31)=7,"RA7",IF(SUM(W31:AC31)=6,"RA 6",IF(SUM(W31:AC31)=5,"RA 5",IF(SUM(W31:AC31)=4,"RA 4",IF(SUM(W31:AC31)=3,"RA3",IF(SUM(W31:AC31)=2,"RA 2",IF(SUM(W31:AC31)=1,"RA1","None Indicated"))))))) -> None Indicated | AE31: Trained and assisted
B32: City of Silay | C32: Negros Occidental | D32: 2008 | E32: 2017 | F32: SP R-0092 | H32: 2008 | I32: 2017 | J32: SP R-0092 | K32: =DAY(N32) -> 0 | L32: =MONTH(N32) -> 1 | M32: =YEAR(N32) -> 1900 | O32: =IF((I32="")=TRUE(),IF((N32="")=TRUE(),"No CLUP",IF(YEAR(NOW())-YEAR(N32)<=10,"Updated","For Updating")),IF(YEAR(NOW())-I32<=0,"Updated","For Updating")) -> For Updating | P32: 1 | Q32: 1 | R32: 1 | S32: 1 | T32: 1 | U32: 1 | V32: =IF(SUM(P32:U32)=6,"Phase 5",IF(SUM(P32:U32)=5,"Phase 4",IF(SUM(P32:U32)=4,"Phase 3",IF(SUM(P32:U32)=3,"Phase 2",IF(SUM(P32:U32)=2,"Phase 1",IF(SUM(P32:U32)=1,"Prephase","None Indicated")))))) -> Phase 5 | W32: 1 | X32: 1 | Y32: 1 | AD32: =IF(SUM(W32:AC32)=7,"RA7",IF(SUM(W32:AC32)=6,"RA 6",IF(SUM(W32:AC32)=5,"RA 5",IF(SUM(W32:AC32)=4,"RA 4",IF(SUM(W32:AC32)=3,"RA3",IF(SUM(W32:AC32)=2,"RA 2",IF(SUM(W32:AC32)=1,"RA1","None Indicated"))))))) -> RA3 | AE32: Trained and assisted
B33: City of Sipalay | C33: Negros Occidental | D33: 2006 | E33: 2015 | F33: SP R-300 | H33: 2006 | I33: 2015 | J33: SP R-300 | K33: =DAY(N33) -> 0 | L33: =MONTH(N33) -> 1 | M33: =YEAR(N33) -> 1900 | O33: =IF((I33="")=TRUE(),IF((N33="")=TRUE(),"No CLUP",IF(YEAR(NOW())-YEAR(N33)<=10,"Updated","For Updating")),IF(YEAR(NOW())-I33<=0,"Updated","For Updating")) -> For Updating | P33: 1 | Q33: 1 | R33: 1 | S33: 1 | T33: 1 | U33: 1 | V33: =IF(SUM(P33:U33)=6,"Phase 5",IF(SUM(P33:U33)=5,"Phase 4",IF(SUM(P33:U33)=4,"Phase 3",IF(SUM(P33:U33)=3,"Phase 2",IF(SUM(P33:U33)=2,"Phase 1",IF(SUM(P33:U33)=1,"Prephase","None Indicated")))))) -> Phase 5 | W33: 1 | X33: 1 | Y33: 1 | AD33: =IF(SUM(W33:AC33)=7,"RA7",IF(SUM(W33:AC33)=6,"RA 6",IF(SUM(W33:AC33)=5,"RA 5",IF(SUM(W33:AC33)=4,"RA 4",IF(SUM(W33:AC33)=3,"RA3",IF(SUM(W33:AC33)=2,"RA 2",IF(SUM(W33:AC33)=1,"RA1","None Indicated"))))))) -> RA3 | AE33: Trained and assisted
B34: City of Talisay | C34: Negros Occidental | D34: 2022 | E34: 2032 | F34: SP R-1382 s 2023 | H34: 2022 | I34: 2032 | J34: SP R-1382 s 2023 | K34: =DAY(N34) -> 0 | L34: =MONTH(N34) -> 1 | M34: =YEAR(N34) -> 1900 | O34: =IF((I34="")=TRUE(),IF((N34="")=TRUE(),"No CLUP",IF(YEAR(NOW())-YEAR(N34)<=10,"Updated","For Updating")),IF(YEAR(NOW())-I34<=0,"Updated","For Updating")) -> Updated | V34: =IF(SUM(P34:U34)=6,"Phase 5",IF(SUM(P34:U34)=5,"Phase 4",IF(SUM(P34:U34)=4,"Phase 3",IF(SUM(P34:U34)=3,"Phase 2",IF(SUM(P34:U34)=2,"Phase 1",IF(SUM(P34:U34)=1,"Prephase","None Indicated")))))) -> None Indicated | AD34: =IF(SUM(W34:AC34)=7,"RA7",IF(SUM(W34:AC34)=6,"RA 6",IF(SUM(W34:AC34)=5,"RA 5",IF(SUM(W34:AC34)=4,"RA 4",IF(SUM(W34:AC34)=3,"RA3",IF(SUM(W34:AC34)=2,"RA 2",IF(SUM(W34:AC34)=1,"RA1","None Indicated"))))))) -> None Indicated | AE34: Trained and assisted
B35: Toboso | C35: Negros Occidental | D35: 2013 | E35: 2022 | F35: SP R-0378 s 2018 | H35: 2013 | I35: 2022 | J35: SP R-0378 s 2018 | K35: =DAY(N35) -> 0 | L35: =MONTH(N35) -> 1 | M35: =YEAR(N35) -> 1900 | O35: =IF((I35="")=TRUE(),IF((N35="")=TRUE(),"No CLUP",IF(YEAR(NOW())-YEAR(N35)<=10,"Updated","For Updating")),IF(YEAR(NOW())-I35<=0,"Updated","For Updating")) -> For Updating | P35: 1 | V35: =IF(SUM(P35:U35)=6,"Phase 5",IF(SUM(P35:U35)=5,"Phase 4",IF(SUM(P35:U35)=4,"Phase 3",IF(SUM(P35:U35)=3,"Phase 2",IF(SUM(P35:U35)=2,"Phase 1",IF(SUM(P35:U35)=1,"Prephase","None Indicated")))))) -> Prephase | AD35: =IF(SUM(W35:AC35)=7,"RA7",IF(SUM(W35:AC35)=6,"RA 6",IF(SUM(W35:AC35)=5,"RA 5",IF(SUM(W35:AC35)=4,"RA 4",IF(SUM(W35:AC35)=3,"RA3",IF(SUM(W35:AC35)=2,"RA 2",IF(SUM(W35:AC35)=1,"RA1","None Indicated"))))))) -> None Indicated | AE35: Trained and assisted
B36: Valladolid | C36: Negros Occidental | D36: 2001 | E36: 2010 | F36: SP R-534 | H36: 2001 | I36: 2010 | J36: SP R-534 | K36: =DAY(N36) -> 0 | L36: =MONTH(N36) -> 1 | M36: =YEAR(N36) -> 1900 | O36: =IF((I36="")=TRUE(),IF((N36="")=TRUE(),"No CLUP",IF(YEAR(NOW())-YEAR(N36)<=10,"Updated","For Updating")),IF(YEAR(NOW())-I36<=0,"Updated","For Updating")) -> For Updating | P36: 1 | V36: =IF(SUM(P36:U36)=6,"Phase 5",IF(SUM(P36:U36)=5,"Phase 4",IF(SUM(P36:U36)=4,"Phase 3",IF(SUM(P36:U36)=3,"Phase 2",IF(SUM(P36:U36)=2,"Phase 1",IF(SUM(P36:U36)=1,"Prephase","None Indicated")))))) -> Prephase | AD36: =IF(SUM(W36:AC36)=7,"RA7",IF(SUM(W36:AC36)=6,"RA 6",IF(SUM(W36:AC36)=5,"RA 5",IF(SUM(W36:AC36)=4,"RA 4",IF(SUM(W36:AC36)=3,"RA3",IF(SUM(W36:AC36)=2,"RA 2",IF(SUM(W36:AC36)=1,"RA1","None Indicated"))))))) -> None Indicated | AE36: Trained and assisted
B37: City of Victorias | C37: Negros Occidental | D37: 2018 | E37: 2028 | F37: SP R-0674 | H37: 2018 | I37: 2028 | J37: SP R-0674 | K37: =DAY(N37) -> 0 | L37: =MONTH(N37) -> 1 | M37: =YEAR(N37) -> 1900 | O37: =IF((I37="")=TRUE(),IF((N37="")=TRUE(),"No CLUP",IF(YEAR(NOW())-YEAR(N37)<=10,"Updated","For Updating")),IF(YEAR(NOW())-I37<=0,"Updated","For Updating")) -> Updated | V37: =IF(SUM(P37:U37)=6,"Phase 5",IF(SUM(P37:U37)=5,"Phase 4",IF(SUM(P37:U37)=4,"Phase 3",IF(SUM(P37:U37)=3,"Phase 2",IF(SUM(P37:U37)=2,"Phase 1",IF(SUM(P37:U37)=1,"Prephase","None Indicated")))))) -> None Indicated | AD37: =IF(SUM(W37:AC37)=7,"RA7",IF(SUM(W37:AC37)=6,"RA 6",IF(SUM(W37:AC37)=5,"RA 5",IF(SUM(W37:AC37)=4,"RA 4",IF(SUM(W37:AC37)=3,"RA3",IF(SUM(W37:AC37)=2,"RA 2",IF(SUM(W37:AC37)=1,"RA1","None Indicated"))))))) -> None Indicated | AE37: Trained and assisted
B38: Salvador Benedicto | C38: Negros Occidental | D38: 2001 | E38: 2010 | F38: SP R-21 | H38: 2001 | I38: 2010 | J38: SP R-21 | K38: =DAY(N38) -> 0 | L38: =MONTH(N38) -> 1 | M38: =YEAR(N38) -> 1900 | O38: =IF((I38="")=TRUE(),IF((N38="")=TRUE(),"No CLUP",IF(YEAR(NOW())-YEAR(N38)<=10,"Updated","For Updating")),IF(YEAR(NOW())-I38<=0,"Updated","For Updating")) -> For Updating | P38: 1 | V38: =IF(SUM(P38:U38)=6,"Phase 5",IF(SUM(P38:U38)=5,"Phase 4",IF(SUM(P38:U38)=4,"Phase 3",IF(SUM(P38:U38)=3,"Phase 2",IF(SUM(P38:U38)=2,"Phase 1",IF(SUM(P38:U38)=1,"Prephase","None Indicated")))))) -> Prephase | AD38: =IF(SUM(W38:AC38)=7,"RA7",IF(SUM(W38:AC38)=6,"RA 6",IF(SUM(W38:AC38)=5,"RA 5",IF(SUM(W38:AC38)=4,"RA 4",IF(SUM(W38:AC38)=3,"RA3",IF(SUM(W38:AC38)=2,"RA 2",IF(SUM(W38:AC38)=1,"RA1","None Indicated"))))))) -> None Indicated | AE38: Trained and assisted
B39: City of Bacolod | C39: Negros Occidental | D39: 2017 | E39: 2026 | F39: DHSUD DC No. 2023-004 | H39: 2017 | I39: 2026 | J39: DHSUD DC No. 2023-004 | K39: =DAY(N39) -> 0 | L39: =MONTH(N39) -> 1 | M39: =YEAR(N39) -> 1900 | O39: =IF((I39="")=TRUE(),IF((N39="")=TRUE(),"No CLUP",IF(YEAR(NOW())-YEAR(N39)<=10,"Updated","For Updating")),IF(YEAR(NOW())-I39<=0,"Updated","For Updating")) -> Updated | V39: =IF(SUM(P39:U39)=6,"Phase 5",IF(SUM(P39:U39)=5,"Phase 4",IF(SUM(P39:U39)=4,"Phase 3",IF(SUM(P39:U39)=3,"Phase 2",IF(SUM(P39:U39)=2,"Phase 1",IF(SUM(P39:U39)=1,"Prephase","None Indicated")))))) -> None Indicated | AD39: =IF(SUM(W39:AC39)=7,"RA7",IF(SUM(W39:AC39)=6,"RA 6",IF(SUM(W39:AC39)=5,"RA 5",IF(SUM(W39:AC39)=4,"RA 4",IF(SUM(W39:AC39)=3,"RA3",IF(SUM(W39:AC39)=2,"RA 2",IF(SUM(W39:AC39)=1,"RA1","None Indicated"))))))) -> None Indicated | AE39: Trained and assisted
B40: Amlan | C40: Negros Oriental | D40: 1982 | E40: 1991 | F40: SP 771 | H40: 1982 | I40: 1991 | J40: SP 771 | K40: =DAY(N40) -> 0 | L40: =MONTH(N40) -> 1 | M40: =YEAR(N40) -> 1900 | O40: =IF((I40="")=TRUE(),IF((N40="")=TRUE(),"No CLUP",IF(YEAR(NOW())-YEAR(N40)<=10,"Updated","For Updating")),IF(YEAR(NOW())-I40<=0,"Updated","For Updating")) -> For Updating | P40: 1 | Q40: 1 | V40: =IF(SUM(P40:U40)=6,"Phase 5",IF(SUM(P40:U40)=5,"Phase 4",IF(SUM(P40:U40)=4,"Phase 3",IF(SUM(P40:U40)=3,"Phase 2",IF(SUM(P40:U40)=2,"Phase 1",IF(SUM(P40:U40)=1,"Prephase","None Indicated")))))) -> Phase 1 | AD40: =IF(SUM(W40:AC40)=7,"RA7",IF(SUM(W40:AC40)=6,"RA 6",IF(SUM(W40:AC40)=5,"RA 5",IF(SUM(W40:AC40)=4,"RA 4",IF(SUM(W40:AC40)=3,"RA3",IF(SUM(W40:AC40)=2,"RA 2",IF(SUM(W40:AC40)=1,"RA1","None Indicated"))))))) -> None Indicated | AE40: Trained and assisted
B41: Ayungon | C41: Negros Oriental | D41: 2006 | E41: 2015 | F41: SP 716 | H41: 2006 | I41: 2015 | J41: SP 716 | K41: =DAY(N41) -> 0 | L41: =MONTH(N41) -> 1 | M41: =YEAR(N41) -> 1900 | O41: =IF((I41="")=TRUE(),IF((N41="")=TRUE(),"No CLUP",IF(YEAR(NOW())-YEAR(N41)<=10,"Updated","For Updating")),IF(YEAR(NOW())-I41<=0,"Updated","For Updating")) -> For Updating | P41: 1 | Q41: 1 | R41: 1 | S41: 1 | T41: 1 | U41: 1 | V41: =IF(SUM(P41:U41)=6,"Phase 5",IF(SUM(P41:U41)=5,"Phase 4",IF(SUM(P41:U41)=4,"Phase 3",IF(SUM(P41:U41)=3,"Phase 2",IF(SUM(P41:U41)=2,"Phase 1",IF(SUM(P41:U41)=1,"Prephase","None Indicated")))))) -> Phase 5 | AD41: =IF(SUM(W41:AC41)=7,"RA7",IF(SUM(W41:AC41)=6,"RA 6",IF(SUM(W41:AC41)=5,"RA 5",IF(SUM(W41:AC41)=4,"RA 4",IF(SUM(W41:AC41)=3,"RA3",IF(SUM(W41:AC41)=2,"RA 2",IF(SUM(W41:AC41)=1,"RA1","None Indicated"))))))) -> None Indicated | AE41: Trained and assisted
B42: Bacong | C42: Negros Oriental | D42: 1983 | E42: 1993 | F42: Res. No. 25 | H42: 1983 | I42: 1993 | J42: Res. No. 25 | K42: =DAY(N42) -> 0 | L42: =MONTH(N42) -> 1 | M42: =YEAR(N42) -> 1900 | O42: =IF((I42="")=TRUE(),IF((N42="")=TRUE(),"No CLUP",IF(YEAR(NOW())-YEAR(N42)<=10,"Updated","For Updating")),IF(YEAR(NOW())-I42<=0,"Updated","For Updating")) -> For Updating | P42: 1 | Q42: 1 | R42: 1 | V42: =IF(SUM(P42:U42)=6,"Phase 5",IF(SUM(P42:U42)=5,"Phase 4",IF(SUM(P42:U42)=4,"Phase 3",IF(SUM(P42:U42)=3,"Phase 2",IF(SUM(P42:U42)=2,"Phase 1",IF(SUM(P42:U42)=1,"Prephase","None Indicated")))))) -> Phase 2 | AD42: =IF(SUM(W42:AC42)=7,"RA7",IF(SUM(W42:AC42)=6,"RA 6",IF(SUM(W42:AC42)=5,"RA 5",IF(SUM(W42:AC42)=4,"RA 4",IF(SUM(W42:AC42)=3,"RA3",IF(SUM(W42:AC42)=2,"RA 2",IF(SUM(W42:AC42)=1,"RA1","None Indicated"))))))) -> None Indicated | AE42: Trained and assisted
B43: City of Bais | C43: Negros Oriental | D43: 1996 | E43: 2005 | F43: SP 91 s.96 | H43: 1996 | I43: 2005 | J43: SP 91 s.96 | K43: =DAY(N43) -> 0 | L43: =MONTH(N43) -> 1 | M43: =YEAR(N43) -> 1900 | O43: =IF((I43="")=TRUE(),IF((N43="")=TRUE(),"No CLUP",IF(YEAR(NOW())-YEAR(N43)<=10,"Updated","For Updating")),IF(YEAR(NOW())-I43<=0,"Updated","For Updating")) -> For Updating | P43: 1 | Q43: 1 | R43: 1 | S43: 1 | T43: 1 | U43: 1 | V43: =IF(SUM(P43:U43)=6,"Phase 5",IF(SUM(P43:U43)=5,"Phase 4",IF(SUM(P43:U43)=4,"Phase 3",IF(SUM(P43:U43)=3,"Phase 2",IF(SUM(P43:U43)=2,"Phase 1",IF(SUM(P43:U43)=1,"Prephase","None Indicated")))))) -> Phase 5 | W43: 1 | AD43: =IF(SUM(W43:AC43)=7,"RA7",IF(SUM(W43:AC43)=6,"RA 6",IF(SUM(W43:AC43)=5,"RA 5",IF(SUM(W43:AC43)=4,"RA 4",IF(SUM(W43:AC43)=3,"RA3",IF(SUM(W43:AC43)=2,"RA 2",IF(SUM(W43:AC43)=1,"RA1","None Indicated"))))))) -> RA1 | AE43: Trained and assisted
B44: Basay | C44: Negros Oriental | D44: 1979 | E44: 1990 | F44: HSRC Res. No. R-38-2 s.1980 | H44: 1979 | I44: 1990 | J44: HSRC Res. No. R-38-2 s.1980 | K44: =DAY(N44) -> 0 | L44: =MONTH(N44) -> 1 | M44: =YEAR(N44) -> 1900 | O44: =IF((I44="")=TRUE(),IF((N44="")=TRUE(),"No CLUP",IF(YEAR(NOW())-YEAR(N44)<=10,"Updated","For Updating")),IF(YEAR(NOW())-I44<=0,"Updated","For Updating")) -> For Updating | P44: 1 | Q44: 1 | V44: =IF(SUM(P44:U44)=6,"Phase 5",IF(SUM(P44:U44)=5,"Phase 4",IF(SUM(P44:U44)=4,"Phase 3",IF(SUM(P44:U44)=3,"Phase 2",IF(SUM(P44:U44)=2,"Phase 1",IF(SUM(P44:U44)=1,"Prephase","None Indicated")))))) -> Phase 1 | AD44: =IF(SUM(W44:AC44)=7,"RA7",IF(SUM(W44:AC44)=6,"RA 6",IF(SUM(W44:AC44)=5,"RA 5",IF(SUM(W44:AC44)=4,"RA 4",IF(SUM(W44:AC44)=3,"RA3",IF(SUM(W44:AC44)=2,"RA 2",IF(SUM(W44:AC44)=1,"RA1","None Indicated"))))))) -> None Indicated | AE44: Trained and assisted
B45: City of Bayawan | C45: Negros Oriental | D45: 2003 | E45: 2012 | F45: SP 367 s. 2003 | H45: 2003 | I45: 2012 | J45: SP 367 s. 2003 | K45: =DAY(N45) -> 0 | L45: =MONTH(N45) -> 1 | M45: =YEAR(N45) -> 1900 | O45: =IF((I45="")=TRUE(),IF((N45="")=TRUE(),"No CLUP",IF(YEAR(NOW())-YEAR(N45)<=10,"Updated","For Updating")),IF(YEAR(NOW())-I45<=0,"Updated","For Updating")) -> For Updating | P45: 1 | Q45: 1 | R45: 1 | S45: 1 | T45: 1 | U45: 1 | V45: =IF(SUM(P45:U45)=6,"Phase 5",IF(SUM(P45:U45)=5,"Phase 4",IF(SUM(P45:U45)=4,"Phase 3",IF(SUM(P45:U45)=3,"Phase 2",IF(SUM(P45:U45)=2,"Phase 1",IF(SUM(P45:U45)=1,"Prephase","None Indicated")))))) -> Phase 5 | AD45: =IF(SUM(W45:AC45)=7,"RA7",IF(SUM(W45:AC45)=6,"RA 6",IF(SUM(W45:AC45)=5,"RA 5",IF(SUM(W45:AC45)=4,"RA 4",IF(SUM(W45:AC45)=3,"RA3",IF(SUM(W45:AC45)=2,"RA 2",IF(SUM(W45:AC45)=1,"RA1","None Indicated"))))))) -> None Indicated | AE45: Trained and assisted
B46: Bindoy | C46: Negros Oriental | D46: 2020 | E46: 2030 | F46: SP Res. No. 1261 s2024 | H46: 2020 | I46: 2030 | J46: SP Res. No. 1261 s2024 | K46: =DAY(N46) -> 0 | L46: =MONTH(N46) -> 1 | M46: =YEAR(N46) -> 1900 | O46: =IF((I46="")=TRUE(),IF((N46="")=TRUE(),"No CLUP",IF(YEAR(NOW())-YEAR(N46)<=10,"Updated","For Updating")),IF(YEAR(NOW())-I46<=0,"Updated","For Updating")) -> Updated | P46: 1 | Q46: 1 | R46: 1 | S46: 1 | T46: 1 | U46: 1 | V46: =IF(SUM(P46:U46)=6,"Phase 5",IF(SUM(P46:U46)=5,"Phase 4",IF(SUM(P46:U46)=4,"Phase 3",IF(SUM(P46:U46)=3,"Phase 2",IF(SUM(P46:U46)=2,"Phase 1",IF(SUM(P46:U46)=1,"Prephase","None Indicated")))))) -> Phase 5 | W46: 1 | X46: 1 | Y46: 1 | Z46: 1 | AA46: 1 | AB46: 1 | AC46: 1 | AD46: =IF(SUM(W46:AC46)=7,"RA7",IF(SUM(W46:AC46)=6,"RA 6",IF(SUM(W46:AC46)=5,"RA 5",IF(SUM(W46:AC46)=4,"RA 4",IF(SUM(W46:AC46)=3,"RA3",IF(SUM(W46:AC46)=2,"RA 2",IF(SUM(W46:AC46)=1,"RA1","None Indicated"))))))) -> RA7 | AE46: Trained and assisted
B47: City of Canlaon | C47: Negros Oriental | D47: 1996 | E47: 2026 | F47: SP 67 s. 2001 | H47: 1996 | I47: 2026 | J47: SP 67 s. 2001 | K47: =DAY(N47) -> 0 | L47: =MONTH(N47) -> 1 | M47: =YEAR(N47) -> 1900 | O47: =IF((I47="")=TRUE(),IF((N47="")=TRUE(),"No CLUP",IF(YEAR(NOW())-YEAR(N47)<=10,"Updated","For Updating")),IF(YEAR(NOW())-I47<=0,"Updated","For Updating")) -> Updated | P47: 1 | Q47: 1 | R47: 1 | S47: 1 | T47: 1 | U47: 1 | V47: =IF(SUM(P47:U47)=6,"Phase 5",IF(SUM(P47:U47)=5,"Phase 4",IF(SUM(P47:U47)=4,"Phase 3",IF(SUM(P47:U47)=3,"Phase 2",IF(SUM(P47:U47)=2,"Phase 1",IF(SUM(P47:U47)=1,"Prephase","None Indicated")))))) -> Phase 5 | W47: 1 | X47: 1 | AD47: =IF(SUM(W47:AC47)=7,"RA7",IF(SUM(W47:AC47)=6,"RA 6",IF(SUM(W47:AC47)=5,"RA 5",IF(SUM(W47:AC47)=4,"RA 4",IF(SUM(W47:AC47)=3,"RA3",IF(SUM(W47:AC47)=2,"RA 2",IF(SUM(W47:AC47)=1,"RA1","None Indicated"))))))) -> RA 2 | AE47: Trained and assisted
B48: Dauin | C48: Negros Oriental | D48: 2020 | E48: 2029 | F48: SP Resolution No. 755 | H48: 2020 | I48: 2029 | J48: SP Resolution No. 755 | K48: =DAY(N48) -> 0 | L48: =MONTH(N48) -> 1 | M48: =YEAR(N48) -> 1900 | O48: =IF((I48="")=TRUE(),IF((N48="")=TRUE(),"No CLUP",IF(YEAR(NOW())-YEAR(N48)<=10,"Updated","For Updating")),IF(YEAR(NOW())-I48<=0,"Updated","For Updating")) -> Updated | P48: 1 | Q48: 1 | R48: 1 | S48: 1 | T48: 1 | U48: 1 | V48: =IF(SUM(P48:U48)=6,"Phase 5",IF(SUM(P48:U48)=5,"Phase 4",IF(SUM(P48:U48)=4,"Phase 3",IF(SUM(P48:U48)=3,"Phase 2",IF(SUM(P48:U48)=2,"Phase 1",IF(SUM(P48:U48)=1,"Prephase","None Indicated")))))) -> Phase 5 | W48: 1 | X48: 1 | Y48: 1 | Z48: 1 | AA48: 1 | AB48: 1 | AC48: 1 | AD48: =IF(SUM(W48:AC48)=7,"RA7",IF(SUM(W48:AC48)=6,"RA 6",IF(SUM(W48:AC48)=5,"RA 5",IF(SUM(W48:AC48)=4,"RA 4",IF(SUM(W48:AC48)=3,"RA3",IF(SUM(W48:AC48)=2,"RA 2",IF(SUM(W48:AC48)=1,"RA1","None Indicated"))))))) -> RA7 | AE48: Trained and assisted
B49: City of Dumaguete | C49: Negros Oriental | D49: 2013 | E49: 2023 | F49: SP 703 s.2015 | H49: 2013 | I49: 2023 | J49: SP 703 s.2015 | K49: =DAY(N49) -> 0 | L49: =MONTH(N49) -> 1 | M49: =YEAR(N49) -> 1900 | O49: =IF((I49="")=TRUE(),IF((N49="")=TRUE(),"No CLUP",IF(YEAR(NOW())-YEAR(N49)<=10,"Updated","For Updating")),IF(YEAR(NOW())-I49<=0,"Updated","For Updating")) -> For Updating | P49: 1 | Q49: 1 | V49: =IF(SUM(P49:U49)=6,"Phase 5",IF(SUM(P49:U49)=5,"Phase 4",IF(SUM(P49:U49)=4,"Phase 3",IF(SUM(P49:U49)=3,"Phase 2",IF(SUM(P49:U49)=2,"Phase 1",IF(SUM(P49:U49)=1,"Prephase","None Indicated")))))) -> Phase 1 | AD49: =IF(SUM(W49:AC49)=7,"RA7",IF(SUM(W49:AC49)=6,"RA 6",IF(SUM(W49:AC49)=5,"RA 5",IF(SUM(W49:AC49)=4,"RA 4",IF(SUM(W49:AC49)=3,"RA3",IF(SUM(W49:AC49)=2,"RA 2",IF(SUM(W49:AC49)=1,"RA1","None Indicated"))))))) -> None Indicated | AE49: Trained and assisted
B50: City of Guihulngan | C50: Negros Oriental | D50: 2021 | E50: 2029 | F50: SP Res. No. 1099-2023 | H50: 2021 | I50: 2029 | J50: SP Res. No. 1099-2023 | K50: =DAY(N50) -> 0 | L50: =MONTH(N50) -> 1 | M50: =YEAR(N50) -> 1900 | O50: =IF((I50="")=TRUE(),IF((N50="")=TRUE(),"No CLUP",IF(YEAR(NOW())-YEAR(N50)<=10,"Updated","For Updating")),IF(YEAR(NOW())-I50<=0,"Updated","For Updating")) -> Updated | P50: 1 | Q50: 1 | R50: 1 | S50: 1 | T50: 1 | U50: 1 | V50: =IF(SUM(P50:U50)=6,"Phase 5",IF(SUM(P50:U50)=5,"Phase 4",IF(SUM(P50:U50)=4,"Phase 3",IF(SUM(P50:U50)=3,"Phase 2",IF(SUM(P50:U50)=2,"Phase 1",IF(SUM(P50:U50)=1,"Prephase","None Indicated")))))) -> Phase 5 | W50: 1 | X50: 1 | Y50: 1 | Z50: 1 | AA50: 1 | AB50: 1 | AC50: 1 | AD50: =IF(SUM(W50:AC50)=7,"RA7",IF(SUM(W50:AC50)=6,"RA 6",IF(SUM(W50:AC50)=5,"RA 5",IF(SUM(W50:AC50)=4,"RA 4",IF(SUM(W50:AC50)=3,"RA3",IF(SUM(W50:AC50)=2,"RA 2",IF(SUM(W50:AC50)=1,"RA1","None Indicated"))))))) -> RA7 | AE50: Trained and assisted
B51: Jimalalud | C51: Negros Oriental | K51: =DAY(N51) -> 0 | L51: =MONTH(N51) -> 1 | M51: =YEAR(N51) -> 1900 | O51: =IF((I51="")=TRUE(),IF((N51="")=TRUE(),"No CLUP",IF(YEAR(NOW())-YEAR(N51)<=10,"Updated","For Updating")),IF(YEAR(NOW())-I51<=0,"Updated","For Updating")) -> #VALUE! | P51: 1 | Q51: 1 | R51: 1 | S51: 1 | V51: =IF(SUM(P51:U51)=6,"Phase 5",IF(SUM(P51:U51)=5,"Phase 4",IF(SUM(P51:U51)=4,"Phase 3",IF(SUM(P51:U51)=3,"Phase 2",IF(SUM(P51:U51)=2,"Phase 1",IF(SUM(P51:U51)=1,"Prephase","None Indicated")))))) -> Phase 3 | AD51: =IF(SUM(W51:AC51)=7,"RA7",IF(SUM(W51:AC51)=6,"RA 6",IF(SUM(W51:AC51)=5,"RA 5",IF(SUM(W51:AC51)=4,"RA 4",IF(SUM(W51:AC51)=3,"RA3",IF(SUM(W51:AC51)=2,"RA 2",IF(SUM(W51:AC51)=1,"RA1","None Indicated"))))))) -> None Indicated | AE51: Trained and assisted
B52: La Libertad | C52: Negros Oriental | K52: =DAY(N52) -> 0 | L52: =MONTH(N52) -> 1 | M52: =YEAR(N52) -> 1900 | O52: =IF((I52="")=TRUE(),IF((N52="")=TRUE(),"No CLUP",IF(YEAR(NOW())-YEAR(N52)<=10,"Updated","For Updating")),IF(YEAR(NOW())-I52<=0,"Updated","For Updating")) -> #VALUE! | P52: 1 | Q52: 1 | R52: 1 | S52: 1 | V52: =IF(SUM(P52:U52)=6,"Phase 5",IF(SUM(P52:U52)=5,"Phase 4",IF(SUM(P52:U52)=4,"Phase 3",IF(SUM(P52:U52)=3,"Phase 2",IF(SUM(P52:U52)=2,"Phase 1",IF(SUM(P52:U52)=1,"Prephase","None Indicated")))))) -> Phase 3 | AD52: =IF(SUM(W52:AC52)=7,"RA7",IF(SUM(W52:AC52)=6,"RA 6",IF(SUM(W52:AC52)=5,"RA 5",IF(SUM(W52:AC52)=4,"RA 4",IF(SUM(W52:AC52)=3,"RA3",IF(SUM(W52:AC52)=2,"RA 2",IF(SUM(W52:AC52)=1,"RA1","None Indicated"))))))) -> None Indicated | AE52: Trained and assisted
B53: Mabinay | C53: Negros Oriental | D53: 2022 | E53: 2031 | F53: SP. Resolution No. 354 | H53: 2022 | I53: 2031 | J53: SP. Resolution No. 354 | K53: =DAY(N53) -> 0 | L53: =MONTH(N53) -> 1 | M53: =YEAR(N53) -> 1900 | O53: =IF((I53="")=TRUE(),IF((N53="")=TRUE(),"No CLUP",IF(YEAR(NOW())-YEAR(N53)<=10,"Updated","For Updating")),IF(YEAR(NOW())-I53<=0,"Updated","For Updating")) -> Updated | P53: 1 | Q53: 1 | R53: 1 | S53: 1 | T53: 1 | U53: 1 | V53: =IF(SUM(P53:U53)=6,"Phase 5",IF(SUM(P53:U53)=5,"Phase 4",IF(SUM(P53:U53)=4,"Phase 3",IF(SUM(P53:U53)=3,"Phase 2",IF(SUM(P53:U53)=2,"Phase 1",IF(SUM(P53:U53)=1,"Prephase","None Indicated")))))) -> Phase 5 | W53: 1 | X53: 1 | Y53: 1 | Z53: 1 | AA53: 1 | AB53: 1 | AC53: 1 | AD53: =IF(SUM(W53:AC53)=7,"RA7",IF(SUM(W53:AC53)=6,"RA 6",IF(SUM(W53:AC53)=5,"RA 5",IF(SUM(W53:AC53)=4,"RA 4",IF(SUM(W53:AC53)=3,"RA3",IF(SUM(W53:AC53)=2,"RA 2",IF(SUM(W53:AC53)=1,"RA1","None Indicated"))))))) -> RA7 | AE53: Trained and assisted
B54: Manjuyod | C54: Negros Oriental | D54: 1982 | E54: 1992 | F54: R 214 s. 1984 | H54: 1982 | I54: 1992 | J54: R 214 s. 1984 | K54: =DAY(N54) -> 0 | L54: =MONTH(N54) -> 1 | M54: =YEAR(N54) -> 1900 | O54: =IF((I54="")=TRUE(),IF((N54="")=TRUE(),"No CLUP",IF(YEAR(NOW())-YEAR(N54)<=10,"Updated","For Updating")),IF(YEAR(NOW())-I54<=0,"Updated","For Updating")) -> For Updating | P54: 1 | V54: =IF(SUM(P54:U54)=6,"Phase 5",IF(SUM(P54:U54)=5,"Phase 4",IF(SUM(P54:U54)=4,"Phase 3",IF(SUM(P54:U54)=3,"Phase 2",IF(SUM(P54:U54)=2,"Phase 1",IF(SUM(P54:U54)=1,"Prephase","None Indicated")))))) -> Prephase | AD54: =IF(SUM(W54:AC54)=7,"RA7",IF(SUM(W54:AC54)=6,"RA 6",IF(SUM(W54:AC54)=5,"RA 5",IF(SUM(W54:AC54)=4,"RA 4",IF(SUM(W54:AC54)=3,"RA3",IF(SUM(W54:AC54)=2,"RA 2",IF(SUM(W54:AC54)=1,"RA1","None Indicated"))))))) -> None Indicated | AE54: Trained and assisted
B55: Pamplona | C55: Negros Oriental | D55: 2006 | E55: 2016 | F55: SP 319 | H55: 2006 | I55: 2016 | J55: SP 319 | K55: =DAY(N55) -> 0 | L55: =MONTH(N55) -> 1 | M55: =YEAR(N55) -> 1900 | O55: =IF((I55="")=TRUE(),IF((N55="")=TRUE(),"No CLUP",IF(YEAR(NOW())-YEAR(N55)<=10,"Updated","For Updating")),IF(YEAR(NOW())-I55<=0,"Updated","For Updating")) -> For Updating | P55: 1 | V55: =IF(SUM(P55:U55)=6,"Phase 5",IF(SUM(P55:U55)=5,"Phase 4",IF(SUM(P55:U55)=4,"Phase 3",IF(SUM(P55:U55)=3,"Phase 2",IF(SUM(P55:U55)=2,"Phase 1",IF(SUM(P55:U55)=1,"Prephase","None Indicated")))))) -> Prephase | AD55: =IF(SUM(W55:AC55)=7,"RA7",IF(SUM(W55:AC55)=6,"RA 6",IF(SUM(W55:AC55)=5,"RA 5",IF(SUM(W55:AC55)=4,"RA 4",IF(SUM(W55:AC55)=3,"RA3",IF(SUM(W55:AC55)=2,"RA 2",IF(SUM(W55:AC55)=1,"RA1","None Indicated"))))))) -> None Indicated | AE55: Trained and assisted
B56: San Jose | C56: Negros Oriental | D56: 2020 | E56: 2029 | F56: SP Resolution No. 547, Series of 2022 | H56: 2020 | I56: 2029 | J56: SP Resolution No. 547, Series of 2022 | K56: =DAY(N56) -> 0 | L56: =MONTH(N56) -> 1 | M56: =YEAR(N56) -> 1900 | O56: =IF((I56="")=TRUE(),IF((N56="")=TRUE(),"No CLUP",IF(YEAR(NOW())-YEAR(N56)<=10,"Updated","For Updating")),IF(YEAR(NOW())-I56<=0,"Updated","For Updating")) -> Updated | P56: 1 | Q56: 1 | R56: 1 | S56: 1 | T56: 1 | U56: 1 | V56: =IF(SUM(P56:U56)=6,"Phase 5",IF(SUM(P56:U56)=5,"Phase 4",IF(SUM(P56:U56)=4,"Phase 3",IF(SUM(P56:U56)=3,"Phase 2",IF(SUM(P56:U56)=2,"Phase 1",IF(SUM(P56:U56)=1,"Prephase","None Indicated")))))) -> Phase 5 | W56: 1 | X56: 1 | Y56: 1 | Z56: 1 | AA56: 1 | AB56: 1 | AC56: 1 | AD56: =IF(SUM(W56:AC56)=7,"RA7",IF(SUM(W56:AC56)=6,"RA 6",IF(SUM(W56:AC56)=5,"RA 5",IF(SUM(W56:AC56)=4,"RA 4",IF(SUM(W56:AC56)=3,"RA3",IF(SUM(W56:AC56)=2,"RA 2",IF(SUM(W56:AC56)=1,"RA1","None Indicated"))))))) -> RA7 | AE56: Trained and assisted
B57: Santa Catalina | C57: Negros Oriental | D57: 2010 | E57: 2019 | F57: SP 559 | H57: 2010 | I57: 2019 | J57: SP 559 | K57: =DAY(N57) -> 0 | L57: =MONTH(N57) -> 1 | M57: =YEAR(N57) -> 1900 | O57: =IF((I57="")=TRUE(),IF((N57="")=TRUE(),"No CLUP",IF(YEAR(NOW())-YEAR(N57)<=10,"Updated","For Updating")),IF(YEAR(NOW())-I57<=0,"Updated","For Updating")) -> For Updating | P57: 1 | Q57: 1 | R57: 1 | S57: 1 | T57: 1 | V57: =IF(SUM(P57:U57)=6,"Phase 5",IF(SUM(P57:U57)=5,"Phase 4",IF(SUM(P57:U57)=4,"Phase 3",IF(SUM(P57:U57)=3,"Phase 2",IF(SUM(P57:U57)=2,"Phase 1",IF(SUM(P57:U57)=1,"Prephase","None Indicated")))))) -> Phase 4 | AD57: =IF(SUM(W57:AC57)=7,"RA7",IF(SUM(W57:AC57)=6,"RA 6",IF(SUM(W57:AC57)=5,"RA 5",IF(SUM(W57:AC57)=4,"RA 4",IF(SUM(W57:AC57)=3,"RA3",IF(SUM(W57:AC57)=2,"RA 2",IF(SUM(W57:AC57)=1,"RA1","None Indicated"))))))) -> None Indicated | AE57: Trained and assisted
B58: Siaton | C58: Negros Oriental | D58: 1979 | E58: 2000 | F58: Resolution No. R11 s. 1981 | H58: 1979 | I58: 2000 | J58: Resolution No. R11 s. 1981 | K58: =DAY(N58) -> 0 | L58: =MONTH(N58) -> 1 | M58: =YEAR(N58) -> 1900 | O58: =IF((I58="")=TRUE(),IF((N58="")=TRUE(),"No CLUP",IF(YEAR(NOW())-YEAR(N58)<=10,"Updated","For Updating")),IF(YEAR(NOW())-I58<=0,"Updated","For Updating")) -> For Updating | P58: 1 | Q58: 1 | R58: 1 | V58: =IF(SUM(P58:U58)=6,"Phase 5",IF(SUM(P58:U58)=5,"Phase 4",IF(SUM(P58:U58)=4,"Phase 3",IF(SUM(P58:U58)=3,"Phase 2",IF(SUM(P58:U58)=2,"Phase 1",IF(SUM(P58:U58)=1,"Prephase","None Indicated")))))) -> Phase 2 | AD58: =IF(SUM(W58:AC58)=7,"RA7",IF(SUM(W58:AC58)=6,"RA 6",IF(SUM(W58:AC58)=5,"RA 5",IF(SUM(W58:AC58)=4,"RA 4",IF(SUM(W58:AC58)=3,"RA3",IF(SUM(W58:AC58)=2,"RA 2",IF(SUM(W58:AC58)=1,"RA1","None Indicated"))))))) -> None Indicated | AE58: Trained and assisted
B59: Sibulan | C59: Negros Oriental | D59: 2020 | E59: 2029 | F59: SP Resolution No. 111 | H59: 2020 | I59: 2029 | J59: SP Resolution No. 111 | K59: =DAY(N59) -> 0 | L59: =MONTH(N59) -> 1 | M59: =YEAR(N59) -> 1900 | O59: =IF((I59="")=TRUE(),IF((N59="")=TRUE(),"No CLUP",IF(YEAR(NOW())-YEAR(N59)<=10,"Updated","For Updating")),IF(YEAR(NOW())-I59<=0,"Updated","For Updating")) -> Updated | P59: 1 | Q59: 1 | R59: 1 | S59: 1 | T59: 1 | U59: 1 | V59: =IF(SUM(P59:U59)=6,"Phase 5",IF(SUM(P59:U59)=5,"Phase 4",IF(SUM(P59:U59)=4,"Phase 3",IF(SUM(P59:U59)=3,"Phase 2",IF(SUM(P59:U59)=2,"Phase 1",IF(SUM(P59:U59)=1,"Prephase","None Indicated")))))) -> Phase 5 | W59: 1 | X59: 1 | Y59: 1 | Z59: 1 | AA59: 1 | AB59: 1 | AC59: 1 | AD59: =IF(SUM(W59:AC59)=7,"RA7",IF(SUM(W59:AC59)=6,"RA 6",IF(SUM(W59:AC59)=5,"RA 5",IF(SUM(W59:AC59)=4,"RA 4",IF(SUM(W59:AC59)=3,"RA3",IF(SUM(W59:AC59)=2,"RA 2",IF(SUM(W59:AC59)=1,"RA1","None Indicated"))))))) -> RA7 | AE59: Trained and assisted
B60: City of Tanjay | C60: Negros Oriental | D60: 1998 | E60: 2010 | F60: SP 312 | H60: 1998 | I60: 2010 | J60: SP 312 | K60: =DAY(N60) -> 0 | L60: =MONTH(N60) -> 1 | M60: =YEAR(N60) -> 1900 | O60: =IF((I60="")=TRUE(),IF((N60="")=TRUE(),"No CLUP",IF(YEAR(NOW())-YEAR(N60)<=10,"Updated","For Updating")),IF(YEAR(NOW())-I60<=0,"Updated","For Updating")) -> For Updating | P60: 1 | Q60: 1 | R60: 1 | V60: =IF(SUM(P60:U60)=6,"Phase 5",IF(SUM(P60:U60)=5,"Phase 4",IF(SUM(P60:U60)=4,"Phase 3",IF(SUM(P60:U60)=3,"Phase 2",IF(SUM(P60:U60)=2,"Phase 1",IF(SUM(P60:U60)=1,"Prephase","None Indicated")))))) -> Phase 2 | AD60: =IF(SUM(W60:AC60)=7,"RA7",IF(SUM(W60:AC60)=6,"RA 6",IF(SUM(W60:AC60)=5,"RA 5",IF(SUM(W60:AC60)=4,"RA 4",IF(SUM(W60:AC60)=3,"RA3",IF(SUM(W60:AC60)=2,"RA 2",IF(SUM(W60:AC60)=1,"RA1","None Indicated"))))))) -> None Indicated | AE60: Trained and assisted
B61: Tayasan | C61: Negros Oriental | D61: 1979 | E61: 2000 | F61: R38-2 s.1980 | H61: 1979 | I61: 2000 | J61: R38-2 s.1980 | K61: =DAY(N61) -> 0 | L61: =MONTH(N61) -> 1 | M61: =YEAR(N61) -> 1900 | O61: =IF((I61="")=TRUE(),IF((N61="")=TRUE(),"No CLUP",IF(YEAR(NOW())-YEAR(N61)<=10,"Updated","For Updating")),IF(YEAR(NOW())-I61<=0,"Updated","For Updating")) -> For Updating | P61: 1 | Q61: 1 | R61: 1 | V61: =IF(SUM(P61:U61)=6,"Phase 5",IF(SUM(P61:U61)=5,"Phase 4",IF(SUM(P61:U61)=4,"Phase 3",IF(SUM(P61:U61)=3,"Phase 2",IF(SUM(P61:U61)=2,"Phase 1",IF(SUM(P61:U61)=1,"Prephase","None Indicated")))))) -> Phase 2 | AD61: =IF(SUM(W61:AC61)=7,"RA7",IF(SUM(W61:AC61)=6,"RA 6",IF(SUM(W61:AC61)=5,"RA 5",IF(SUM(W61:AC61)=4,"RA 4",IF(SUM(W61:AC61)=3,"RA3",IF(SUM(W61:AC61)=2,"RA 2",IF(SUM(W61:AC61)=1,"RA1","None Indicated"))))))) -> None Indicated | AE61: Trained and assisted
B62: Valencia | C62: Negros Oriental | D62: 2004 | E62: 2013 | F62: SP Res. 1009-2025 | H62: 2004 | I62: 2013 | J62: SP Res. 1009-2025 | K62: =DAY(N62) -> 0 | L62: =MONTH(N62) -> 1 | M62: =YEAR(N62) -> 1900 | O62: =IF((I62="")=TRUE(),IF((N62="")=TRUE(),"No CLUP",IF(YEAR(NOW())-YEAR(N62)<=10,"Updated","For Updating")),IF(YEAR(NOW())-I62<=0,"Updated","For Updating")) -> For Updating | P62: 1 | Q62: 1 | R62: 1 | S62: 1 | T62: 1 | U62: 1 | V62: =IF(SUM(P62:U62)=6,"Phase 5",IF(SUM(P62:U62)=5,"Phase 4",IF(SUM(P62:U62)=4,"Phase 3",IF(SUM(P62:U62)=3,"Phase 2",IF(SUM(P62:U62)=2,"Phase 1",IF(SUM(P62:U62)=1,"Prephase","None Indicated")))))) -> Phase 5 | W62: 1 | X62: 1 | Y62: 1 | Z62: 1 | AA62: 1 | AB62: 1 | AC62: 1 | AD62: =IF(SUM(W62:AC62)=7,"RA7",IF(SUM(W62:AC62)=6,"RA 6",IF(SUM(W62:AC62)=5,"RA 5",IF(SUM(W62:AC62)=4,"RA 4",IF(SUM(W62:AC62)=3,"RA3",IF(SUM(W62:AC62)=2,"RA 2",IF(SUM(W62:AC62)=1,"RA1","None Indicated"))))))) -> RA7 | AE62: Trained and assisted
B63: Vallehermoso | C63: Negros Oriental | D63: 2020 | E63: 2029 | F63: SP Res. No 35 | H63: 2020 | I63: 2029 | J63: SP Res. No 35 | K63: =DAY(N63) -> 0 | L63: =MONTH(N63) -> 1 | M63: =YEAR(N63) -> 1900 | O63: =IF((I63="")=TRUE(),IF((N63="")=TRUE(),"No CLUP",IF(YEAR(NOW())-YEAR(N63)<=10,"Updated","For Updating")),IF(YEAR(NOW())-I63<=0,"Updated","For Updating")) -> Updated | P63: 1 | Q63: 1 | R63: 1 | S63: 1 | T63: 1 | U63: 1 | V63: =IF(SUM(P63:U63)=6,"Phase 5",IF(SUM(P63:U63)=5,"Phase 4",IF(SUM(P63:U63)=4,"Phase 3",IF(SUM(P63:U63)=3,"Phase 2",IF(SUM(P63:U63)=2,"Phase 1",IF(SUM(P63:U63)=1,"Prephase","None Indicated")))))) -> Phase 5 | W63: 1 | X63: 1 | Y63: 1 | Z63: 1 | AA63: 1 | AB63: 1 | AC63: 1 | AD63: =IF(SUM(W63:AC63)=7,"RA7",IF(SUM(W63:AC63)=6,"RA 6",IF(SUM(W63:AC63)=5,"RA 5",IF(SUM(W63:AC63)=4,"RA 4",IF(SUM(W63:AC63)=3,"RA3",IF(SUM(W63:AC63)=2,"RA 2",IF(SUM(W63:AC63)=1,"RA1","None Indicated"))))))) -> RA7 | AE63: Trained and assisted
B64: Zamboanguita | C64: Negros Oriental | D64: 2008 | E64: 2017 | F64: SP 394 | H64: 2008 | I64: 2017 | J64: SP 394 | K64: =DAY(N64) -> 0 | L64: =MONTH(N64) -> 1 | M64: =YEAR(N64) -> 1900 | O64: =IF((I64="")=TRUE(),IF((N64="")=TRUE(),"No CLUP",IF(YEAR(NOW())-YEAR(N64)<=10,"Updated","For Updating")),IF(YEAR(NOW())-I64<=0,"Updated","For Updating")) -> For Updating | P64: 1 | Q64: 1 | R64: 1 | S64: 1 | T64: 1 | U64: 1 | V64: =IF(SUM(P64:U64)=6,"Phase 5",IF(SUM(P64:U64)=5,"Phase 4",IF(SUM(P64:U64)=4,"Phase 3",IF(SUM(P64:U64)=3,"Phase 2",IF(SUM(P64:U64)=2,"Phase 1",IF(SUM(P64:U64)=1,"Prephase","None Indicated")))))) -> Phase 5 | W64: 1 | X64: 1 | Y64: 1 | AD64: =IF(SUM(W64:AC64)=7,"RA7",IF(SUM(W64:AC64)=6,"RA 6",IF(SUM(W64:AC64)=5,"RA 5",IF(SUM(W64:AC64)=4,"RA 4",IF(SUM(W64:AC64)=3,"RA3",IF(SUM(W64:AC64)=2,"RA 2",IF(SUM(W64:AC64)=1,"RA1","None Indicated"))))))) -> RA3 | AE64: Trained and assisted
B65: Enrique Villanueva | C65: Siquijor | D65: 2001 | E65: 2010 | F65: SP 092 | H65: 2001 | I65: 2010 | J65: SP 092 | K65: =DAY(N65) -> 0 | L65: =MONTH(N65) -> 1 | M65: =YEAR(N65) -> 1900 | O65: =IF((I65="")=TRUE(),IF((N65="")=TRUE(),"No CLUP",IF(YEAR(NOW())-YEAR(N65)<=10,"Updated","For Updating")),IF(YEAR(NOW())-I65<=0,"Updated","For Updating")) -> For Updating | P65: 1 | Q65: 1 | V65: =IF(SUM(P65:U65)=6,"Phase 5",IF(SUM(P65:U65)=5,"Phase 4",IF(SUM(P65:U65)=4,"Phase 3",IF(SUM(P65:U65)=3,"Phase 2",IF(SUM(P65:U65)=2,"Phase 1",IF(SUM(P65:U65)=1,"Prephase","None Indicated")))))) -> Phase 1 | AD65: =IF(SUM(W65:AC65)=7,"RA7",IF(SUM(W65:AC65)=6,"RA 6",IF(SUM(W65:AC65)=5,"RA 5",IF(SUM(W65:AC65)=4,"RA 4",IF(SUM(W65:AC65)=3,"RA3",IF(SUM(W65:AC65)=2,"RA 2",IF(SUM(W65:AC65)=1,"RA1","None Indicated"))))))) -> None Indicated | AE65: Trained and assisted
B66: Larena | C66: Siquijor | D66: 2001 | E66: 2010 | F66: SP 092 | H66: 2001 | I66: 2010 | J66: SP 092 | K66: =DAY(N66) -> 0 | L66: =MONTH(N66) -> 1 | M66: =YEAR(N66) -> 1900 | O66: =IF((I66="")=TRUE(),IF((N66="")=TRUE(),"No CLUP",IF(YEAR(NOW())-YEAR(N66)<=10,"Updated","For Updating")),IF(YEAR(NOW())-I66<=0,"Updated","For Updating")) -> For Updating | P66: 1 | Q66: 1 | V66: =IF(SUM(P66:U66)=6,"Phase 5",IF(SUM(P66:U66)=5,"Phase 4",IF(SUM(P66:U66)=4,"Phase 3",IF(SUM(P66:U66)=3,"Phase 2",IF(SUM(P66:U66)=2,"Phase 1",IF(SUM(P66:U66)=1,"Prephase","None Indicated")))))) -> Phase 1 | AD66: =IF(SUM(W66:AC66)=7,"RA7",IF(SUM(W66:AC66)=6,"RA 6",IF(SUM(W66:AC66)=5,"RA 5",IF(SUM(W66:AC66)=4,"RA 4",IF(SUM(W66:AC66)=3,"RA3",IF(SUM(W66:AC66)=2,"RA 2",IF(SUM(W66:AC66)=1,"RA1","None Indicated"))))))) -> None Indicated | AE66: Trained and assisted
B67: Lazi | C67: Siquijor | D67: 2001 | E67: 2010 | F67: SP 092 | H67: 2001 | I67: 2010 | J67: SP 092 | K67: =DAY(N67) -> 0 | L67: =MONTH(N67) -> 1 | M67: =YEAR(N67) -> 1900 | O67: =IF((I67="")=TRUE(),IF((N67="")=TRUE(),"No CLUP",IF(YEAR(NOW())-YEAR(N67)<=10,"Updated","For Updating")),IF(YEAR(NOW())-I67<=0,"Updated","For Updating")) -> For Updating | P67: 1 | Q67: 1 | V67: =IF(SUM(P67:U67)=6,"Phase 5",IF(SUM(P67:U67)=5,"Phase 4",IF(SUM(P67:U67)=4,"Phase 3",IF(SUM(P67:U67)=3,"Phase 2",IF(SUM(P67:U67)=2,"Phase 1",IF(SUM(P67:U67)=1,"Prephase","None Indicated")))))) -> Phase 1 | AD67: =IF(SUM(W67:AC67)=7,"RA7",IF(SUM(W67:AC67)=6,"RA 6",IF(SUM(W67:AC67)=5,"RA 5",IF(SUM(W67:AC67)=4,"RA 4",IF(SUM(W67:AC67)=3,"RA3",IF(SUM(W67:AC67)=2,"RA 2",IF(SUM(W67:AC67)=1,"RA1","None Indicated"))))))) -> None Indicated | AE67: Trained and assisted
B68: Maria | C68: Siquijor | D68: 2001 | E68: 2010 | F68: SP 092 | H68: 2001 | I68: 2010 | J68: SP 092 | K68: =DAY(N68) -> 0 | L68: =MONTH(N68) -> 1 | M68: =YEAR(N68) -> 1900 | O68: =IF((I68="")=TRUE(),IF((N68="")=TRUE(),"No CLUP",IF(YEAR(NOW())-YEAR(N68)<=10,"Updated","For Updating")),IF(YEAR(NOW())-I68<=0,"Updated","For Updating")) -> For Updating | P68: 1 | Q68: 1 | V68: =IF(SUM(P68:U68)=6,"Phase 5",IF(SUM(P68:U68)=5,"Phase 4",IF(SUM(P68:U68)=4,"Phase 3",IF(SUM(P68:U68)=3,"Phase 2",IF(SUM(P68:U68)=2,"Phase 1",IF(SUM(P68:U68)=1,"Prephase","None Indicated")))))) -> Phase 1 | AD68: =IF(SUM(W68:AC68)=7,"RA7",IF(SUM(W68:AC68)=6,"RA 6",IF(SUM(W68:AC68)=5,"RA 5",IF(SUM(W68:AC68)=4,"RA 4",IF(SUM(W68:AC68)=3,"RA3",IF(SUM(W68:AC68)=2,"RA 2",IF(SUM(W68:AC68)=1,"RA1","None Indicated"))))))) -> None Indicated | AE68: Trained and assisted
B69: San Juan | C69: Siquijor | D69: 2002 | E69: 2012 | F69: SP 034 | H69: 2002 | I69: 2012 | J69: SP 034 | K69: =DAY(N69) -> 0 | L69: =MONTH(N69) -> 1 | M69: =YEAR(N69) -> 1900 | O69: =IF((I69="")=TRUE(),IF((N69="")=TRUE(),"No CLUP",IF(YEAR(NOW())-YEAR(N69)<=10,"Updated","For Updating")),IF(YEAR(NOW())-I69<=0,"Updated","For Updating")) -> For Updating | P69: 1 | Q69: 1 | R69: 1 | S69: 1 | T69: 1 | U69: 1 | V69: =IF(SUM(P69:U69)=6,"Phase 5",IF(SUM(P69:U69)=5,"Phase 4",IF(SUM(P69:U69)=4,"Phase 3",IF(SUM(P69:U69)=3,"Phase 2",IF(SUM(P69:U69)=2,"Phase 1",IF(SUM(P69:U69)=1,"Prephase","None Indicated")))))) -> Phase 5 | W69: 1 | X69: 1 | Y69: 1 | Z69: 1 | AA69: 1 | AD69: =IF(SUM(W69:AC69)=7,"RA7",IF(SUM(W69:AC69)=6,"RA 6",IF(SUM(W69:AC69)=5,"RA 5",IF(SUM(W69:AC69)=4,"RA 4",IF(SUM(W69:AC69)=3,"RA3",IF(SUM(W69:AC69)=2,"RA 2",IF(SUM(W69:AC69)=1,"RA1","None Indicated"))))))) -> RA 5 | AE69: Trained and assisted
B70: Siquijor | C70: Siquijor | D70: 2001 | E70: 2010 | F70: SP 092 | H70: 2001 | I70: 2010 | J70: SP 092 | K70: =DAY(N70) -> 0 | L70: =MONTH(N70) -> 1 | M70: =YEAR(N70) -> 1900 | O70: =IF((I70="")=TRUE(),IF((N70="")=TRUE(),"No CLUP",IF(YEAR(NOW())-YEAR(N70)<=10,"Updated","For Updating")),IF(YEAR(NOW())-I70<=0,"Updated","For Updating")) -> For Updating | P70: 1 | Q70: 1 | R70: 1 | S70: 1 | T70: 1 | U70: 1 | V70: =IF(SUM(P70:U70)=6,"Phase 5",IF(SUM(P70:U70)=5,"Phase 4",IF(SUM(P70:U70)=4,"Phase 3",IF(SUM(P70:U70)=3,"Phase 2",IF(SUM(P70:U70)=2,"Phase 1",IF(SUM(P70:U70)=1,"Prephase","None Indicated")))))) -> Phase 5 | W70: 1 | X70: 1 | Y70: 1 | Z70: 1 | AA70: 1 | AD70: =IF(SUM(W70:AC70)=7,"RA7",IF(SUM(W70:AC70)=6,"RA 6",IF(SUM(W70:AC70)=5,"RA 5",IF(SUM(W70:AC70)=4,"RA 4",IF(SUM(W70:AC70)=3,"RA3",IF(SUM(W70:AC70)=2,"RA 2",IF(SUM(W70:AC70)=1,"RA1","None Indicated"))))))) -> RA 5 | AE70: Trained and assisted
K71: =DAY(N71) -> 0 | L71: =MONTH(N71) -> 1 | M71: =YEAR(N71) -> 1900 | O71: =IF((I71="")=TRUE(),IF((N71="")=TRUE(),"No CLUP",IF(YEAR(NOW())-YEAR(N71)<=10,"Updated","For Updating")),IF(YEAR(NOW())-I71<=0,"Updated","For Updating")) -> No CLUP | V71: =IF(SUM(P71:U71)=6,"Phase 5",IF(SUM(P71:U71)=5,"Phase 4",IF(SUM(P71:U71)=4,"Phase 3",IF(SUM(P71:U71)=3,"Phase 2",IF(SUM(P71:U71)=2,"Phase 1",IF(SUM(P71:U71)=1,"Prephase","None Indicated")))))) -> None Indicated | AD71: =IF(SUM(W71:AC71)=7,"RA7",IF(SUM(W71:AC71)=6,"RA 6",IF(SUM(W71:AC71)=5,"RA 5",IF(SUM(W71:AC71)=4,"RA 4",IF(SUM(W71:AC71)=3,"RA3",IF(SUM(W71:AC71)=2,"RA 2",IF(SUM(W71:AC71)=1,"RA1","None Indicated"))))))) -> None Indicated
K72: =DAY(N72) -> 0 | L72: =MONTH(N72) -> 1 | M72: =YEAR(N72) -> 1900 | O72: =IF((I72="")=TRUE(),IF((N72="")=TRUE(),"No CLUP",IF(YEAR(NOW())-YEAR(N72)<=10,"Updated","For Updating")),IF(YEAR(NOW())-I72<=0,"Updated","For Updating")) -> No CLUP | V72: =IF(SUM(P72:U72)=6,"Phase 5",IF(SUM(P72:U72)=5,"Phase 4",IF(SUM(P72:U72)=4,"Phase 3",IF(SUM(P72:U72)=3,"Phase 2",IF(SUM(P72:U72)=2,"Phase 1",IF(SUM(P72:U72)=1,"Prephase","None Indicated")))))) -> None Indicated | AD72: =IF(SUM(W72:AC72)=7,"RA7",IF(SUM(W72:AC72)=6,"RA 6",IF(SUM(W72:AC72)=5,"RA 5",IF(SUM(W72:AC72)=4,"RA 4",IF(SUM(W72:AC72)=3,"RA3",IF(SUM(W72:AC72)=2,"RA 2",IF(SUM(W72:AC72)=1,"RA1","None Indicated"))))))) -> None Indicated
K73: =DAY(N73) -> 0 | L73: =MONTH(N73) -> 1 | M73: =YEAR(N73) -> 1900 | O73: =IF((I73="")=TRUE(),IF((N73="")=TRUE(),"No CLUP",IF(YEAR(NOW())-YEAR(N73)<=10,"Updated","For Updating")),IF(YEAR(NOW())-I73<=0,"Updated","For Updating")) -> No CLUP | V73: =IF(SUM(P73:U73)=6,"Phase 5",IF(SUM(P73:U73)=5,"Phase 4",IF(SUM(P73:U73)=4,"Phase 3",IF(SUM(P73:U73)=3,"Phase 2",IF(SUM(P73:U73)=2,"Phase 1",IF(SUM(P73:U73)=1,"Prephase","None Indicated")))))) -> None Indicated | AD73: =IF(SUM(W73:AC73)=7,"RA7",IF(SUM(W73:AC73)=6,"RA 6",IF(SUM(W73:AC73)=5,"RA 5",IF(SUM(W73:AC73)=4,"RA 4",IF(SUM(W73:AC73)=3,"RA3",IF(SUM(W73:AC73)=2,"RA 2",IF(SUM(W73:AC73)=1,"RA1","None Indicated"))))))) -> None Indicated
K74: =DAY(N74) -> 0 | L74: =MONTH(N74) -> 1 | M74: =YEAR(N74) -> 1900 | O74: =IF((I74="")=TRUE(),IF((N74="")=TRUE(),"No CLUP",IF(YEAR(NOW())-YEAR(N74)<=10,"Updated","For Updating")),IF(YEAR(NOW())-I74<=0,"Updated","For Updating")) -> No CLUP | V74: =IF(SUM(P74:U74)=6,"Phase 5",IF(SUM(P74:U74)=5,"Phase 4",IF(SUM(P74:U74)=4,"Phase 3",IF(SUM(P74:U74)=3,"Phase 2",IF(SUM(P74:U74)=2,"Phase 1",IF(SUM(P74:U74)=1,"Prephase","None Indicated")))))) -> None Indicated | AD74: =IF(SUM(W74:AC74)=7,"RA7",IF(SUM(W74:AC74)=6,"RA 6",IF(SUM(W74:AC74)=5,"RA 5",IF(SUM(W74:AC74)=4,"RA 4",IF(SUM(W74:AC74)=3,"RA3",IF(SUM(W74:AC74)=2,"RA 2",IF(SUM(W74:AC74)=1,"RA1","None Indicated"))))))) -> None Indicated
K75: =DAY(N75) -> 0 | L75: =MONTH(N75) -> 1 | M75: =YEAR(N75) -> 1900 | O75: =IF((I75="")=TRUE(),IF((N75="")=TRUE(),"No CLUP",IF(YEAR(NOW())-YEAR(N75)<=10,"Updated","For Updating")),IF(YEAR(NOW())-I75<=0,"Updated","For Updating")) -> No CLUP | V75: =IF(SUM(P75:U75)=6,"Phase 5",IF(SUM(P75:U75)=5,"Phase 4",IF(SUM(P75:U75)=4,"Phase 3",IF(SUM(P75:U75)=3,"Phase 2",IF(SUM(P75:U75)=2,"Phase 1",IF(SUM(P75:U75)=1,"Prephase","None Indicated")))))) -> None Indicated | AD75: =IF(SUM(W75:AC75)=7,"RA7",IF(SUM(W75:AC75)=6,"RA 6",IF(SUM(W75:AC75)=5,"RA 5",IF(SUM(W75:AC75)=4,"RA 4",IF(SUM(W75:AC75)=3,"RA3",IF(SUM(W75:AC75)=2,"RA 2",IF(SUM(W75:AC75)=1,"RA1","None Indicated"))))))) -> None Indicated
K76: =DAY(N76) -> 0 | L76: =MONTH(N76) -> 1 | M76: =YEAR(N76) -> 1900 | O76: =IF((I76="")=TRUE(),IF((N76="")=TRUE(),"No CLUP",IF(YEAR(NOW())-YEAR(N76)<=10,"Updated","For Updating")),IF(YEAR(NOW())-I76<=0,"Updated","For Updating")) -> No CLUP | V76: =IF(SUM(P76:U76)=6,"Phase 5",IF(SUM(P76:U76)=5,"Phase 4",IF(SUM(P76:U76)=4,"Phase 3",IF(SUM(P76:U76)=3,"Phase 2",IF(SUM(P76:U76)=2,"Phase 1",IF(SUM(P76:U76)=1,"Prephase","None Indicated")))))) -> None Indicated | AD76: =IF(SUM(W76:AC76)=7,"RA7",IF(SUM(W76:AC76)=6,"RA 6",IF(SUM(W76:AC76)=5,"RA 5",IF(SUM(W76:AC76)=4,"RA 4",IF(SUM(W76:AC76)=3,"RA3",IF(SUM(W76:AC76)=2,"RA 2",IF(SUM(W76:AC76)=1,"RA1","None Indicated"))))))) -> None Indicated
K77: =DAY(N77) -> 0 | L77: =MONTH(N77) -> 1 | M77: =YEAR(N77) -> 1900 | O77: =IF((I77="")=TRUE(),IF((N77="")=TRUE(),"No CLUP",IF(YEAR(NOW())-YEAR(N77)<=10,"Updated","For Updating")),IF(YEAR(NOW())-I77<=0,"Updated","For Updating")) -> No CLUP | V77: =IF(SUM(P77:U77)=6,"Phase 5",IF(SUM(P77:U77)=5,"Phase 4",IF(SUM(P77:U77)=4,"Phase 3",IF(SUM(P77:U77)=3,"Phase 2",IF(SUM(P77:U77)=2,"Phase 1",IF(SUM(P77:U77)=1,"Prephase","None Indicated")))))) -> None Indicated | AD77: =IF(SUM(W77:AC77)=7,"RA7",IF(SUM(W77:AC77)=6,"RA 6",IF(SUM(W77:AC77)=5,"RA 5",IF(SUM(W77:AC77)=4,"RA 4",IF(SUM(W77:AC77)=3,"RA3",IF(SUM(W77:AC77)=2,"RA 2",IF(SUM(W77:AC77)=1,"RA1","None Indicated"))))))) -> None Indicated
K78: =DAY(N78) -> 0 | L78: =MONTH(N78) -> 1 | M78: =YEAR(N78) -> 1900 | O78: =IF((I78="")=TRUE(),IF((N78="")=TRUE(),"No CLUP",IF(YEAR(NOW())-YEAR(N78)<=10,"Updated","For Updating")),IF(YEAR(NOW())-I78<=0,"Updated","For Updating")) -> No CLUP | V78: =IF(SUM(P78:U78)=6,"Phase 5",IF(SUM(P78:U78)=5,"Phase 4",IF(SUM(P78:U78)=4,"Phase 3",IF(SUM(P78:U78)=3,"Phase 2",IF(SUM(P78:U78)=2,"Phase 1",IF(SUM(P78:U78)=1,"Prephase","None Indicated")))))) -> None Indicated | AD78: =IF(SUM(W78:AC78)=7,"RA7",IF(SUM(W78:AC78)=6,"RA 6",IF(SUM(W78:AC78)=5,"RA 5",IF(SUM(W78:AC78)=4,"RA 4",IF(SUM(W78:AC78)=3,"RA3",IF(SUM(W78:AC78)=2,"RA 2",IF(SUM(W78:AC78)=1,"RA1","None Indicated"))))))) -> None Indicated
K79: =DAY(N79) -> 0 | L79: =MONTH(N79) -> 1 | M79: =YEAR(N79) -> 1900 | O79: =IF((I79="")=TRUE(),IF((N79="")=TRUE(),"No CLUP",IF(YEAR(NOW())-YEAR(N79)<=10,"Updated","For Updating")),IF(YEAR(NOW())-I79<=0,"Updated","For Updating")) -> No CLUP | V79: =IF(SUM(P79:U79)=6,"Phase 5",IF(SUM(P79:U79)=5,"Phase 4",IF(SUM(P79:U79)=4,"Phase 3",IF(SUM(P79:U79)=3,"Phase 2",IF(SUM(P79:U79)=2,"Phase 1",IF(SUM(P79:U79)=1,"Prephase","None Indicated")))))) -> None Indicated | AD79: =IF(SUM(W79:AC79)=7,"RA7",IF(SUM(W79:AC79)=6,"RA 6",IF(SUM(W79:AC79)=5,"RA 5",IF(SUM(W79:AC79)=4,"RA 4",IF(SUM(W79:AC79)=3,"RA3",IF(SUM(W79:AC79)=2,"RA 2",IF(SUM(W79:AC79)=1,"RA1","None Indicated"))))))) -> None Indicated
K80: =DAY(N80) -> 0 | L80: =MONTH(N80) -> 1 | M80: =YEAR(N80) -> 1900 | O80: =IF((I80="")=TRUE(),IF((N80="")=TRUE(),"No CLUP",IF(YEAR(NOW())-YEAR(N80)<=10,"Updated","For Updating")),IF(YEAR(NOW())-I80<=0,"Updated","For Updating")) -> No CLUP | V80: =IF(SUM(P80:U80)=6,"Phase 5",IF(SUM(P80:U80)=5,"Phase 4",IF(SUM(P80:U80)=4,"Phase 3",IF(SUM(P80:U80)=3,"Phase 2",IF(SUM(P80:U80)=2,"Phase 1",IF(SUM(P80:U80)=1,"Prephase","None Indicated")))))) -> None Indicated | AD80: =IF(SUM(W80:AC80)=7,"RA7",IF(SUM(W80:AC80)=6,"RA 6",IF(SUM(W80:AC80)=5,"RA 5",IF(SUM(W80:AC80)=4,"RA 4",IF(SUM(W80:AC80)=3,"RA3",IF(SUM(W80:AC80)=2,"RA 2",IF(SUM(W80:AC80)=1,"RA1","None Indicated"))))))) -> None Indicated
K81: =DAY(N81) -> 0 | L81: =MONTH(N81) -> 1 | M81: =YEAR(N81) -> 1900 | O81: =IF((I81="")=TRUE(),IF((N81="")=TRUE(),"No CLUP",IF(YEAR(NOW())-YEAR(N81)<=10,"Updated","For Updating")),IF(YEAR(NOW())-I81<=0,"Updated","For Updating")) -> No CLUP | V81: =IF(SUM(P81:U81)=6,"Phase 5",IF(SUM(P81:U81)=5,"Phase 4",IF(SUM(P81:U81)=4,"Phase 3",IF(SUM(P81:U81)=3,"Phase 2",IF(SUM(P81:U81)=2,"Phase 1",IF(SUM(P81:U81)=1,"Prephase","None Indicated")))))) -> None Indicated | AD81: =IF(SUM(W81:AC81)=7,"RA7",IF(SUM(W81:AC81)=6,"RA 6",IF(SUM(W81:AC81)=5,"RA 5",IF(SUM(W81:AC81)=4,"RA 4",IF(SUM(W81:AC81)=3,"RA3",IF(SUM(W81:AC81)=2,"RA 2",IF(SUM(W81:AC81)=1,"RA1","None Indicated"))))))) -> None Indicated
K82: =DAY(N82) -> 0 | L82: =MONTH(N82) -> 1 | M82: =YEAR(N82) -> 1900 | O82: =IF((I82="")=TRUE(),IF((N82="")=TRUE(),"No CLUP",IF(YEAR(NOW())-YEAR(N82)<=10,"Updated","For Updating")),IF(YEAR(NOW())-I82<=0,"Updated","For Updating")) -> No CLUP | V82: =IF(SUM(P82:U82)=6,"Phase 5",IF(SUM(P82:U82)=5,"Phase 4",IF(SUM(P82:U82)=4,"Phase 3",IF(SUM(P82:U82)=3,"Phase 2",IF(SUM(P82:U82)=2,"Phase 1",IF(SUM(P82:U82)=1,"Prephase","None Indicated")))))) -> None Indicated | AD82: =IF(SUM(W82:AC82)=7,"RA7",IF(SUM(W82:AC82)=6,"RA 6",IF(SUM(W82:AC82)=5,"RA 5",IF(SUM(W82:AC82)=4,"RA 4",IF(SUM(W82:AC82)=3,"RA3",IF(SUM(W82:AC82)=2,"RA 2",IF(SUM(W82:AC82)=1,"RA1","None Indicated"))))))) -> None Indicated
... K84: =DAY(N84) -> 0 | L84: =MONTH(N84) -> 1 | M84: =YEAR(N84) -> 1900 | O84: =IF((I84="")=TRUE(),IF((N84="")=TRUE(),"No CLUP",IF(YEAR(NOW())-YEAR(N84)<=10,"Updated","For Updating")),IF(YEAR(NOW())-I84<=0,"Updated","For Updating")) -> No CLUP | V84: =IF(SUM(P84:U84)=6,"Phase 5",IF(SUM(P84:U84)=5,"Phase 4",IF(SUM(P84:U84)=4,"Phase 3",IF(SUM(P84:U84)=3,"Phase 2",IF(SUM(P84:U84)=2,"Phase 1",IF(SUM(P84:U84)=1,"Prephase","None Indicated")))))) -> None Indicated | AD84: =IF(SUM(W84:AC84)=7,"RA7",IF(SUM(W84:AC84)=6,"RA 6",IF(SUM(W84:AC84)=5,"RA 5",IF(SUM(W84:AC84)=4,"RA 4",IF(SUM(W84:AC84)=3,"RA3",IF(SUM(W84:AC84)=2,"RA 2",IF(SUM(W84:AC84)=1,"RA1","None Indicated"))))))) -> None Indicated

Sheet PSGC
A1: 10-digit PSGC | B1: Region | C1: Province | D1: City/Municipality | E1: Correspondence Code | F1: Geographic Level | G1: Old names | H1: City Class | I1: Income Classification
A2: 1380100000 | B2: NCR | C2: Metro Manila | D2: City of Caloocan | E2: 137501000 | F2: City | H2: HUC | I2: 1st
A3: 1380200000 | B3: NCR | C3: Metro Manila | D3: City of Las Piñas | E3: 137601000 | F3: City | H3: HUC | I3: 1st
A4: 1380300000 | B4: NCR | C4: Metro Manila | D4: City of Makati | E4: 137602000 | F4: City | H4: HUC | I4: 1st
A5: 1380400000 | B5: NCR | C5: Metro Manila | D5: City of Malabon | E5: 137502000 | F5: City | H5: HUC | I5: 1st
A6: 1380500000 | B6: NCR | C6: Metro Manila | D6: City of Mandaluyong | E6: 137401000 | F6: City | H6: HUC | I6: 1st
A7: 1380600000 | B7: NCR | C7: Metro Manila | D7: City of Manila | E7: 133900000 | F7: City | H7: HUC | I7: Special
A8: 1380700000 | B8: NCR | C8: Metro Manila | D8: City of Marikina | E8: 137402000 | F8: City | H8: HUC | I8: 1st
A9: 1380800000 | B9: NCR | C9: Metro Manila | D9: City of Muntinlupa | E9: 137603000 | F9: City | H9: HUC | I9: 1st
A10: 1380900000 | B10: NCR | C10: Metro Manila | D10: City of Navotas | E10: 137503000 | F10: City | H10: HUC | I10: 2nd
A11: 1381000000 | B11: NCR | C11: Metro Manila | D11: City of Parañaque | E11: 137604000 | F11: City | H11: HUC | I11: 1st
A12: 1381100000 | B12: NCR | C12: Metro Manila | D12: Pasay City | E12: 137605000 | F12: City | H12: HUC | I12: 1st
A13: 1381200000 | B13: NCR | C13: Metro Manila | D13: City of Pasig | E13: 137403000 | F13: City | H13: HUC | I13: 1st
A14: 1381300000 | B14: NCR | C14: Metro Manila | D14: Quezon City | E14: 137404000 | F14: City | H14: HUC | I14: Special
... A17: 1381600000 | B17: NCR | C17: Metro Manila | D17: City of Valenzuela | E17: 137504000 | F17: City | H17: HUC | I17: 1st
A18: 1381701000 | B18: NCR | C18: Metro Manila | D18: Pateros | E18: 137606000 | F18: Mun | I18: 1st
A19: 1400101000 | B19: CAR | C19: Abra | D19: Bangued | E19: 140101000 | F19: Mun | I19: 1st
A20: 1400102000 | B20: CAR | C20: Abra | D20: Boliney | E20: 140102000 | F20: Mun | I20: 5th
A21: 1400103000 | B21: CAR | C21: Abra | D21: Bucay | E21: 140103000 | F21: Mun | I21: 5th
A22: 1400104000 | B22: CAR | C22: Abra | D22: Bucloc | E22: 140104000 | F22: Mun | I22: 6th
A23: 1400105000 | B23: CAR | C23: Abra | D23: Daguioman | E23: 140105000 | F23: Mun | I23: 5th
A24: 1400106000 | B24: CAR | C24: Abra | D24: Danglas | E24: 140106000 | F24: Mun | I24: 5th
A25: 1400107000 | B25: CAR | C25: Abra | D25: Dolores | E25: 140107000 | F25: Mun | I25: 5th
A26: 1400108000 | B26: CAR | C26: Abra | D26: La Paz | E26: 140108000 | F26: Mun | I26: 5th
A27: 1400109000 | B27: CAR | C27: Abra | D27: Lacub | E27: 140109000 | F27: Mun | I27: 5th
A28: 1400110000 | B28: CAR | C28: Abra | D28: Lagangilang | E28: 140110000 | F28: Mun | I28: 5th
A29: 1400111000 | B29: CAR | C29: Abra | D29: Lagayan | E29: 140111000 | F29: Mun | I29: 5th
A30: 1400112000 | B30: CAR | C30: Abra | D30: Langiden | E30: 140112000 | F30: Mun | I30: 5th
A31: 1400113000 | B31: CAR | C31: Abra | D31: Licuan-Baay | E31: 140113000 | F31: Mun | G31: Licuan | I31: 5th
A32: 1400114000 | B32: CAR | C32: Abra | D32: Luba | E32: 140114000 | F32: Mun | I32: 5th
A33: 1400115000 | B33: CAR | C33: Abra | D33: Malibcong | E33: 140115000 | F33: Mun | I33: 5th
A34: 1400116000 | B34: CAR | C34: Abra | D34: Manabo | E34: 140116000 | F34: Mun | I34: 5th
A35: 1400117000 | B35: CAR | C35: Abra | D35: Peñarrubia | E35: 140117000 | F35: Mun | I35: 6th
A36: 1400118000 | B36: CAR | C36: Abra | D36: Pidigan | E36: 140118000 | F36: Mun | I36: 5th
A37: 1400119000 | B37: CAR | C37: Abra | D37: Pilar | E37: 140119000 | F37: Mun | I37: 5th
A38: 1400120000 | B38: CAR | C38: Abra | D38: Sallapadan | E38: 140120000 | F38: Mun | I38: 5th
A39: 1400121000 | B39: CAR | C39: Abra | D39: San Isidro | E39: 140121000 | F39: Mun | I39: 5th
